Workbook

Sheet SAP-Auszug
A1: Bilanz/GuV-Position | B1: Text Bilanz/GuV-Position | C1: Summe der Berichtsperiode | D1: Summe der Vergleichsperiode | E1: Absolute Abweichung | F1: Relative Abweichung
C2: Jahr 2025 | D2: Jahr 2024
A3: 1000000 | B3: A k t i v a | C3: 0 | D3: 0 | E3: 0
A4: 1000000 | B4: =========== | C4: 0 | D4: 0 | E4: 0
A5: 1030000 | B5: A. Anlagevermögen | C5: 0 | D5: 0 | E5: 0
A6: 1030000 | B6: ================= | C6: 0 | D6: 0 | E6: 0
A7: 1031000 | B7: I. Immaterielle Vermögensgegenstände | C7: 0 | D7: 0 | E7: 0
A8: 1031000 | B8: =================================== | C8: 0 | D8: 0 | E8: 0
A9: 1031010 | B9: 1. Entgeltlich erworbene Konzessionen, | C9: 0 | D9: 0 | E9: 0
A10: 1031010 | B10: gewerbliche Schutzrechte und ähnliche | C10: 0 | D10: 0 | E10: 0
A11: 1031010 | B11: Rechte und Werte sowie Lizenzen an | C11: 0 | D11: 0 | E11: 0
A12: 1031010 | B12: solchen Rechten und Werten | C12: 0 | D12: 0 | E12: 0
A13: 1031011 | B13: Software und sonstige immaterielle WG | C13: 0 | D13: 0 | E13: 0
A14: 1031011 | B14: ========================================= | C14: 0 | D14: 0 | E14: 0
A15: 1031011 | B15: 050000 Software und sonstige immat. Wirtschaftsgüter | C15: 23331784 | D15: 24007275 | E15: -675491 | F15: 2,8-
A16: 1031011 | B16: Summe Software und sonstige immaterielle WG | C16: 23331784 | D16: 24007275 | E16: -675491 | F16: 2,8-
A17: 1031030 | B17: 2. Geleistete Anzahlungen | C17: 0 | D17: 0 | E17: 0
A18: 1031030 | B18: ===================== | C18: 0 | D18: 0 | E18: 0
A19: 1031031 | B19: 050090 Software Anzahlungen | C19: 61500.77 | D19: 90926.55 | E19: -29425.78 | F19: 32,4-
A20: 1031030 | C20: 61500.77 | D20: 90926.55 | E20: -29425.78 | F20: 32,4-
A21: 1031000 | B21: Summe Immaterielle Vermögensgegenstände | C21: 23393285 | D21: 24098201 | E21: -704916.78 | F21: 2,9-
A22: 1031000 | B22: ======================================= | C22: 0 | D22: 0 | E22: 0
A23: 1032000 | B23: II. Sachanlagen | C23: 0 | D23: 0 | E23: 0
A24: 1032000 | B24: ============ | C24: 0 | D24: 0 | E24: 0
A25: 1032010 | B25: 1. Grundstücke, grundstücksgleiche Rechte und | C25: 0 | D25: 0 | E25: 0
A26: 1032010 | B26: Bauten einschließlich der Bauten auf | C26: 0 | D26: 0 | E26: 0
A27: 1032010 | B27: fremden Grundstücken | C27: 0 | D27: 0 | E27: 0
A28: 1032010 | B28: ====================================== | C28: 0 | D28: 0 | E28: 0
A29: 1032011 | B29: Flughafenbauten (inkl. Grundstücke) | C29: 0 | D29: 0 | E29: 0
A30: 1032011 | B30: 010000 Bauten auf eig.Grundstücken +grundstücksgl.Rechten | C30: 4.6661927e+08 | D30: 4.935888e+08 | E30: -26969527 | F30: 5,5-
A31: 1032011 | C31: 4.6661927e+08 | D31: 4.935888e+08 | E31: -26969527 | F31: 5,5-
A32: 1032012 | B32: Grundstücke mit Wohnbauten | C32: 0 | D32: 0 | E32: 0
A33: 1032012 | B33: 011000 Bebaute Wohngrundstücke (Flank. Massnahmen) | C33: 15893830 | D33: 16219074 | E33: -325244.54 | F33: 2,0-
A34: 1032012 | C34: 15893830 | D34: 16219074 | E34: -325244.54 | F34: 2,0-
A35: 1032013 | B35: Grundstücke ohne Bauten | C35: 0 | D35: 0 | E35: 0
A36: 1032013 | B36: 012000 Grundstücke | C36: 10069325 | D36: 10069325 | E36: 0 | F36: 0,0
A37: 1032013 | C37: 10069325 | D37: 10069325 | E37: 0 | F37: 0,0
A38: 1032014 | B38: Erbbaurechte | C38: 0 | D38: 0 | E38: 0
A39: 1032014 | B39: 013000 Grundstücksgleiche Rechte ohne Bauten | C39: 45422597 | D39: 47633457 | E39: -2210860 | F39: 4,6-
A40: 1032014 | C40: 45422597 | D40: 47633457 | E40: -2210860 | F40: 4,6-
A41: 1032010 | B41: Summe Grundstücke, grundstücksgleiche Rechte | C41: 5.3800502e+08 | D41: 5.6751065e+08 | E41: -29505632 | F41: 5,2-
A42: 1032010 | B42: und Bauten einschließlich der Bauten auf | C42: 0 | D42: 0 | E42: 0
A43: 1032010 | B43: fremden Grundstücken | C43: 0 | D43: 0 | E43: 0
A44: 1032020 | B44: 2. Technische Anlagen und Maschinen | C44: 0 | D44: 0 | E44: 0
A45: 1032020 | B45: =============================== | C45: 0 | D45: 0 | E45: 0
A46: 1032021 | B46: Flughafenanlagen | C46: 0 | D46: 0 | E46: 0
A47: 1032021 | B47: 020000 Außenanlagen / Flughafenanlagen | C47: 162147137 | D47: 152926183 | E47: 9220954 | F47: 6,0
A48: 1032021 | C48: 162147137 | D48: 152926183 | E48: 9220954 | F48: 6,0
A49: 1032022 | B49: Betriebsanlagen | C49: 0 | D49: 0 | E49: 0
A50: 1032022 | B50: 030000 Betriebsanlagen | C50: 1.2904117e+08 | D50: 1.328927e+08 | E50: -3851526 | F50: 2,9-
A51: 1032022 | C51: 1.2904117e+08 | D51: 1.328927e+08 | E51: -3851526 | F51: 2,9-
A52: 1032020 | B52: Summe Technische Anlagen und Maschinen | C52: 2.9118831e+08 | D52: 2.8581888e+08 | E52: 5369428 | F52: 1,9
A53: 1032030 | B53: 3. Andere Anlagen, Betriebs- und | C53: 0 | D53: 0 | E53: 0
A54: 1032030 | B54: Geschäftsausstattung | C54: 0 | D54: 0 | E54: 0
A55: 1032030 | B55: ========================== | C55: 0 | D55: 0 | E55: 0
A56: 1032031 | B56: 040000 Betriebs- und Geschäftsausstattung | C56: 29725982 | D56: 29227160 | E56: 498822 | F56: 1,7
A57: 1032031 | B57: SUMME ANDERE ANLAGEN SOWIE BETRIEBS- UND | C57: 29725982 | D57: 29227160 | E57: 498822 | F57: 1,7
A58: 1032031 | B58: GESCHAEFTSAUSSTATTUNG | C58: 0 | D58: 0 | E58: 0
A59: 1032030 | C59: 29725982 | D59: 29227160 | E59: 498822 | F59: 1,7
A60: 1032040 | B60: 4. Geleistete Anzahlungen und Anlagen im Bau | C60: 0 | D60: 0 | E60: 0
A61: 1032040 | B61: ===================================== | C61: 0 | D61: 0 | E61: 0
A62: 1032041 | B62: 058009 Im Bau befindliche Anlagen + gel. Anzahlungen | C62: 1.0669265e+08 | D62: 71983416 | E62: 34709235 | F62: 48,2
A63: 1032041 | B63: SUMME GELEISTETE ANZAHLUNGEN UND ANLAGEN | C63: 1.0669265e+08 | D63: 71983416 | E63: 34709235 | F63: 48,2
A64: 1032041 | B64: IM BAU | C64: 0 | D64: 0 | E64: 0
A65: 1032040 | C65: 1.0669265e+08 | D65: 71983416 | E65: 34709235 | F65: 48,2
A66: 1032000 | B66: Summe Sachanlagen | C66: 9.6561197e+08 | D66: 9.5454011e+08 | E66: 11071854 | F66: 1,2
A67: 1032000 | B67: ================= | C67: 0 | D67: 0 | E67: 0
A68: 1033000 | B68: Finanzanlagen | C68: 0 | D68: 0 | E68: 0
A69: 1033000 | B69: ============ | C69: 0 | D69: 0 | E69: 0
A70: 1033010 | B70: Anteile an verbundenen Unternehmen | C70: 0 | D70: 0 | E70: 0
A71: 1033010 | B71: ============================== | C71: 0 | D71: 0 | E71: 0
A72: 1033010 | B72: 065015 Beteiligung FD Immobilien GmbH | C72: 9453546 | D72: 9453546 | E72: 0 | F72: 0,0
A73: 1033010 | B73: 065016 Beteiligung FD Ground Handling GmbH | C73: 1 | D73: 1 | E73: 0 | F73: 0,0
A74: 1033010 | B74: 065019 Beteiligung Flughafen Düsseldorf Security GmbH | C74: 30000 | D74: 30000 | E74: 0 | F74: 0,0
A75: 1033010 | B75: 065022 Beteiligung FD Energie GmbH | C75: 25000 | D75: 25000 | E75: 0 | F75: 0,0
A76: 1033010 | B76: Summe Anteile an verbundenen Unternehmen | C76: 9508547 | D76: 9508547 | E76: 0 | F76: 0,0
A77: 1033030 | B77: Beteiligungen | C77: 0 | D77: 0 | E77: 0
A78: 1033030/00 | B78: 065018 Beteiligung SITA Airport IT GmbH | C78: 147784.75 | D78: 147784.75 | E78: 0 | F78: 0,0
A79: 1033030/00 | B79: 065025 Beteiligung Flughafengesell. Mönchengladbach GmbH | C79: 1 | D79: 1 | E79: 0 | F79: 0,0
A80: 1033030/00 | B80: 067000 Beteiligung Swissport DUS Cargo Sevices GmbH | C80: 2221952 | D80: 2221952 | E80: 0 | F80: 0,0
A81: 1033030/00 | C81: 2369737.7 | D81: 2369737.7 | E81: 0 | F81: 0,0
A82: 1033030 | B82: Summe Beteiligungen | C82: 2369737.7 | D82: 2369737.7 | E82: 0 | F82: 0,0
A83: 1033030 | B83: ------------------- | C83: 0 | D83: 0 | E83: 0
A84: 1033040 | B84: Ausleihungen an Unternehmen, mit denen ein | C84: 0 | D84: 0 | E84: 0
A85: 1033040 | B85: Beteiligungsverhältnis besteht | C85: 0 | D85: 0 | E85: 0
A86: 1033040 | B86: ===================================== | C86: 0 | D86: 0 | E86: 0
A87: 1033042 | B87: Mit einer Rstlaufzeit über einem Jahr | C87: 0 | D87: 0 | E87: 0
A88: 1033042 | B88: ----------------------------------------- | C88: 0 | D88: 0 | E88: 0
A89: 1033042 | B89: 066002 Darlehen Flughafen Düsseldorf Cargo GmbH | C89: 251000 | D89: 878500 | E89: -627500 | F89: 71,4-
A90: 1033042 | C90: 251000 | D90: 878500 | E90: -627500 | F90: 71,4-
A91: 1033040 | B91: Summe Ausleihungen an Unternehmen, mit denen | C91: 251000 | D91: 878500 | E91: -627500 | F91: 71,4-
A92: 1033040 | B92: ein Beteiligungsverhältnis besteht | C92: 0 | D92: 0 | E92: 0
A93: 1033060 | B93: Sonstige Ausleihungen | C93: 0 | D93: 0 | E93: 0
A94: 1033060 | B94: =================== | C94: 0 | D94: 0 | E94: 0
A95: 1033062 | B95: 064009 Arbeitgeberdarlehen - Hauptbuchkonto | C95: 2191.24 | D95: 3960.83 | E95: -1769.59 | F95: 44,7-
A96: 1033062 | C96: 2191.24 | D96: 3960.83 | E96: -1769.59 | F96: 44,7-
A97: 1033060 | B97: Summe Sonstige Ausleihungen | C97: 2191.24 | D97: 3960.83 | E97: -1769.59 | F97: 44,7-
A98: 1033000 | B98: Summe Finanzanlagen | C98: 12131476 | D98: 12760746 | E98: -629269.59 | F98: 4,9-
A99: 1033000 | B99: =================== | C99: 0 | D99: 0 | E99: 0
A100: 1030000 | B100: Summe Anlagevermögen | C100: 1.0011367e+09 | D100: 9.9139906e+08 | E100: 9737667.3 | F100: 1,0
...

Sheet Bilanz
A1: Bilanz zum 31. Dezember 2025
N3: =TODAY() -> 46297
A5: Flughafen Düsseldorf GmbH, Düsseldorf
B9: A K T I V A | F9: 46022 | H9: 45657 | J9: P A S S I V A | N9: 46022 | P9: 45657
F11: EUR | G11: EUR | H11: EUR | N11: EUR | O11: EUR | P11: EUR
B14: A. | C14: ANLAGEVERMÖGEN | J14: A. | K14: EIGENKAPITAL
C16: I. | D16: Immaterielle Vermögensgegenstände | K16: I. | L16: Gezeichnetes Kapital | N16: =+'SAP-Auszug'!C294*-1 -> 25600000 | P16: ='SAP-Auszug'!D294*-1 -> 25600000
K17: II. | L17: Kapitalrücklage | N17: =+'SAP-Auszug'!C298*-1 -> 80582203 | P17: =+'SAP-Auszug'!D298*-1 -> 80582203
D18: 1. | E18: Entgeltlich erworbene Konzessionen, gewerbliche Schutzrechte | K18: III. | L18: Gewinnrücklagen (andere Gewinnrücklagen) | N18: =+'SAP-Auszug'!C304*-1 -> 1230210.1 | P18: =+'SAP-Auszug'!D304*-1 -> 1230210.1
E19: und ähnliche Rechte und Werte sowie Lizenzen an solchen Rechten | K19: IV. | L19: Verlustvortrag | N19: ='SAP-Auszug'!C309*-1 -> -1.4892217e+08 | P19: ='SAP-Auszug'!D309*-1 -> -1.6250925e+08
E20: und Werten | F20: =+'SAP-Auszug'!C16 -> 23331784 | H20: =+'SAP-Auszug'!D16 -> 24007275 | K20: V. | L20: Jahresüberschuss | N20: ='SAP-Auszug'!C1031*-1 -> 20246589 | P20: ='SAP-Auszug'!D1031*-1 -> 13587076
D21: 2. | E21: Geleistete Anzahlungen | F21: =+'SAP-Auszug'!C20 -> 61500.77 | H21: =+'SAP-Auszug'!D20 -> 90926.55 | K21: VI. | L21: Nicht durch Eigenkapital gedeckter Fehlbetrag | N21: ='SAP-Auszug'!C320*-1 -> 21263169 | P21: ='SAP-Auszug'!D320*-1 -> 41509758
G22: =F20+F21 -> 23393285 | H22: =H20+H21 -> 24098201 | O22: =SUM(N16:N21) -> 0 | P22: =SUM(P16:P21) -> 0
J24: B. | K24: SONDERPOSTEN FÜR INVESTITIONSZUSCHÜSSE
K25: ZU SACHANLAGEN | O25: ='SAP-Auszug'!C328*-1 -> 23175339 | P25: ='SAP-Auszug'!D328*-1 -> 25680683
C26: II. | D26: Sachanlagen
D28: 1. | E28: Grundstücke, grundstücksgleiche Rechte und Bauten | J28: C. | K28: SONDERPOSTEN MIT RÜCKLAGEANTEIL | O28: ='SAP-Auszug'!C335*-1 -> 33330800 | P28: ='SAP-Auszug'!D335*-1 -> 35405877
E29: einschließlich der Bauten auf fremden Grundstücken
E30: a) Flughafenbauten inkl. Grundstücke | F30: =+'SAP-Auszug'!C31 -> 4.6661927e+08 | H30: =+'SAP-Auszug'!D31 -> 4.935888e+08
E31: b) Grundstücke mit Wohnbauten | F31: =+'SAP-Auszug'!C34 -> 15893830 | H31: =+'SAP-Auszug'!D34 -> 16219074
E32: c) Grundstücke ohne Bauten | F32: =+'SAP-Auszug'!C37 -> 10069325 | H32: =+'SAP-Auszug'!D37 -> 10069325 | J32: D. | K32: RÜCKSTELLUNGEN
E33: d) Erbbaurechte | F33: =+'SAP-Auszug'!C40 -> 45422597 | H33: =+'SAP-Auszug'!D40 -> 47633457
D34: 2. | E34: Technische Anlagen und Maschinen | K34: 1. | L34: Rückstellungen für Pensionen und ähnliche Verpflichtungen | N34: ='SAP-Auszug'!C344*-1 -> 6926768 | P34: ='SAP-Auszug'!D344*-1 -> 7642053
E35: a) Flughafenanlagen | F35: =+'SAP-Auszug'!C48 -> 162147137 | H35: =+'SAP-Auszug'!D48 -> 152926183 | K35: 2. | L35: Steuerrückstellungen | N35: ='SAP-Auszug'!C349*-1 -> 382170.67 | P35: ='SAP-Auszug'!D349*-1 -> 217165.84
E36: b) Betriebsanlagen | F36: =+'SAP-Auszug'!C51 -> 1.2904117e+08 | H36: =+'SAP-Auszug'!D51 -> 1.328927e+08 | K36: 3. | L36: Sonstige Rückstellungen | N36: ='SAP-Auszug'!C376*-1 -> 53497136 | P36: ='SAP-Auszug'!D376*-1 -> 46057309
D37: 3. | E37: Andere Anlagen, Betriebs- und Geschäftsausstattung | F37: =+'SAP-Auszug'!C59 -> 29725982 | H37: =+'SAP-Auszug'!D59 -> 29227160 | O37: =SUM(N34:N36) -> 60806075 | P37: =SUM(P34:P36) -> 53916527
D38: 4. | E38: Geleistete Anzahlungen und Anlagen im Bau | F38: =+'SAP-Auszug'!C65 -> 1.0669265e+08 | H38: =+'SAP-Auszug'!D65 -> 71983416
G39: =SUM(F30:F38) -> 9.6561197e+08 | H39: =SUM(H30:H38) -> 9.5454011e+08
J40: E. | K40: VERBINDLICHKEITEN
C42: III. | D42: Finanzanlagen | K42: 1. | L42: Verbindlichkeiten gegenüber Kreditinstituten | N42: ='SAP-Auszug'!C404*-1 -> 6.3271334e+08 | P42: ='SAP-Auszug'!D404*-1 -> 7.3868932e+08
K43: 2. | L43: Verbindlichkeiten gegenüber weiteren Darlehensgebern | N43: ='SAP-Auszug'!C412*-1 -> 1.9148117e+08 | P43: ='SAP-Auszug'!D412*-1 -> 123000000
D44: 1. | E44: Anteile an verbundenen Unternehmen | F44: =+'SAP-Auszug'!C76 -> 9508547 | H44: =+'SAP-Auszug'!D76 -> 9508547 | K44: 3. | L44: Verbindlichkeiten aus Lieferungen und Leistungen | N44: ='SAP-Auszug'!C424*-1 -> 9933099 | P44: ='SAP-Auszug'!D424*-1 -> 9374437.6
D45: 2. | E45: Beteiligungen | F45: =+'SAP-Auszug'!C82 -> 2369737.7 | H45: =+'SAP-Auszug'!D82 -> 2369737.7 | K45: 4. | L45: Verbindlichkeiten gegenüber Gesellschaftern | N45: ='SAP-Auszug'!C434*-1 -> 1.3052078e+08 | P45: ='SAP-Auszug'!D434*-1 -> 1.2336988e+08
D46: 3. | E46: Ausleihungen an Unternehmen mit denen ein Beteiligungsverhältnis | K46: 5. | L46: Verbindlichkeiten gegenüber verbundenen Unternehmen | N46: ='SAP-Auszug'!C447*-1 -> 4483686.6 | P46: ='SAP-Auszug'!D447*-1 -> 2681406.4
E47: besteht | F47: =+'SAP-Auszug'!C91 -> 251000 | H47: =+'SAP-Auszug'!D91 -> 878500 | K47: 6. | L47: Verbindlichkeiten gegenüber Unternehmen,
D48: 4. | E48: Sonstige Ausleihungen | F48: =+'SAP-Auszug'!C97 -> 2191.24 | H48: =+'SAP-Auszug'!D97 -> 3960.83 | L48: mit denen ein Beteiligungsverhältnis besteht | N48: ='SAP-Auszug'!C456*-1 -> 1627465.7 | P48: ='SAP-Auszug'!D456*-1 -> 2591912.1
G49: =SUM(F44:F48) -> 12131476 | H49: =SUM(H44:H48) -> 12760746 | K49: 7. | L49: Sonstige Verbindlichkeiten | N49: ='SAP-Auszug'!C505*-1 -> 23022959 | P49: ='SAP-Auszug'!D505*-1 -> 19607182
O50: =SUM(N42:N49) -> 9.937825e+08 | P50: =SUM(P42:P49) -> 1.0193141e+09
G51: =G22+G39+G49 -> 1.0011367e+09 | H51: =H49+H39+H22 -> 9.9139906e+08
B54: B. | C54: UMLAUFVERMÖGEN
J55: F. | K55: RECHNUNGSABGRENZUNGSPOSTEN | O55: ='SAP-Auszug'!C512*-1 -> 3778372.6 | P55: ='SAP-Auszug'!D512*-1 -> 2911313
C56: I. | D56: Vorräte
D58: 1. | E58: Roh-, Hilfs- und Betriebsstoffe | G58: =+'SAP-Auszug'!C131 -> 4842319.6 | H58: =+'SAP-Auszug'!D131 -> 4612055.7
C61: II. | D61: Forderungen und sonstige Vermögensgegenstände
D63: 1. | E63: Forderungen aus Lieferungen und Leistungen | F63: =+'SAP-Auszug'!C157 -> 25047148 | H63: =+'SAP-Auszug'!D157 -> 20029047
D64: 2. | E64: Forderungen gegen verbundene Unternehmen | F64: =+'SAP-Auszug'!C184 -> 12770377 | H64: =+'SAP-Auszug'!D184 -> 17322527
D65: 3. | E65: Forderungen gegen Unternehmen,
E66: mit denen ein Beteiligungsverhältnis besteht | F66: =+'SAP-Auszug'!C195 -> 120513.71 | H66: =+'SAP-Auszug'!D195 -> 53931.72
D67: 4. | E67: Sonstige Vermögensgegenstände | F67: =+'SAP-Auszug'!C221 -> 2740346.2 | H67: =+'SAP-Auszug'!D221 -> 2229903.8
G68: =SUM(F63:F67) -> 40678385 | H68: =SUM(H63:H67) -> 39635410
C70: III. | D70: Flüssige Mittel | G70: =+'SAP-Auszug'!C264 -> 45073930 | H70: =+'SAP-Auszug'!D264 -> 56824308
G72: =G58+G68+G70 -> 90594635 | H72: =H70+H68+H58 -> 101071774
B74: C. | C74: RECHNUNGSABGRENZUNGSPOSTEN | G74: =+'SAP-Auszug'!C275 -> 1283956.8 | H74: =+'SAP-Auszug'!D275 -> 1670783.5
B77: D. | C77: AKTIVER UNTERSCHIEDSBETRAG AUS DER
C78: VERMÖGENSVERRECHNUNG | G78: =+'SAP-Auszug'!C280 -> 594605.24 | H78: =+'SAP-Auszug'!D280 -> 1577169.9
B81: E. | C81: NICHT DURCH EIGENKAPITAL GEDECKTER FEHLBETRAG | G81: =+'SAP-Auszug'!C284 -> 21263169 | H81: =+'SAP-Auszug'!D284 -> 41509758
G84: =G22+G39+G49+G58+G68+G70+G74+G78+G81 -> 1.1148731e+09 | H84: =H22+H39+H49+H58+H68+H70+H74+H78+H81 -> 1.1372285e+09 | O84: =O55+O50+O37+O28+O25+O22 -> 1.1148731e+09 | P84: =P55+P50+P37+P28+P25+P22 -> 1.1372285e+09
O86: =O25+O28+O37+O50+O55 -> 1.1148731e+09 | P86: =P25+P28+P37+P50+P55 -> 1.1372285e+09
G87: =G22+G39+G49+G58+G68+G70+G74+G78+G81 -> 1.1148731e+09 | H87: =H22+H39+H49+H58+H68+H70+H74+H78+H81 -> 1.1372285e+09 | O87: =G84-O84 -> 0 | P87: =H84-P84 -> 0
O90: =-G81+O25/2+O28/2+N45 -> 1.3751068e+08
O92: =O90/O86 -> 0.123342

Sheet G+V
A1: Gewinn- und Verlustrechnung
A3: für den Zeitraum vom 01. Januar bis 31. Dezember 2025
A5: der
A7: Flughafen Düsseldorf GmbH, Düsseldorf
E8: =TODAY() -> 46297
D11: 01.01.-31.12. | E11: 01.01.-31.12.
D12: 2025 | E12: 2024
D14: EUR | E14: EUR
A17: 1. | B17: Umsatzerlöse | D17: ='SAP-Auszug'!C638*-1 -> 4.6722847e+08 | E17: ='SAP-Auszug'!D638*-1 -> 4.4299096e+08
A19: 2. | B19: Andere aktivierte Eigenleistungen | D19: ='SAP-Auszug'!C643*-1 -> 3219669.6 | E19: ='SAP-Auszug'!D643*-1 -> 2047153.4
A21: 3. | B21: Sonstige betriebliche Erträge | D21: ='SAP-Auszug'!C679*-1 -> 11043538 | E21: 10555743
A23: 4. | B23: Materialaufwand
B24: a) | C24: Aufwendungen für Roh-, Hilfs- und Betriebsstoffe | D24: ='SAP-Auszug'!C726 -> 35368094 | E24: ='SAP-Auszug'!D726 -> 32429057
B25: b) | C25: Aufwendungen für bezogene Leistungen | D25: ='SAP-Auszug'!C750 -> 1.215559e+08 | E25: ='SAP-Auszug'!D750 -> 1.2156363e+08
D26: =SUM(D24:D25) -> 1.5692399e+08 | E26: =SUM(E24:E25) -> 1.5399269e+08
A27: 5. | B27: Personalaufwand
B28: a) | C28: Löhne und Gehälter | D28: =+'SAP-Auszug'!C777 -> 94688354 | E28: =+'SAP-Auszug'!D777 -> 88505043
B29: b) | C29: Soziale Abgaben und Aufwendungen für Altersversorgung und für Unterstützung | D29: =+'SAP-Auszug'!C804 -> 25168230 | E29: =+'SAP-Auszug'!D804 -> 23936970
D30: =SUM(D28:D29) -> 1.1985658e+08 | E30: =SUM(E28:E29) -> 1.1244201e+08
A32: 6. | B32: Abschreibungen auf immaterielle Vermögensgegenstände des Anlagevermögens und Sachanlagen | D32: =+'SAP-Auszug'!C825 -> 78541278 | E32: =+'SAP-Auszug'!D825 -> 76329430
A34: 7. | B34: Sonstige betriebliche Aufwendungen | D34: =+'SAP-Auszug'!C941 -> 69384919 | E34: 64915860
A36: 8. | B36: Erträge aus Beteiligungen | D36: =+'SAP-Auszug'!C953*-1 -> 404732.85 | E36: =+'SAP-Auszug'!D953*-1 -> 459341.41
A38: 9. | B38: Erträge aus Gewinnabführungsverträgen | D38: =+'SAP-Auszug'!C957*-1 -> 1193400 | E38: =+'SAP-Auszug'!D957*-1 -> 763751.84
A40: 10. | B40: Erträge aus Ausleihungen des Finanzanlagevermögens | D40: =+'SAP-Auszug'!C964*-1 -> 60270.48 | E40: =+'SAP-Auszug'!D964*-1 -> 145.45
A42: 11. | B42: Sonstige Zinsen und ähnliche Erträge | D42: =+'SAP-Auszug'!C977*-1 -> 1829429.1 | E42: =+'SAP-Auszug'!D977*-1 -> 2803574.2
A44: 12. | B44: Aufwendungen aus Verlustübernahme | D44: =+'SAP-Auszug'!C982 -> 1354804.7 | E44: =+'SAP-Auszug'!D982 -> 1735218.4
A46: 13. | B46: Zinsen und ähnliche Aufwendungen | D46: =+'SAP-Auszug'!C1008 -> 35082809 | E46: =+'SAP-Auszug'!D1008 -> 32906422
A48: 14. | B48: Steuern vom Einkommen und vom Ertrag | D48: =+'SAP-Auszug'!C1018 -> 2867908.9 | E48: =+'SAP-Auszug'!D1018 -> 2020682.5
A50: 15. | B50: Ergebnis nach Steuern | D50: =D17+D19+D21-D24-D25-D28-D29-D32-D34+D36+D38+D40+D42-D44-D46-D48 -> 20967217 | E50: =E17+E19+E21-E24-E25-E28-E29-E32-E34+E36+E38+E40+E42-E44-E46-E48 -> 15278358
A52: 16. | B52: Sonstige Steuern | D52: =+'SAP-Auszug'!C1029 -> 720627.36 | E52: =+'SAP-Auszug'!D1029 -> 1691281.5
A55: 17. | B55: Jahresüberschuss/Jahresfehlbetrag | D55: =D50-D52 -> 20246589 | E55: =E50-E52 -> 13587076
