Workbook

Sheet Mapping
A1: Kundenkonto | B1: Bezeichnung Kunde | C1: Bisheriges YCOA-Konto | D1: Bezeichnung bisheriges YCOA | E1: Bilanzposition Kunde (aus Z) | F1: Bilanzposition bisheriges YCOA (aus Y) | G1: Ergebnis Bezeichnungsprüfung (OK/Abweichung) | H1: Ergebnis Bilanzprüfung (OK/Abweichung/nicht prüfbar) | I1: Neues YCOA-Konto | J1: Bezeichnung neues YCOA | K1: Bilanzposition neues YCOA | L1: Begründung | M1: Konfidenz (hoch/mittel/niedrig) | N1: Status (unverändert/korrigiert/Neuanlage prüfen/manuell klären)
A2: 050000 | B2: Software und sonstige immat. Wirtschaftsgüter | C2: 16020000 | D2: Geringwertige Wirtschaftsgüter | E2: Aktiva > A. Anlagevermögen > I. Immaterielle VG > 1. Konzessionen, Schutzrechte, Lizenzen (Software und sonstige immaterielle WG) [1031011] | F2: Assets > Non-Current Assets > Property Plant & Equipment (Net) > Property Plant & Equipment (Gross) | G2: Abweichung | H2: Abweichung | I2: 19320000 | J2: Intangible Assets | K2: Assets > Non-Current Assets > Other Non-Current Assets > Intangible Assets | L2: Bisher Geringwertige Wirtschaftsgüter (Sachanlagen): weder Sachverhalt noch Bilanzposition passen. Neu Intangible Assets (immaterielle Vermögensgegenstände) in Position Intangible Assets, passend zum Abschreibungskonto 64021000. 1:n beachten: Software kann je Anlagenklasse auf 16008000 Computer Software geführt werden (gleiche Position); kumulierte Abschreibung getrennt auf 19420000 bzw. 17008000 (Kunde weist netto auf einem Konto aus). | M2: mittel | N2: korrigiert
A3: 050090 | B3: Software Anzahlungen | C3: 16012000 | D3: Aktivierte Anzahlungen auf Anlagen | E3: Aktiva > A. Anlagevermögen > I. Immaterielle VG > 2. Geleistete Anzahlungen [1031031] | F3: Assets > Non-Current Assets > Property Plant & Equipment (Net) > Property Plant & Equipment (Gross) | G3: OK | H3: Abweichung | L3: Bezeichnung passt (Anzahlungen auf Anlagen), 16012000 liegt aber in Property Plant & Equipment; der Kunde weist Anzahlungen auf immaterielle VG gesondert unter A.I.2 aus. In Intangible Assets existiert kein Anzahlungskonto. Neuanlage prüfen (Kopiervorlage 16012000, Zuordnung zu Intangible Assets). Rückfall ohne Neuanlage: 16012000 mit abweichendem Bilanzausweis. | M3: hoch | N3: Neuanlage prüfen
A4: 010000 | B4: Bauten auf eig.Grundstücken +grundstücksgl.Rechten | C4: 64000000 | D4: Abschreib. - Grundstücke und grundstücksgl. Rechte | E4: Aktiva > A. Anlagevermögen > II. Sachanlagen > 1. Grundstücke und Bauten > a) Flughafenbauten inkl. Grundstücke [1032011] | F4: nicht in [Y] enthalten | G4: Abweichung | H4: Abweichung | I4: 16001000 | J4: Gebäude / Buildings | K4: Assets > Non-Current Assets > Property Plant & Equipment (Net) > Property Plant & Equipment (Gross) | L4: Bisher Abschreibungskonto (Aufwand, zudem nicht in [Y]) für ein Bestandskonto. Neu Gebäude in Property Plant & Equipment (Gross). Grundstücksanteile je Anlagenklasse auf 16000000. Hinweis: Der Kunde führt Anschaffungskosten und Wertberichtigung auf einem Konto (Nettoausweis); in YCOA sind Bestandskonto (16xxxxxx) und Wertberichtigungskonto (17xxxxxx) getrennt – Kontenfindung FI-AA und Altdatenübernahme brutto je Anlagenklasse. | M4: hoch | N4: korrigiert
A5: 011000 | B5: Bebaute Wohngrundstücke (Flank. Massnahmen) | C5: 17000000 | D5: Wertberichtigungen Grundstücke | E5: Aktiva > A. Anlagevermögen > II. Sachanlagen > 1. Grundstücke und Bauten > b) Grundstücke mit Wohnbauten [1032012] | F5: Assets > Non-Current Assets > Property Plant & Equipment (Net) > Accumulated Depreciation | G5: Abweichung | H5: OK | I5: 16001000 | J5: Gebäude / Buildings | K5: Assets > Non-Current Assets > Property Plant & Equipment (Net) > Property Plant & Equipment (Gross) | L5: Bisher Wertberichtigungskonto (Accumulated Depreciation) für ein Bestandskonto. Neu Gebäude; der Grundstücksanteil der bebauten Wohngrundstücke gehört je Anlagenklasse auf 16000000 (1:n). n:1 mit 010000: die Unterposition b) Grundstücke mit Wohnbauten der Kundenbilanz ist auf Kontenebene nicht mehr trennbar – über Anlagenklasse auswertbar, sonst eigenes Konto anlegen. Hinweis: Der Kunde führt Anschaffungskosten und Wertberichtigung auf einem Konto (Nettoausweis); in YCOA sind Bestandskonto (16xxxxxx) und Wertberichtigungskonto (17xxxxxx) getrennt – Kontenfindung FI-AA und Altdatenübernahme brutto je Anlagenklasse. | M5: mittel | N5: korrigiert
A6: 012000 | B6: Grundstücke | C6: 17000000 | D6: Wertberichtigungen Grundstücke | E6: Aktiva > A. Anlagevermögen > II. Sachanlagen > 1. Grundstücke und Bauten > c) Grundstücke ohne Bauten [1032013] | F6: Assets > Non-Current Assets > Property Plant & Equipment (Net) > Accumulated Depreciation | G6: Abweichung | H6: OK | I6: 16000000 | J6: Grundstücke und grundstücksgleiche Rechte / Land & Land Improvements | K6: Assets > Non-Current Assets > Property Plant & Equipment (Net) > Property Plant & Equipment (Gross) | L6: Bisher Wertberichtigungskonto (Accumulated Depreciation) für ein Bestandskonto. Neu Grundstücke und grundstücksgleiche Rechte in Property Plant & Equipment (Gross). | M6: hoch | N6: korrigiert
A7: 013000 | B7: Grundstücksgleiche Rechte ohne Bauten | C7: 16000000 | D7: Grundstücke und grundstücksgleiche Rechte | E7: Aktiva > A. Anlagevermögen > II. Sachanlagen > 1. Grundstücke und Bauten > d) Erbbaurechte [1032014] | F7: Assets > Non-Current Assets > Property Plant & Equipment (Net) > Property Plant & Equipment (Gross) | G7: OK | H7: OK | I7: 16000000 | J7: Grundstücke und grundstücksgleiche Rechte / Land & Land Improvements | K7: Assets > Non-Current Assets > Property Plant & Equipment (Net) > Property Plant & Equipment (Gross) | L7: Bezeichnung und Bilanzposition passen. n:1 mit 012000: die Unterpositionen c) Grundstücke ohne Bauten und d) Erbbaurechte der Kundenbilanz sind auf Kontenebene nicht mehr trennbar (über Anlagenklasse auswertbar). Hinweis: Der Kunde führt Anschaffungskosten und Wertberichtigung auf einem Konto (Nettoausweis); in YCOA sind Bestandskonto (16xxxxxx) und Wertberichtigungskonto (17xxxxxx) getrennt – Kontenfindung FI-AA und Altdatenübernahme brutto je Anlagenklasse. | M7: hoch | N7: unverändert
A8: 020000 | B8: Außenanlagen / Flughafenanlagen | C8: TBD | E8: Aktiva > A. Anlagevermögen > II. Sachanlagen > 2. Technische Anlagen und Maschinen > a) Flughafenanlagen [1032021] | G8: kein Mapping (TBD) | H8: kein Mapping (TBD) | I8: 16002000 | J8: Machinery & Equipment | K8: Assets > Non-Current Assets > Property Plant & Equipment (Net) > Property Plant & Equipment (Gross) | L8: Bisher ohne Zuordnung. Der Kunde weist Flughafenanlagen unter Technische Anlagen und Maschinen aus; sinngemäß Machinery & Equipment. n:1 mit 030000: die Unterpositionen a) Flughafenanlagen und b) Betriebsanlagen sind auf Kontenebene nicht mehr trennbar – bei Bedarf eigenes Konto anlegen. Hinweis: Der Kunde führt Anschaffungskosten und Wertberichtigung auf einem Konto (Nettoausweis); in YCOA sind Bestandskonto (16xxxxxx) und Wertberichtigungskonto (17xxxxxx) getrennt – Kontenfindung FI-AA und Altdatenübernahme brutto je Anlagenklasse. | M8: mittel | N8: korrigiert
A9: 030000 | B9: Betriebsanlagen | C9: TBD | E9: Aktiva > A. Anlagevermögen > II. Sachanlagen > 2. Technische Anlagen und Maschinen > b) Betriebsanlagen [1032022] | G9: kein Mapping (TBD) | H9: kein Mapping (TBD) | I9: 16002000 | J9: Machinery & Equipment | K9: Assets > Non-Current Assets > Property Plant & Equipment (Net) > Property Plant & Equipment (Gross) | L9: Bisher ohne Zuordnung. Betriebsanlagen entsprechen Technische Anlagen und Maschinen (Machinery & Equipment). n:1 mit 020000 (siehe dort). Hinweis: Der Kunde führt Anschaffungskosten und Wertberichtigung auf einem Konto (Nettoausweis); in YCOA sind Bestandskonto (16xxxxxx) und Wertberichtigungskonto (17xxxxxx) getrennt – Kontenfindung FI-AA und Altdatenübernahme brutto je Anlagenklasse. | M9: hoch | N9: korrigiert
A10: 040000 | B10: Betriebs- und Geschäftsausstattung | C10: 16005000 | D10: Betriebs- und Geschäftsausstattung | E10: Aktiva > A. Anlagevermögen > II. Sachanlagen > 3. Andere Anlagen, Betriebs- und Geschäftsausstattung [1032031] | F10: Assets > Non-Current Assets > Property Plant & Equipment (Net) > Property Plant & Equipment (Gross) | G10: OK | H10: OK | I10: 16005000 | J10: Betriebs- und Geschäftsausstattung / Office Equipment | K10: Assets > Non-Current Assets > Property Plant & Equipment (Net) > Property Plant & Equipment (Gross) | L10: Bezeichnung identisch, Bilanzposition passt. 1:n beachten: Fahrzeuge, Mobiliar, IT-Hardware und geringwertige Wirtschaftsgüter können je Anlagenklasse auf 16004000/16006000/16007000/16020000 differenziert werden. Hinweis: Der Kunde führt Anschaffungskosten und Wertberichtigung auf einem Konto (Nettoausweis); in YCOA sind Bestandskonto (16xxxxxx) und Wertberichtigungskonto (17xxxxxx) getrennt – Kontenfindung FI-AA und Altdatenübernahme brutto je Anlagenklasse. | M10: hoch | N10: unverändert
A11: 058009 | B11: Im Bau befindliche Anlagen + gel. Anzahlungen | C11: 16009000 | D11: Anlagen im Bau | E11: Aktiva > A. Anlagevermögen > II. Sachanlagen > 4. Geleistete Anzahlungen und Anlagen im Bau [1032041] | F11: Assets > Non-Current Assets > Property Plant & Equipment (Net) > Property Plant & Equipment (Gross) | G11: OK | H11: OK | I11: 16009000 | J11: Anlagen im Bau / Assets under Construction | K11: Assets > Non-Current Assets > Property Plant & Equipment (Net) > Property Plant & Equipment (Gross) | L11: Bezeichnung (Anlagen im Bau) und Bilanzposition passen. 1:n beachten: geleistete Anzahlungen auf Sachanlagen laufen in YCOA über 16010000/16012000 (gleiche Position). | M11: hoch | N11: unverändert
A12: 065015 | B12: Beteiligung FD Immobilien GmbH | C12: 18010000 | D12: (in [X] ohne Bezeichnung; laut [Y]: Investment Subsidiaries) | E12: Aktiva > A. Anlagevermögen > III. Finanzanlagen > 1. Anteile an verbundenen Unternehmen [1033010] | F12: Assets > Non-Current Assets > Other Non-Current Assets > Long-Term Investments | G12: OK | H12: OK | I12: 18010000 | J12: Beteiligung Tochtergesellschaften / Investment Subsidiaries | K12: Assets > Non-Current Assets > Other Non-Current Assets > Long-Term Investments | L12: Anteile an verbundenen Unternehmen entsprechen Investment Subsidiaries (Beteiligung Tochtergesellschaften); Position Long-Term Investments passt. In [X] war die Kontonummer ohne Bezeichnung und mit Status TBD hinterlegt – bestätigt. n:1 über vier Gesellschaften: Trennung je Gesellschaft über Partnergesellschaft möglich. | M12: hoch | N12: unverändert
A13: 065016 | B13: Beteiligung FD Ground Handling GmbH | C13: 18010000 | D13: (in [X] ohne Bezeichnung; laut [Y]: Investment Subsidiaries) | E13: Aktiva > A. Anlagevermögen > III. Finanzanlagen > 1. Anteile an verbundenen Unternehmen [1033010] | F13: Assets > Non-Current Assets > Other Non-Current Assets > Long-Term Investments | G13: OK | H13: OK | I13: 18010000 | J13: Beteiligung Tochtergesellschaften / Investment Subsidiaries | K13: Assets > Non-Current Assets > Other Non-Current Assets > Long-Term Investments | L13: Anteile an verbundenen Unternehmen entsprechen Investment Subsidiaries (Beteiligung Tochtergesellschaften); Position Long-Term Investments passt. In [X] war die Kontonummer ohne Bezeichnung und mit Status TBD hinterlegt – bestätigt. n:1 über vier Gesellschaften: Trennung je Gesellschaft über Partnergesellschaft möglich. | M13: hoch | N13: unverändert
A14: 065019 | B14: Beteiligung Flughafen Düsseldorf Security GmbH | C14: 18010000 | D14: (in [X] ohne Bezeichnung; laut [Y]: Investment Subsidiaries) | E14: Aktiva > A. Anlagevermögen > III. Finanzanlagen > 1. Anteile an verbundenen Unternehmen [1033010] | F14: Assets > Non-Current Assets > Other Non-Current Assets > Long-Term Investments | G14: OK | H14: OK | I14: 18010000 | J14: Beteiligung Tochtergesellschaften / Investment Subsidiaries | K14: Assets > Non-Current Assets > Other Non-Current Assets > Long-Term Investments | L14: Anteile an verbundenen Unternehmen entsprechen Investment Subsidiaries (Beteiligung Tochtergesellschaften); Position Long-Term Investments passt. In [X] war die Kontonummer ohne Bezeichnung und mit Status TBD hinterlegt – bestätigt. n:1 über vier Gesellschaften: Trennung je Gesellschaft über Partnergesellschaft möglich. | M14: hoch | N14: unverändert
A15: 065022 | B15: Beteiligung FD Energie GmbH | C15: 18010000 | D15: (in [X] ohne Bezeichnung; laut [Y]: Investment Subsidiaries) | E15: Aktiva > A. Anlagevermögen > III. Finanzanlagen > 1. Anteile an verbundenen Unternehmen [1033010] | F15: Assets > Non-Current Assets > Other Non-Current Assets > Long-Term Investments | G15: OK | H15: OK | I15: 18010000 | J15: Beteiligung Tochtergesellschaften / Investment Subsidiaries | K15: Assets > Non-Current Assets > Other Non-Current Assets > Long-Term Investments | L15: Anteile an verbundenen Unternehmen entsprechen Investment Subsidiaries (Beteiligung Tochtergesellschaften); Position Long-Term Investments passt. In [X] war die Kontonummer ohne Bezeichnung und mit Status TBD hinterlegt – bestätigt. n:1 über vier Gesellschaften: Trennung je Gesellschaft über Partnergesellschaft möglich. | M15: hoch | N15: unverändert
A16: 065018 | B16: Beteiligung SITA Airport IT GmbH | C16: 18010000 | D16: (in [X] ohne Bezeichnung; laut [Y]: Investment Subsidiaries) | E16: Aktiva > A. Anlagevermögen > III. Finanzanlagen > 2. Beteiligungen [1033030/00] | F16: Assets > Non-Current Assets > Other Non-Current Assets > Long-Term Investments | G16: Abweichung | H16: Abweichung | I16: 18020000 | J16: Other Long Term Investments | K16: Assets > Non-Current Assets > Other Non-Current Assets > Long-Term Investments | L16: Beteiligung (Bilanzposition A.III.2 des Kunden), kein verbundenes Unternehmen; 18010000 ist den Tochtergesellschaften vorbehalten, sonst geht die Trennung Anteile an verbundenen Unternehmen / Beteiligungen verloren. Neu Other Long Term Investments (gleiche SAP-Position Long-Term Investments). Bezeichnung des Zielkontos ist generisch; ein eigenes Konto Beteiligungen wäre die saubere Alternative. | M16: mittel | N16: korrigiert
A17: 065025 | B17: Beteiligung Flughafengesell. Mönchengladbach GmbH | C17: 18010000 | D17: (in [X] ohne Bezeichnung; laut [Y]: Investment Subsidiaries) | E17: Aktiva > A. Anlagevermögen > III. Finanzanlagen > 2. Beteiligungen [1033030/00] | F17: Assets > Non-Current Assets > Other Non-Current Assets > Long-Term Investments | G17: Abweichung | H17: Abweichung | I17: 18020000 | J17: Other Long Term Investments | K17: Assets > Non-Current Assets > Other Non-Current Assets > Long-Term Investments | L17: Beteiligung (Bilanzposition A.III.2 des Kunden), kein verbundenes Unternehmen; 18010000 ist den Tochtergesellschaften vorbehalten, sonst geht die Trennung Anteile an verbundenen Unternehmen / Beteiligungen verloren. Neu Other Long Term Investments (gleiche SAP-Position Long-Term Investments). Bezeichnung des Zielkontos ist generisch; ein eigenes Konto Beteiligungen wäre die saubere Alternative. | M17: mittel | N17: korrigiert
A18: 067000 | B18: Beteiligung Swissport DUS Cargo Sevices GmbH | C18: 18010000 | D18: (in [X] ohne Bezeichnung; laut [Y]: Investment Subsidiaries) | E18: Aktiva > A. Anlagevermögen > III. Finanzanlagen > 2. Beteiligungen [1033030/00] | F18: Assets > Non-Current Assets > Other Non-Current Assets > Long-Term Investments | G18: Abweichung | H18: Abweichung | I18: 18020000 | J18: Other Long Term Investments | K18: Assets > Non-Current Assets > Other Non-Current Assets > Long-Term Investments | L18: Beteiligung (Bilanzposition A.III.2 des Kunden), kein verbundenes Unternehmen; 18010000 ist den Tochtergesellschaften vorbehalten, sonst geht die Trennung Anteile an verbundenen Unternehmen / Beteiligungen verloren. Neu Other Long Term Investments (gleiche SAP-Position Long-Term Investments). Bezeichnung des Zielkontos ist generisch; ein eigenes Konto Beteiligungen wäre die saubere Alternative. | M18: mittel | N18: korrigiert
A19: 066002 | B19: Darlehen Flughafen Düsseldorf Cargo GmbH | C19: 19110000 | D19: Sonstige Darlehen - langfristig | E19: Aktiva > A. Anlagevermögen > III. Finanzanlagen > 3. Ausleihungen an Unternehmen mit Beteiligungsverhältnis (Restlaufzeit > 1 Jahr) [1033042] | F19: nicht in [Y] enthalten | G19: OK | H19: Abweichung | L19: Bezeichnung des bisherigen Kontos passt (langfristiges Darlehen), 19110000 ist aber in [Y] nicht vorhanden – Bilanzposition nicht belegbar. In Long-Term Investments gibt es kein Konto für Ausleihungen an Beteiligungsunternehmen (Bilanzposition A.III.3 des Kunden, nach § 266 HGB gesondert auszuweisen). Neuanlage prüfen. Rückfall: 18020000 (Verlust des gesonderten Ausweises) oder 19110000 aus [X] nach Anlage im Buchungskreis und Zuordnung in der Bilanzstruktur. | M19: mittel | N19: Neuanlage prüfen
A20: 064009 | B20: Arbeitgeberdarlehen - Hauptbuchkonto | C20: TBD | E20: Aktiva > A. Anlagevermögen > III. Finanzanlagen > 4. Sonstige Ausleihungen [1033062] | G20: kein Mapping (TBD) | H20: kein Mapping (TBD) | I20: 14107000 | J20: Mitarbeiterdarlehen / Loans to Staff | K20: Assets > Non-Current Assets > Other Non-Current Assets > Long-Term Investments | L20: Bisher ohne Zuordnung. Arbeitgeberdarlehen entsprechen Mitarbeiterdarlehen (Loans to Staff) in Long-Term Investments; Position Sonstige Ausleihungen passt sinngemäß. | M20: hoch | N20: korrigiert
A21: 099200 | B21: Wertberichtigung Altbestand Lagermaterial | C21: 17009000 | D21: Wertberichtigung - Anlagen im Bau | E21: Aktiva > B. Umlaufvermögen > I. Vorräte > 1. Roh-, Hilfs- und Betriebsstoffe [1041010] | F21: Assets > Non-Current Assets > Property Plant & Equipment (Net) > Accumulated Depreciation | G21: Abweichung | H21: Abweichung | I21: 13100900 | J21: Inventory - Revaluation Raw Material | K21: Assets > Current Assets > Inventories | L21: Bisher Wertberichtigung Anlagen im Bau (Anlagevermögen) für eine Wertberichtigung auf Lagermaterial. Neu Inventory - Revaluation Raw Material in Position Inventories (Bewertungsabschlag auf RHB-Bestand). | M21: mittel | N21: korrigiert
A22: 300019 | B22: Material für Kraftfahrzeugwerkstatt | C22: 65200000 | D22: Sonstiges Material | E22: Aktiva > B. Umlaufvermögen > I. Vorräte > 1. Roh-, Hilfs- und Betriebsstoffe [1041010] | F22: Net Income > Operating Income > Operating Expense > Employee Expense > Office Expense | G22: Abweichung | H22: Abweichung | I22: 13100000 | J22: Inventory - Raw Material | K22: Assets > Current Assets > Inventories | L22: Bisher Aufwandskonto Sonstiges Material (Office Expense). Bestandskonto für Lagermaterial: Zielkonto muss in Inventories liegen. Neu Inventory - Raw Material als Bestandskonto für Roh-, Hilfs- und Betriebsstoffe. n:1: die Trennung nach Werkstatt/Materialart geht auf Kontenebene verloren, bleibt aber über Bewertungsklasse, Warengruppe oder Lagerort auswertbar; eigene Bestandskonten je Materialart nur bei Bedarf anlegen. | M22: hoch | N22: korrigiert
A23: 300029 | B23: Material für Klempnerei | C23: 65200000 | D23: Sonstiges Material | E23: Aktiva > B. Umlaufvermögen > I. Vorräte > 1. Roh-, Hilfs- und Betriebsstoffe [1041010] | F23: Net Income > Operating Income > Operating Expense > Employee Expense > Office Expense | G23: Abweichung | H23: Abweichung | I23: 13100000 | J23: Inventory - Raw Material | K23: Assets > Current Assets > Inventories | L23: Bisher Aufwandskonto Sonstiges Material (Office Expense). Bestandskonto für Lagermaterial: Zielkonto muss in Inventories liegen. Neu Inventory - Raw Material als Bestandskonto für Roh-, Hilfs- und Betriebsstoffe. n:1: die Trennung nach Werkstatt/Materialart geht auf Kontenebene verloren, bleibt aber über Bewertungsklasse, Warengruppe oder Lagerort auswertbar; eigene Bestandskonten je Materialart nur bei Bedarf anlegen. | M23: hoch | N23: korrigiert
A24: 300039 | B24: Material für Schreinerei / Schlüsseldienst | C24: 52544000 | D24: Ertr. aus Preisdifferenzen - Material-Ledger (LKW) | E24: Aktiva > B. Umlaufvermögen > I. Vorräte > 1. Roh-, Hilfs- und Betriebsstoffe [1041010] | F24: Net Income > Operating Income > Other Operating Revenue | G24: Abweichung | H24: Abweichung | I24: 13100000 | J24: Inventory - Raw Material | K24: Assets > Current Assets > Inventories | L24: Bisher Ertragskonto Preisdifferenzen Material-Ledger. Bestandskonto für Lagermaterial: Zielkonto muss in Inventories liegen. Neu Inventory - Raw Material als Bestandskonto für Roh-, Hilfs- und Betriebsstoffe. n:1: die Trennung nach Werkstatt/Materialart geht auf Kontenebene verloren, bleibt aber über Bewertungsklasse, Warengruppe oder Lagerort auswertbar; eigene Bestandskonten je Materialart nur bei Bedarf anlegen. | M24: hoch | N24: korrigiert
A25: 300049 | B25: Material für Normteile | C25: 65200000 | D25: Sonstiges Material | E25: Aktiva > B. Umlaufvermögen > I. Vorräte > 1. Roh-, Hilfs- und Betriebsstoffe [1041010] | F25: Net Income > Operating Income > Operating Expense > Employee Expense > Office Expense | G25: Abweichung | H25: Abweichung | I25: 13100000 | J25: Inventory - Raw Material | K25: Assets > Current Assets > Inventories | L25: Bisher Aufwandskonto Sonstiges Material (Office Expense). Bestandskonto für Lagermaterial: Zielkonto muss in Inventories liegen. Neu Inventory - Raw Material als Bestandskonto für Roh-, Hilfs- und Betriebsstoffe. n:1: die Trennung nach Werkstatt/Materialart geht auf Kontenebene verloren, bleibt aber über Bewertungsklasse, Warengruppe oder Lagerort auswertbar; eigene Bestandskonten je Materialart nur bei Bedarf anlegen. | M25: hoch | N25: korrigiert
A26: 300059 | B26: Material für Mechanikerwerkstatt | C26: 65200000 | D26: Sonstiges Material | E26: Aktiva > B. Umlaufvermögen > I. Vorräte > 1. Roh-, Hilfs- und Betriebsstoffe [1041010] | F26: Net Income > Operating Income > Operating Expense > Employee Expense > Office Expense | G26: Abweichung | H26: Abweichung | I26: 13100000 | J26: Inventory - Raw Material | K26: Assets > Current Assets > Inventories | L26: Bisher Aufwandskonto Sonstiges Material (Office Expense). Bestandskonto für Lagermaterial: Zielkonto muss in Inventories liegen. Neu Inventory - Raw Material als Bestandskonto für Roh-, Hilfs- und Betriebsstoffe. n:1: die Trennung nach Werkstatt/Materialart geht auf Kontenebene verloren, bleibt aber über Bewertungsklasse, Warengruppe oder Lagerort auswertbar; eigene Bestandskonten je Materialart nur bei Bedarf anlegen. | M26: hoch | N26: korrigiert
A27: 300069 | B27: Material für Heizungsdienst | C27: 65200000 | D27: Sonstiges Material | E27: Aktiva > B. Umlaufvermögen > I. Vorräte > 1. Roh-, Hilfs- und Betriebsstoffe [1041010] | F27: Net Income > Operating Income > Operating Expense > Employee Expense > Office Expense | G27: Abweichung | H27: Abweichung | I27: 13100000 | J27: Inventory - Raw Material | K27: Assets > Current Assets > Inventories | L27: Bisher Aufwandskonto Sonstiges Material (Office Expense). Bestandskonto für Lagermaterial: Zielkonto muss in Inventories liegen. Neu Inventory - Raw Material als Bestandskonto für Roh-, Hilfs- und Betriebsstoffe. n:1: die Trennung nach Werkstatt/Materialart geht auf Kontenebene verloren, bleibt aber über Bewertungsklasse, Warengruppe oder Lagerort auswertbar; eigene Bestandskonten je Materialart nur bei Bedarf anlegen. | M27: hoch | N27: korrigiert
A28: 300079 | B28: Material für Schlosserei | C28: 65200000 | D28: Sonstiges Material | E28: Aktiva > B. Umlaufvermögen > I. Vorräte > 1. Roh-, Hilfs- und Betriebsstoffe [1041010] | F28: Net Income > Operating Income > Operating Expense > Employee Expense > Office Expense | G28: Abweichung | H28: Abweichung | I28: 13100000 | J28: Inventory - Raw Material | K28: Assets > Current Assets > Inventories | L28: Bisher Aufwandskonto Sonstiges Material (Office Expense). Bestandskonto für Lagermaterial: Zielkonto muss in Inventories liegen. Neu Inventory - Raw Material als Bestandskonto für Roh-, Hilfs- und Betriebsstoffe. n:1: die Trennung nach Werkstatt/Materialart geht auf Kontenebene verloren, bleibt aber über Bewertungsklasse, Warengruppe oder Lagerort auswertbar; eigene Bestandskonten je Materialart nur bei Bedarf anlegen. | M28: hoch | N28: korrigiert
A29: 300089 | B29: Material für Elektrowerkstatt | C29: 65200000 | D29: Sonstiges Material | E29: Aktiva > B. Umlaufvermögen > I. Vorräte > 1. Roh-, Hilfs- und Betriebsstoffe [1041010] | F29: Net Income > Operating Income > Operating Expense > Employee Expense > Office Expense | G29: Abweichung | H29: Abweichung | I29: 13100000 | J29: Inventory - Raw Material | K29: Assets > Current Assets > Inventories | L29: Bisher Aufwandskonto Sonstiges Material (Office Expense). Bestandskonto für Lagermaterial: Zielkonto muss in Inventories liegen. Neu Inventory - Raw Material als Bestandskonto für Roh-, Hilfs- und Betriebsstoffe. n:1: die Trennung nach Werkstatt/Materialart geht auf Kontenebene verloren, bleibt aber über Bewertungsklasse, Warengruppe oder Lagerort auswertbar; eigene Bestandskonten je Materialart nur bei Bedarf anlegen. | M29: hoch | N29: korrigiert
A30: 300099 | B30: Material für Hf-Werkstatt | C30: 50300000 | D30: Kosten des Umsatzes (HF & FE ohne Kostenart) | E30: Aktiva > B. Umlaufvermögen > I. Vorräte > 1. Roh-, Hilfs- und Betriebsstoffe [1041010] | F30: Net Income > Operating Income > Operating Expense > Material Expense | G30: Abweichung | H30: Abweichung | I30: 13100000 | J30: Inventory - Raw Material | K30: Assets > Current Assets > Inventories | L30: Bisher Kosten des Umsatzes (GuV). Bestandskonto für Lagermaterial: Zielkonto muss in Inventories liegen. Neu Inventory - Raw Material als Bestandskonto für Roh-, Hilfs- und Betriebsstoffe. n:1: die Trennung nach Werkstatt/Materialart geht auf Kontenebene verloren, bleibt aber über Bewertungsklasse, Warengruppe oder Lagerort auswertbar; eigene Bestandskonten je Materialart nur bei Bedarf anlegen. | M30: hoch | N30: korrigiert
A31: 673505 | B31: Aufwand Mobilitätssachbezug für MWSt | C31: 66010000 | D31: Aufwand Abzinsung (ZKB) | E31: GuV > 7. Sonstige betriebliche Aufwendungen > Personalnebenkosten [3082034] | F31: Net Income > Operating Income > Operating Expense > Other Operating Expense | G31: Abweichung | H31: Abweichung | I31: 61010000 | J31: Sonstige Personalkosten / Payroll - Other Personnel Expenses | K31: Net Income > Operating Income > Operating Expense > Employee Expense > Payroll and Benefits > Payroll Other | L31: Bisher Aufwand Abzinsung (ZKB): falsch. Aufwand aus Mobilitätssachbezügen als Personalnebenkosten; neu Payroll - Other Personnel Expenses. Umsatzsteuerbezug der Sachbezüge und Gegenkonten 889002/889003 beachten. n:1 auf 61010000 Sonstige Personalkosten – Trennung nach Art der Leistung geht verloren (lohnsteuerliche Behandlung beachten). | M31: mittel | N31: korrigiert
A32: 300119 | B32: Kfz-Betriebsstoffe/Heizstoffe/Öle/Enteisung | C32: TBD | E32: Aktiva > B. Umlaufvermögen > I. Vorräte > 1. Roh-, Hilfs- und Betriebsstoffe [1041010] | G32: kein Mapping (TBD) | H32: kein Mapping (TBD) | I32: 13100000 | J32: Inventory - Raw Material | K32: Assets > Current Assets > Inventories | L32: Bisher ohne Zuordnung. Bestandskonto für Lagermaterial: Zielkonto muss in Inventories liegen. Neu Inventory - Raw Material als Bestandskonto für Roh-, Hilfs- und Betriebsstoffe. n:1: die Trennung nach Werkstatt/Materialart geht auf Kontenebene verloren, bleibt aber über Bewertungsklasse, Warengruppe oder Lagerort auswertbar; eigene Bestandskonten je Materialart nur bei Bedarf anlegen. | M32: hoch | N32: korrigiert
A33: 300139 | B33: Material für Bauabteilung | C33: 65200000 | D33: Sonstiges Material | E33: Aktiva > B. Umlaufvermögen > I. Vorräte > 1. Roh-, Hilfs- und Betriebsstoffe [1041010] | F33: Net Income > Operating Income > Operating Expense > Employee Expense > Office Expense | G33: Abweichung | H33: Abweichung | I33: 13100000 | J33: Inventory - Raw Material | K33: Assets > Current Assets > Inventories | L33: Bisher Aufwandskonto Sonstiges Material (Office Expense). Bestandskonto für Lagermaterial: Zielkonto muss in Inventories liegen. Neu Inventory - Raw Material als Bestandskonto für Roh-, Hilfs- und Betriebsstoffe. n:1: die Trennung nach Werkstatt/Materialart geht auf Kontenebene verloren, bleibt aber über Bewertungsklasse, Warengruppe oder Lagerort auswertbar; eigene Bestandskonten je Materialart nur bei Bedarf anlegen. | M33: hoch | N33: korrigiert
A34: 300149 | B34: Werkzeuge | C34: TBD | E34: Aktiva > B. Umlaufvermögen > I. Vorräte > 1. Roh-, Hilfs- und Betriebsstoffe [1041010] | G34: kein Mapping (TBD) | H34: kein Mapping (TBD) | I34: 13100000 | J34: Inventory - Raw Material | K34: Assets > Current Assets > Inventories | L34: Bisher ohne Zuordnung. Bestandskonto für Lagermaterial: Zielkonto muss in Inventories liegen. Neu Inventory - Raw Material als Bestandskonto für Roh-, Hilfs- und Betriebsstoffe. n:1: die Trennung nach Werkstatt/Materialart geht auf Kontenebene verloren, bleibt aber über Bewertungsklasse, Warengruppe oder Lagerort auswertbar; eigene Bestandskonten je Materialart nur bei Bedarf anlegen. | M34: hoch | N34: korrigiert
A35: 300159 | B35: Berufs-und Schutzkleidung | C35: TBD | E35: Aktiva > B. Umlaufvermögen > I. Vorräte > 1. Roh-, Hilfs- und Betriebsstoffe [1041010] | G35: kein Mapping (TBD) | H35: kein Mapping (TBD) | I35: 13100000 | J35: Inventory - Raw Material | K35: Assets > Current Assets > Inventories | L35: Bisher ohne Zuordnung. Bestandskonto für Lagermaterial: Zielkonto muss in Inventories liegen. Neu Inventory - Raw Material als Bestandskonto für Roh-, Hilfs- und Betriebsstoffe. n:1: die Trennung nach Werkstatt/Materialart geht auf Kontenebene verloren, bleibt aber über Bewertungsklasse, Warengruppe oder Lagerort auswertbar; eigene Bestandskonten je Materialart nur bei Bedarf anlegen. | M35: hoch | N35: korrigiert
A36: 300169 | B36: Material für Malerwerkstatt | C36: 65200000 | D36: Sonstiges Material | E36: Aktiva > B. Umlaufvermögen > I. Vorräte > 1. Roh-, Hilfs- und Betriebsstoffe [1041010] | F36: Net Income > Operating Income > Operating Expense > Employee Expense > Office Expense | G36: Abweichung | H36: Abweichung | I36: 13100000 | J36: Inventory - Raw Material | K36: Assets > Current Assets > Inventories | L36: Bisher Aufwandskonto Sonstiges Material (Office Expense). Bestandskonto für Lagermaterial: Zielkonto muss in Inventories liegen. Neu Inventory - Raw Material als Bestandskonto für Roh-, Hilfs- und Betriebsstoffe. n:1: die Trennung nach Werkstatt/Materialart geht auf Kontenebene verloren, bleibt aber über Bewertungsklasse, Warengruppe oder Lagerort auswertbar; eigene Bestandskonten je Materialart nur bei Bedarf anlegen. | M36: hoch | N36: korrigiert
A37: 300219 | B37: Material - Werbegeschenke < 35 EUR | C37: TBD | E37: Aktiva > B. Umlaufvermögen > I. Vorräte > 1. Roh-, Hilfs- und Betriebsstoffe [1041010] | G37: kein Mapping (TBD) | H37: kein Mapping (TBD) | I37: 13100000 | J37: Inventory - Raw Material | K37: Assets > Current Assets > Inventories | L37: Bisher ohne Zuordnung. Der Kunde führt Werbe- und Jubiläumsgeschenke als Lagerbestand unter RHB. Bestandskonto für Lagermaterial: Zielkonto muss in Inventories liegen. Neu Inventory - Raw Material als Bestandskonto für Roh-, Hilfs- und Betriebsstoffe. n:1: die Trennung nach Werkstatt/Materialart geht auf Kontenebene verloren, bleibt aber über Bewertungsklasse, Warengruppe oder Lagerort auswertbar; eigene Bestandskonten je Materialart nur bei Bedarf anlegen. Für Geschenke ist die steuerliche Trennung auf der Verbrauchsseite relevant (siehe 662xxx). | M37: mittel | N37: korrigiert
A38: 300239 | B38: Heizstoffe | C38: TBD | E38: Aktiva > B. Umlaufvermögen > I. Vorräte > 1. Roh-, Hilfs- und Betriebsstoffe [1041010] | G38: kein Mapping (TBD) | H38: kein Mapping (TBD) | I38: 13100000 | J38: Inventory - Raw Material | K38: Assets > Current Assets > Inventories | L38: Bisher ohne Zuordnung. Bestandskonto für Lagermaterial: Zielkonto muss in Inventories liegen. Neu Inventory - Raw Material als Bestandskonto für Roh-, Hilfs- und Betriebsstoffe. n:1: die Trennung nach Werkstatt/Materialart geht auf Kontenebene verloren, bleibt aber über Bewertungsklasse, Warengruppe oder Lagerort auswertbar; eigene Bestandskonten je Materialart nur bei Bedarf anlegen. | M38: hoch | N38: korrigiert
A39: 300249 | B39: Enteisungsmittel | C39: TBD | E39: Aktiva > B. Umlaufvermögen > I. Vorräte > 1. Roh-, Hilfs- und Betriebsstoffe [1041010] | G39: kein Mapping (TBD) | H39: kein Mapping (TBD) | I39: 13100000 | J39: Inventory - Raw Material | K39: Assets > Current Assets > Inventories | L39: Bisher ohne Zuordnung. Bestandskonto für Lagermaterial: Zielkonto muss in Inventories liegen. Neu Inventory - Raw Material als Bestandskonto für Roh-, Hilfs- und Betriebsstoffe. n:1: die Trennung nach Werkstatt/Materialart geht auf Kontenebene verloren, bleibt aber über Bewertungsklasse, Warengruppe oder Lagerort auswertbar; eigene Bestandskonten je Materialart nur bei Bedarf anlegen. | M39: hoch | N39: korrigiert
A40: 328000 | B40: Werbegeschenke (PR) | C40: TBD | E40: Aktiva > B. Umlaufvermögen > I. Vorräte > 1. Roh-, Hilfs- und Betriebsstoffe [1041010] | G40: kein Mapping (TBD) | H40: kein Mapping (TBD) | I40: 13100000 | J40: Inventory - Raw Material | K40: Assets > Current Assets > Inventories | L40: Bisher ohne Zuordnung. Der Kunde führt Werbe- und Jubiläumsgeschenke als Lagerbestand unter RHB. Bestandskonto für Lagermaterial: Zielkonto muss in Inventories liegen. Neu Inventory - Raw Material als Bestandskonto für Roh-, Hilfs- und Betriebsstoffe. n:1: die Trennung nach Werkstatt/Materialart geht auf Kontenebene verloren, bleibt aber über Bewertungsklasse, Warengruppe oder Lagerort auswertbar; eigene Bestandskonten je Materialart nur bei Bedarf anlegen. Für Geschenke ist die steuerliche Trennung auf der Verbrauchsseite relevant (siehe 662xxx). | M40: mittel | N40: korrigiert
A41: 328001 | B41: Werbegeschenke (Kleingeschenke) | C41: TBD | E41: Aktiva > B. Umlaufvermögen > I. Vorräte > 1. Roh-, Hilfs- und Betriebsstoffe [1041010] | G41: kein Mapping (TBD) | H41: kein Mapping (TBD) | I41: 13100000 | J41: Inventory - Raw Material | K41: Assets > Current Assets > Inventories | L41: Bisher ohne Zuordnung. Der Kunde führt Werbe- und Jubiläumsgeschenke als Lagerbestand unter RHB. Bestandskonto für Lagermaterial: Zielkonto muss in Inventories liegen. Neu Inventory - Raw Material als Bestandskonto für Roh-, Hilfs- und Betriebsstoffe. n:1: die Trennung nach Werkstatt/Materialart geht auf Kontenebene verloren, bleibt aber über Bewertungsklasse, Warengruppe oder Lagerort auswertbar; eigene Bestandskonten je Materialart nur bei Bedarf anlegen. Für Geschenke ist die steuerliche Trennung auf der Verbrauchsseite relevant (siehe 662xxx). | M41: mittel | N41: korrigiert
A42: 330000 | B42: Goldnadeln für Jubilare | C42: TBD | E42: Aktiva > B. Umlaufvermögen > I. Vorräte > 1. Roh-, Hilfs- und Betriebsstoffe [1041010] | G42: kein Mapping (TBD) | H42: kein Mapping (TBD) | I42: 13100000 | J42: Inventory - Raw Material | K42: Assets > Current Assets > Inventories | L42: Bisher ohne Zuordnung. Der Kunde führt Werbe- und Jubiläumsgeschenke als Lagerbestand unter RHB. Bestandskonto für Lagermaterial: Zielkonto muss in Inventories liegen. Neu Inventory - Raw Material als Bestandskonto für Roh-, Hilfs- und Betriebsstoffe. n:1: die Trennung nach Werkstatt/Materialart geht auf Kontenebene verloren, bleibt aber über Bewertungsklasse, Warengruppe oder Lagerort auswertbar; eigene Bestandskonten je Materialart nur bei Bedarf anlegen. Für Geschenke ist die steuerliche Trennung auf der Verbrauchsseite relevant (siehe 662xxx). | M42: mittel | N42: korrigiert
A43: 098000 | B43: Pauschalwertberichtigungen auf Forderungen | C43: 12401000 | D43: Einzelwertberichtigungen zu Forderungen | E43: Aktiva > B. Umlaufvermögen > II. Forderungen und sonstige VG > 1. Forderungen aus Lieferungen und Leistungen (Restlaufzeit ≤ 1 Jahr) [1042011] | F43: Assets > Current Assets > Accounts Receivable | G43: Abweichung | H43: OK | I43: 12401100 | J43: Allowance for Doubtful Receivables(Valuation) | K43: Assets > Current Assets > Accounts Receivable | L43: Bisher Einzelwertberichtigung; Pauschalwertberichtigung ist ein anderer Sachverhalt. Neu Allowance for Doubtful Receivables (Valuation), das Wertberichtigungskonto der pauschalen Forderungsbewertung, in Accounts Receivable. Ein ausdrücklich als Pauschalwertberichtigung bezeichnetes Bilanzkonto gibt es in [Y] nicht; 12400000 (in [X]: Zweifelhafte Forderungen) eignet sich nach der Bezeichnung eher für umgegliederte zweifelhafte Forderungen. Aufwandsseite: 62020000. | M43: mittel | N43: korrigiert
A44: 099009 | B44: Einzelwertberichtigungen zu Forderungen | C44: 12401000 | D44: Einzelwertberichtigungen zu Forderungen | E44: Aktiva > B. Umlaufvermögen > II. Forderungen und sonstige VG > 1. Forderungen aus Lieferungen und Leistungen (Restlaufzeit ≤ 1 Jahr) [1042011] | F44: Assets > Current Assets > Accounts Receivable | G44: OK | H44: OK | I44: 12401000 | J44: Einzelwertberichtigungen zu Forderungen / Individual Value Adjustments for Receivables | K44: Assets > Current Assets > Accounts Receivable | L44: Bezeichnung identisch, Bilanzposition Accounts Receivable passt. | M44: hoch | N44: unverändert
A45: 673506 | B45: Aufwand Mobilitätssachbezug für MWSt | C45: 66010000 | D45: Aufwand Abzinsung (ZKB) | E45: GuV > 7. Sonstige betriebliche Aufwendungen > Personalnebenkosten [3082034] | F45: Net Income > Operating Income > Operating Expense > Other Operating Expense | G45: Abweichung | H45: Abweichung | I45: 61010000 | J45: Sonstige Personalkosten / Payroll - Other Personnel Expenses | K45: Net Income > Operating Income > Operating Expense > Employee Expense > Payroll and Benefits > Payroll Other | L45: Bisher Aufwand Abzinsung (ZKB): falsch. Aufwand aus Mobilitätssachbezügen als Personalnebenkosten; neu Payroll - Other Personnel Expenses. Umsatzsteuerbezug der Sachbezüge und Gegenkonten 889002/889003 beachten. n:1 auf 61010000 Sonstige Personalkosten – Trennung nach Art der Leistung geht verloren (lohnsteuerliche Behandlung beachten). | M45: mittel | N45: korrigiert
A46: 140001 | B46: Forderungen aus L&L (Kred.Debitoren) | C46: 12530000 | D46: Forderungen aus Zahlungskarten | E46: Aktiva > B. Umlaufvermögen > II. Forderungen und sonstige VG > 1. Forderungen aus Lieferungen und Leistungen (Restlaufzeit ≤ 1 Jahr) [1042011] | F46: Assets > Current Assets > Accounts Receivable | G46: Abweichung | H46: OK | I46: 12102000 | J46: Receivables Domestic Adjustments | K46: Assets > Current Assets > Accounts Receivable | L46: Bisher Forderungen aus Zahlungskarten. Das Konto ist das Korrekturkonto für kreditorische Debitoren (Umgliederung zum Stichtag). Neu Receivables Domestic Adjustments in Accounts Receivable; Gegenseite der Umgliederung: 21180000 Customers with a Credit Balance. | M46: mittel | N46: korrigiert
A47: 140000 | B47: Forderungen aus Lieferungen und Leistungen | C47: 21725000 | D47: RechungsabgrenzPosten – Lieferungen und Leistungen | E47: Aktiva > B. Umlaufvermögen > II. Forderungen und sonstige VG > 1. Forderungen aus Lieferungen und Leistungen (Restlaufzeit ≤ 1 Jahr) [1042011] | F47: Liabilities and Equity > Liabilities > Non-Current Liabilities > Provisions | G47: Abweichung | H47: Abweichung | I47: 12100000 | J47: Receivables Domestic | K47: Assets > Current Assets > Accounts Receivable | L47: Bisher passiver Abgrenzungsposten (Provisions) für ein Forderungskonto. Neu Receivables Domestic (Abstimmkonto Debitoren Inland). Ausländische Debitoren (Airlines) laufen je Abstimmkonto über 12120000. | M47: hoch | N47: korrigiert
A48: 158011 | B48: VR Gepäckwägen | C48: 21700000 | D48: Konzernverbindlichkeiten | E48: Aktiva > B. Umlaufvermögen > II. Forderungen und sonstige VG > 1. Forderungen aus Lieferungen und Leistungen (Restlaufzeit ≤ 1 Jahr) [1042011] | F48: nicht in [Y] enthalten | G48: Abweichung | H48: Abweichung | I48: 12530000 | J48: Forderungen aus Zahlungskarten / Accounts Receivable - Payment Cards | K48: Assets > Current Assets > Accounts Receivable | L48: Bisher Konzernverbindlichkeiten (nicht in [Y]); kein Konzernbezug. Verrechnungskonto für Einnahmen Gepäckwagen, vom Kunden unter Forderungen aus L&L ausgewiesen. Für Verrechnungskonten ohne Kartenbezug gibt es in dieser Bilanzzeile kein passendes Konto: 12540000 Other Receivables bleibt den sonstigen Vermögensgegenständen vorbehalten (ein YCOA-Konto je Bilanzzeile des Kunden). Vorläufig 12530000 wie die übrigen Verrechnungskonten der Verkaufsstellen. Zu klären: Kartenabrechnung (dann 12530000) oder Umgliederung in die sonstigen Vermögensgegenstände (dann 12540000). | M48: niedrig | N48: manuell klären
A49: 158012 | B49: VR Parkautomaten / Concardis | C49: 11001030 | D49: Sonstige Zwischenbuchungen (Bar/Unterkonto) | E49: Aktiva > B. Umlaufvermögen > II. Forderungen und sonstige VG > 1. Forderungen aus Lieferungen und Leistungen (Restlaufzeit ≤ 1 Jahr) [1042011] | F49: Assets > Current Assets > Cash & Equivalents | G49: OK | H49: Abweichung | I49: 12530000 | J49: Forderungen aus Zahlungskarten / Accounts Receivable - Payment Cards | K49: Assets > Current Assets > Accounts Receivable | L49: Bezeichnung als Zwischenkonto plausibel, 11001030 liegt aber in Cash & Equivalents; der Kunde weist die Kartenverrechnung (Concardis/Kreditkarten) unter Forderungen aus L&L aus. Neu Accounts Receivable - Payment Cards in Accounts Receivable. n:1: Trennung je Verkaufsstelle/Acquirer geht verloren (Abstimmung der Kartenabrechnungen) – bei Bedarf über Zuordnung/Profitcenter oder eigene Konten. | M49: mittel | N49: korrigiert
A50: 158014 | B50: VR VIP / Concardis | C50: 11001030 | D50: Sonstige Zwischenbuchungen (Bar/Unterkonto) | E50: Aktiva > B. Umlaufvermögen > II. Forderungen und sonstige VG > 1. Forderungen aus Lieferungen und Leistungen (Restlaufzeit ≤ 1 Jahr) [1042011] | F50: Assets > Current Assets > Cash & Equivalents | G50: OK | H50: Abweichung | I50: 12530000 | J50: Forderungen aus Zahlungskarten / Accounts Receivable - Payment Cards | K50: Assets > Current Assets > Accounts Receivable | L50: Bezeichnung als Zwischenkonto plausibel, 11001030 liegt aber in Cash & Equivalents; der Kunde weist die Kartenverrechnung (Concardis/Kreditkarten) unter Forderungen aus L&L aus. Neu Accounts Receivable - Payment Cards in Accounts Receivable. n:1: Trennung je Verkaufsstelle/Acquirer geht verloren (Abstimmung der Kartenabrechnungen) – bei Bedarf über Zuordnung/Profitcenter oder eigene Konten. | M50: mittel | N50: korrigiert
A51: 158015 | B51: VR Lounges / Concardis | C51: 11001030 | D51: Sonstige Zwischenbuchungen (Bar/Unterkonto) | E51: Aktiva > B. Umlaufvermögen > II. Forderungen und sonstige VG > 1. Forderungen aus Lieferungen und Leistungen (Restlaufzeit ≤ 1 Jahr) [1042011] | F51: Assets > Current Assets > Cash & Equivalents | G51: OK | H51: Abweichung | I51: 12530000 | J51: Forderungen aus Zahlungskarten / Accounts Receivable - Payment Cards | K51: Assets > Current Assets > Accounts Receivable | L51: Bezeichnung als Zwischenkonto plausibel, 11001030 liegt aber in Cash & Equivalents; der Kunde weist die Kartenverrechnung (Concardis/Kreditkarten) unter Forderungen aus L&L aus. Neu Accounts Receivable - Payment Cards in Accounts Receivable. n:1: Trennung je Verkaufsstelle/Acquirer geht verloren (Abstimmung der Kartenabrechnungen) – bei Bedarf über Zuordnung/Profitcenter oder eigene Konten. | M51: mittel | N51: korrigiert
A52: 158016 | B52: VR Verkehrsleitung / Concardis | C52: 11001030 | D52: Sonstige Zwischenbuchungen (Bar/Unterkonto) | E52: Aktiva > B. Umlaufvermögen > II. Forderungen und sonstige VG > 1. Forderungen aus Lieferungen und Leistungen (Restlaufzeit ≤ 1 Jahr) [1042011] | F52: Assets > Current Assets > Cash & Equivalents | G52: OK | H52: Abweichung | I52: 12530000 | J52: Forderungen aus Zahlungskarten / Accounts Receivable - Payment Cards | K52: Assets > Current Assets > Accounts Receivable | L52: Bezeichnung als Zwischenkonto plausibel, 11001030 liegt aber in Cash & Equivalents; der Kunde weist die Kartenverrechnung (Concardis/Kreditkarten) unter Forderungen aus L&L aus. Neu Accounts Receivable - Payment Cards in Accounts Receivable. n:1: Trennung je Verkaufsstelle/Acquirer geht verloren (Abstimmung der Kartenabrechnungen) – bei Bedarf über Zuordnung/Profitcenter oder eigene Konten. | M52: mittel | N52: korrigiert
A53: 158017 | B53: VR MOS Kreditkarten/Giro | C53: 11001030 | D53: Sonstige Zwischenbuchungen (Bar/Unterkonto) | E53: Aktiva > B. Umlaufvermögen > II. Forderungen und sonstige VG > 1. Forderungen aus Lieferungen und Leistungen (Restlaufzeit ≤ 1 Jahr) [1042011] | F53: Assets > Current Assets > Cash & Equivalents | G53: OK | H53: Abweichung | I53: 12530000 | J53: Forderungen aus Zahlungskarten / Accounts Receivable - Payment Cards | K53: Assets > Current Assets > Accounts Receivable | L53: Bezeichnung als Zwischenkonto plausibel, 11001030 liegt aber in Cash & Equivalents; der Kunde weist die Kartenverrechnung (Concardis/Kreditkarten) unter Forderungen aus L&L aus. Neu Accounts Receivable - Payment Cards in Accounts Receivable. n:1: Trennung je Verkaufsstelle/Acquirer geht verloren (Abstimmung der Kartenabrechnungen) – bei Bedarf über Zuordnung/Profitcenter oder eigene Konten. | M53: mittel | N53: korrigiert
A54: 158022 | B54: VR Fundbüro | C54: 21700000 | D54: Konzernverbindlichkeiten | E54: Aktiva > B. Umlaufvermögen > II. Forderungen und sonstige VG > 1. Forderungen aus Lieferungen und Leistungen (Restlaufzeit ≤ 1 Jahr) [1042011] | F54: nicht in [Y] enthalten | G54: Abweichung | H54: Abweichung | I54: 12530000 | J54: Forderungen aus Zahlungskarten / Accounts Receivable - Payment Cards | K54: Assets > Current Assets > Accounts Receivable | L54: Bisher Konzernverbindlichkeiten (nicht in [Y]); kein Konzernbezug. Verrechnungskonto Fundbüro, vom Kunden unter Forderungen aus L&L ausgewiesen. Für Verrechnungskonten ohne Kartenbezug gibt es in dieser Bilanzzeile kein passendes Konto: 12540000 Other Receivables bleibt den sonstigen Vermögensgegenständen vorbehalten (ein YCOA-Konto je Bilanzzeile des Kunden). Vorläufig 12530000 wie die übrigen Verrechnungskonten der Verkaufsstellen. Zu klären: Umgliederung in die sonstigen Vermögensgegenstände (dann 12540000). | M54: niedrig | N54: manuell klären
... A70: 192450 | B70: VR - FDEG - Ergebnisabführung | C70: 29110000 | D70: Sonstige Verbindlichkeiten, Restlaufz. 1-5 Jahre | E70: Aktiva > B. Umlaufvermögen > II. Forderungen und sonstige VG > 2. Forderungen gegen verbundene Unternehmen (saldiert: FD Energie) [1042031/06] | F70: Liabilities and Equity > Liabilities > Current Liabilities > Accounts Payable | G70: Abweichung | H70: Abweichung | I70: 12303000 | J70: Receivables vs affil. Companies (no recon acct) | K70: Assets > Current Assets > Accounts Receivable | L70: Bisher Sonstige Verbindlichkeiten mit Restlaufzeit 1-5 Jahre: der Anspruch aus Gewinnabführung FDEG ist eine kurzfristige Forderung gegen ein verbundenes Unternehmen. Einheitliche Regel für alle Verrechnungskonten der FDG mit verbundenen Unternehmen (Verrechnung, Cash-Pooling, Ergebnisabführung): Receivables vs affil. Companies (no recon acct); Habensalden werden über 21303000 Payables vs affiliated Companies (no recon acct) ausgewiesen. n:1: die Trennung Cash-Pooling / Verrechnung / Ergebnisabführung geht verloren (Zinsberechnung, Abstimmung) – eigene Konten prüfen; Gesellschaft über Partnergesellschaft. Der Kunde saldiert Forderungen, Verbindlichkeiten, Cash-Pooling und Verrechnung je verbundenem Unternehmen in einer Position; der SAP-Standard weist unsaldiert aus. | M70: mittel | N70: korrigiert
A71: 159219 | B71: Forderungen gegen SITA Airport IT GmbH | C71: 12110000 | D71: Forderungen Inland (laut [Y]: Other Down Payments Made Current Assets) | E71: Aktiva > B. Umlaufvermögen > II. Forderungen und sonstige VG > 3. Forderungen gegen Unternehmen mit Beteiligungsverhältnis [1042041] | F71: Assets > Current Assets > Inventories | G71: Abweichung | H71: Abweichung | L71: Bisher 12110000, in [X] als Forderungen Inland bezeichnet, laut [Y] aber Other Down Payments Made Current Assets (Inventories). Für Forderungen gegen Unternehmen mit Beteiligungsverhältnis (§ 266 Abs. 2 B.II.3 HGB, Pflichtausweis) gibt es in [Y] kein eigenes Abstimmkonto. Neuanlage prüfen (Kopiervorlage 12300000). Rückfall: 12100000 mit Verlust des gesonderten Ausweises. | M71: hoch | N71: Neuanlage prüfen
A72: 159224 | B72: Ford. gegen Swissport DUS Cargo Services GmbH | C72: 12110000 | D72: Forderungen Inland (laut [Y]: Other Down Payments Made Current Assets) | E72: Aktiva > B. Umlaufvermögen > II. Forderungen und sonstige VG > 3. Forderungen gegen Unternehmen mit Beteiligungsverhältnis [1042041] | F72: Assets > Current Assets > Inventories | G72: Abweichung | H72: Abweichung | L72: Bisher 12110000, in [X] als Forderungen Inland bezeichnet, laut [Y] aber Other Down Payments Made Current Assets (Inventories). Für Forderungen gegen Unternehmen mit Beteiligungsverhältnis (§ 266 Abs. 2 B.II.3 HGB, Pflichtausweis) gibt es in [Y] kein eigenes Abstimmkonto. Neuanlage prüfen (Kopiervorlage 12300000). Rückfall: 12100000 mit Verlust des gesonderten Ausweises. | M72: hoch | N72: Neuanlage prüfen
A73: 151009 | B73: Forderungen aus Arbeitgeberdarlehen . | C73: 12110000 | D73: Forderungen Inland (laut [Y]: Other Down Payments Made Current Assets) | E73: Aktiva > B. Umlaufvermögen > II. Forderungen und sonstige VG > 4. Sonstige Vermögensgegenstände (Restlaufzeit ≤ 1 Jahr) [1042051] | F73: Assets > Current Assets > Inventories | G73: Abweichung | H73: Abweichung | I73: 12540000 | J73: Other Receivables (no recon acct) | K73: Assets > Current Assets > Accounts Receivable | L73: Bisher 12110000, in [X] als Forderungen Inland bezeichnet, laut [Y] aber Other Down Payments Made Current Assets (Inventories). Kurzfristiger Teil der Arbeitgeberdarlehen unter Sonstige Vermögensgegenstände; 14107000 Loans to Staff liegt in Long-Term Investments und passt für den kurzfristigen Ausweis nicht. Neu Other Receivables (no recon acct). | M73: mittel | N73: korrigiert
A74: 151019 | B74: Lohn-u. Gehaltsüberzahlung | C74: 15200000 | D74: Lohn- und Gehaltsvorschüsse | E74: Aktiva > B. Umlaufvermögen > II. Forderungen und sonstige VG > 4. Sonstige Vermögensgegenstände (Restlaufzeit ≤ 1 Jahr) [1042051] | F74: Assets > Current Assets > Accounts Receivable | G74: Abweichung | H74: OK | I74: 12542000 | J74: Receivables from Employees Overpay (no recon acct) | K74: Assets > Current Assets > Accounts Receivable | L74: Bisher Lohn- und Gehaltsvorschüsse; Überzahlung ist ein anderer Sachverhalt, für den [Y] ein eigenes Konto führt. Neu Receivables from Employees Overpay (no recon acct) in Accounts Receivable. | M74: hoch | N74: korrigiert
A75: 151109 | B75: Sonstige Forderungen Mitarbeiter / durchl. Posten | C75: 12110000 | D75: Forderungen Inland (laut [Y]: Other Down Payments Made Current Assets) | E75: Aktiva > B. Umlaufvermögen > II. Forderungen und sonstige VG > 4. Sonstige Vermögensgegenstände (Restlaufzeit ≤ 1 Jahr) [1042051] | F75: Assets > Current Assets > Inventories | G75: Abweichung | H75: Abweichung | I75: 12540000 | J75: Other Receivables (no recon acct) | K75: Assets > Current Assets > Accounts Receivable | L75: Bisher 12110000, in [X] als Forderungen Inland bezeichnet, laut [Y] aber Other Down Payments Made Current Assets (Inventories). Neu Other Receivables (no recon acct); kein spezifisches Konto für sonstige Mitarbeiterforderungen/durchlaufende Posten. | M75: mittel | N75: korrigiert
A76: 151119 | B76: Kurzfr. Ford. aus Lohn/Gehaltsvorschüssen | C76: 12110000 | D76: Forderungen Inland (laut [Y]: Other Down Payments Made Current Assets) | E76: Aktiva > B. Umlaufvermögen > II. Forderungen und sonstige VG > 4. Sonstige Vermögensgegenstände (Restlaufzeit ≤ 1 Jahr) [1042051] | F76: Assets > Current Assets > Inventories | G76: Abweichung | H76: Abweichung | I76: 15200000 | J76: Lohn- und Gehaltsvorschüsse / Salary and Wages Advances | K76: Assets > Current Assets > Accounts Receivable | L76: Bisher 12110000, in [X] als Forderungen Inland bezeichnet, laut [Y] aber Other Down Payments Made Current Assets (Inventories). Neu Salary and Wages Advances (Lohn- und Gehaltsvorschüsse) in Accounts Receivable. | M76: hoch | N76: korrigiert
A77: 151129 | B77: Kurzfr. Ford. aus Lohn/Gehaltsabschlägen | C77: 12110000 | D77: Forderungen Inland (laut [Y]: Other Down Payments Made Current Assets) | E77: Aktiva > B. Umlaufvermögen > II. Forderungen und sonstige VG > 4. Sonstige Vermögensgegenstände (Restlaufzeit ≤ 1 Jahr) [1042051] | F77: Assets > Current Assets > Inventories | G77: Abweichung | H77: Abweichung | I77: 15200000 | J77: Lohn- und Gehaltsvorschüsse / Salary and Wages Advances | K77: Assets > Current Assets > Accounts Receivable | L77: Bisher 12110000, in [X] als Forderungen Inland bezeichnet, laut [Y] aber Other Down Payments Made Current Assets (Inventories). Abschlagszahlungen sind Vorauszahlungen auf Lohn/Gehalt; neu Salary and Wages Advances. n:1 mit 151119. | M77: mittel | N77: korrigiert
A78: 157009 | B78: Sonstige Forderungen . | C78: 12110000 | D78: Forderungen Inland (laut [Y]: Other Down Payments Made Current Assets) | E78: Aktiva > B. Umlaufvermögen > II. Forderungen und sonstige VG > 4. Sonstige Vermögensgegenstände (Restlaufzeit ≤ 1 Jahr) [1042051] | F78: Assets > Current Assets > Inventories | G78: Abweichung | H78: Abweichung | I78: 12540000 | J78: Other Receivables (no recon acct) | K78: Assets > Current Assets > Accounts Receivable | L78: Bisher 12110000, in [X] als Forderungen Inland bezeichnet, laut [Y] aber Other Down Payments Made Current Assets (Inventories). Neu Other Receivables (no recon acct) in Accounts Receivable. | M78: hoch | N78: korrigiert
A79: 157100 | B79: Sonstige Forderungen (incl. Debit. Kreditoren) | C79: 12110000 | D79: Forderungen Inland (laut [Y]: Other Down Payments Made Current Assets) | E79: Aktiva > B. Umlaufvermögen > II. Forderungen und sonstige VG > 4. Sonstige Vermögensgegenstände (Restlaufzeit ≤ 1 Jahr) [1042051] | F79: Assets > Current Assets > Inventories | G79: Abweichung | H79: Abweichung | I79: 12540000 | J79: Other Receivables (no recon acct) | K79: Assets > Current Assets > Accounts Receivable | L79: Bisher 12110000, in [X] als Forderungen Inland bezeichnet, laut [Y] aber Other Down Payments Made Current Assets (Inventories). Neu Other Receivables (no recon acct). 1:n beachten: der Anteil debitorische Kreditoren wird in YCOA über 12590000 Vendors with a Debit Balance umgegliedert. | M79: mittel | N79: korrigiert
A80: 157920 | B80: Sonst. Forderungen aus überzahlter KSt. | C80: 12110000 | D80: Forderungen Inland (laut [Y]: Other Down Payments Made Current Assets) | E80: Aktiva > B. Umlaufvermögen > II. Forderungen und sonstige VG > 4. Sonstige Vermögensgegenstände (Restlaufzeit ≤ 1 Jahr) [1042051] | F80: Assets > Current Assets > Inventories | G80: Abweichung | H80: Abweichung | I80: 12541000 | J80: Receivables from Tax Authorities (no recon acct) | K80: Assets > Current Assets > Other Current Assets | L80: Bisher 12110000, in [X] als Forderungen Inland bezeichnet, laut [Y] aber Other Down Payments Made Current Assets (Inventories). Erstattungsanspruch Körperschaftsteuer: neu Receivables from Tax Authorities (no recon acct). Das Konto liegt in Other Current Assets, was dem Kundenausweis Sonstige Vermögensgegenstände sinngemäß entspricht. | M80: hoch | N80: korrigiert
A81: 174200 | B81: FA-Dus-Nord - Umsatzsteuer | C81: 22006012 | D81: Gezahlte Umsatzsteuer | E81: Aktiva > B. Umlaufvermögen > II. Forderungen und sonstige VG > 4. Sonstige Vermögensgegenstände (Restlaufzeit ≤ 1 Jahr) [1042051] | F81: nicht in [Y] enthalten | G81: Abweichung | H81: Abweichung | I81: 22090000 | J81: Alterative Tax Payable - UMS | K81: Assets > Current Assets > Other Current Assets | L81: Bisher Gezahlte Umsatzsteuer (nicht in [Y], vermutlich Länderversion). Das Kundenkonto ist das Verrechnungskonto Umsatzsteuer mit dem Finanzamt (Zahllast/Erstattung). Neu Alterative Tax Payable - UMS (Zahllastkonto der Umsatzsteuer-Voranmeldung) in Other Current Assets. Bei Zahllast (Habensaldo) weist der Kunde unter sonstige Verbindlichkeiten aus Steuern aus; das Konto bleibt im SAP-Standard in Other Current Assets. Alternative bei reinem Forderungscharakter: 12541000. | M81: mittel | N81: korrigiert
A82: 157300 | B82: Steuerschuld gg.Zoll | C82: 12402000 | D82: Wertberichtigungen zu Forderungen gg. Verbundene | E82: Aktiva > B. Umlaufvermögen > II. Forderungen und sonstige VG > 4. Sonstige Vermögensgegenstände (Steuerverrechnung Zoll/Stromsteuer, saldoabhängig) [1042052] | Passiva > E. Verbindlichkeiten > 7. Sonstige Verbindlichkeiten > aus Steuern (Steuerverrechnung Zoll/Stromsteuer, saldoabhängig) [2048038] | F82: Assets > Current Assets > Notes Receivable | G82: Abweichung | H82: Abweichung | I82: 21538000 | J82: Sonstige Steuer - zu zahlen | K82: nicht in [Y] enthalten (Konto nur aus [X]) | L82: Bisher Wertberichtigung auf Forderungen gegen Verbundene: falsch. Das Konto ist eine Steuerschuld gegenüber dem Zoll (Strom-/Energiesteuer) und steht in [Z] saldoabhängig auf beiden Bilanzseiten (1042052 und 2048038, gemeinsam mit 195500). In [Y] gibt es kein Konto für Verbindlichkeiten aus sonstigen Steuern. Vorläufig 21538000 Sonstige Steuer - zu zahlen aus [X]: nicht in [Y], Bilanzposition daher nicht belegbar – Anlage im Buchungskreis und Zuordnung zu Other Payable erforderlich, sonst Neuanlage. Rückfall: 21720000. | M82: niedrig | N82: manuell klären
A83: 195500 | B83: VR - Stromsteuer | C83: 21700000 | D83: (in [X] ohne Bezeichnung; sonst in [X]: Konzernverbindlichkeiten) | E83: Aktiva > B. Umlaufvermögen > II. Forderungen und sonstige VG > 4. Sonstige Vermögensgegenstände (Steuerverrechnung Zoll/Stromsteuer, saldoabhängig) [1042052] | Passiva > E. Verbindlichkeiten > 7. Sonstige Verbindlichkeiten > aus Steuern (Steuerverrechnung Zoll/Stromsteuer, saldoabhängig) [2048038] | F83: nicht in [Y] enthalten | G83: Abweichung | H83: Abweichung | I83: 12541000 | J83: Receivables from Tax Authorities (no recon acct) | K83: Assets > Current Assets > Other Current Assets | L83: Bisher 21700000 (in [X] ohne Bezeichnung, nicht in [Y]). Verrechnungskonto Stromsteuer mit Sollsaldo (Vorauszahlungen); neu Receivables from Tax Authorities (no recon acct) in Other Current Assets. In [Z] zusammen mit 157300 saldoabhängig auf beiden Bilanzseiten ausgewiesen. | M83: mittel | N83: korrigiert
A84: 194500 | B84: VR - Hausgeld Niederrheinstr. 185 | C84: 21700000 | D84: (in [X] ohne Bezeichnung; sonst in [X]: Konzernverbindlichkeiten) | E84: Aktiva > B. Umlaufvermögen > II. Forderungen und sonstige VG > 4. Sonstige Vermögensgegenstände (übrige Verrechnungskonten) [1042054] | F84: nicht in [Y] enthalten | G84: Abweichung | H84: Abweichung | I84: 12540000 | J84: Other Receivables (no recon acct) | K84: Assets > Current Assets > Accounts Receivable | L84: Bisher 21700000 (in [X] ohne Bezeichnung, nicht in [Y]). Verrechnungskonto Hausgeld mit Sollsaldo unter Sonstige Vermögensgegenstände; neu Other Receivables (no recon acct). | M84: mittel | N84: korrigiert
... A108: 091000 | B108: Aktive Rechnungsabgrenzung | C108: 12561000 | D108: Aktive Rechnungsabgrenzung | E108: Aktiva > C. Rechnungsabgrenzungsposten [1062000] | F108: Assets > Current Assets > Other Current Assets | G108: OK | H108: OK | I108: 12561000 | J108: Aktive Rechnungsabgrenzung / Prepaid Expenses | K108: Assets > Current Assets > Other Current Assets | L108: Bezeichnung identisch, Position Other Current Assets entspricht dem aktiven Rechnungsabgrenzungsposten (in [X] mit Status TBD hinterlegt – bestätigt). | M108: hoch | N108: unverändert
A109: 064110 | B109: Aktivposten Ausfinanzerung ATZ | C109: TBD | E109: Aktiva > D. Aktiver Unterschiedsbetrag aus der Vermögensverrechnung [1080000] | G109: kein Mapping (TBD) | H109: kein Mapping (TBD) | L109: Bisher ohne Zuordnung. Aktiver Unterschiedsbetrag aus der Vermögensverrechnung (§ 246 Abs. 2 HGB, Deckungsvermögen Altersteilzeit): weder ein passendes YCOA-Konto noch eine entsprechende Position im SAP-Standard vorhanden. Neuanlage und eigene Bilanzposition prüfen. | M109: hoch | N109: Neuanlage prüfen
A110: 140010 | B110: Forderungen aus Lieferungen und Leistungen | C110: 21725000 | D110: RechungsabgrenzPosten – Lieferungen und Leistungen | E110: Aktiva > B. Umlaufvermögen > II. Forderungen und sonstige VG > 1. Forderungen aus Lieferungen und Leistungen (Restlaufzeit ≤ 1 Jahr) [1042011] | F110: Liabilities and Equity > Liabilities > Non-Current Liabilities > Provisions | G110: Abweichung | H110: Abweichung | I110: 12100000 | J110: Receivables Domestic | K110: Assets > Current Assets > Accounts Receivable | L110: Bisher passiver Abgrenzungsposten (Provisions) für ein Forderungskonto. Neu Receivables Domestic. n:1 mit 140000: Abgrenzung der beiden Kundenkonten klären (zweites Abstimmkonto?); bei Auslandsdebitoren 12120000. | M110: mittel | N110: korrigiert
A111: 080000 | B111: Gezeichnetes Kapital | C111: 32100000 | D111: Eingezahltes Kapital aus eigenen Anteilen | E111: Passiva > A. Eigenkapital > I. Gezeichnetes Kapital [2011000] | F111: Liabilities and Equity > Equity > Equity - Reserve Accounts | G111: Abweichung | H111: Abweichung | I111: 31000000 | J111: Common Stock | K111: Liabilities and Equity > Equity > Equity - Subscribed Capital | L111: Bisher Eingezahltes Kapital aus eigenen Anteilen (Equity - Reserve Accounts): anderer Sachverhalt und andere Position. Neu Common Stock (gezeichnetes Kapital) in Equity - Subscribed Capital. | M111: hoch | N111: korrigiert
A112: 080010 | B112: Kapitalrücklage | C112: 24098300 | D112: Kapitalrücklage | E112: Passiva > A. Eigenkapital > II. Kapitalrücklage [2012000] | F112: Liabilities and Equity > Equity > Equity - Reserve Accounts | G112: OK | H112: OK | I112: 24098300 | J112: Kapitalrücklage / Capital Reserve | K112: Liabilities and Equity > Equity > Equity - Reserve Accounts | L112: Bezeichnung identisch (Kapitalrücklage), Position Equity - Reserve Accounts passt. | M112: hoch | N112: unverändert
A113: 093000 | B113: Rücklagen - zur Ausschüttung gesperrt | C113: 24098200 | D113: Gewinnrücklagen | E113: Passiva > A. Eigenkapital > III. Gewinnrücklagen (andere Gewinnrücklagen) [2013000] | F113: nicht in [Y] enthalten | G113: OK | H113: Abweichung | I113: 24098600 | J113: Other Reserves | K113: Liabilities and Equity > Equity > Equity - Reserve Accounts | L113: Bezeichnung Gewinnrücklagen passt, 24098200 ist aber in [Y] nicht vorhanden. Neu Other Reserves (andere Rücklagen) in Equity - Reserve Accounts, entsprechend dem Kundenausweis andere Gewinnrücklagen. n:1: die Trennung der drei Rücklagen (ausschüttungsgesperrt, Investitionszulage, Abzugsbeträge) geht verloren – für die Ausschüttungssperre relevant, eigene Konten prüfen. | M113: mittel | N113: korrigiert
A114: 094000 | B114: Rücklagen aus Invest.-Zul.-Gesetz . | C114: 24098200 | D114: Gewinnrücklagen | E114: Passiva > A. Eigenkapital > III. Gewinnrücklagen (andere Gewinnrücklagen) [2013000] | F114: nicht in [Y] enthalten | G114: OK | H114: Abweichung | I114: 24098600 | J114: Other Reserves | K114: Liabilities and Equity > Equity > Equity - Reserve Accounts | L114: Bezeichnung Gewinnrücklagen passt, 24098200 ist aber in [Y] nicht vorhanden. Neu Other Reserves (andere Rücklagen) in Equity - Reserve Accounts, entsprechend dem Kundenausweis andere Gewinnrücklagen. n:1: die Trennung der drei Rücklagen (ausschüttungsgesperrt, Investitionszulage, Abzugsbeträge) geht verloren – für die Ausschüttungssperre relevant, eigene Konten prüfen. | M114: mittel | N114: korrigiert
A115: 094010 | B115: Rücklagen Abzugsbeträge für Azubi . | C115: 24098200 | D115: Gewinnrücklagen | E115: Passiva > A. Eigenkapital > III. Gewinnrücklagen (andere Gewinnrücklagen) [2013000] | F115: nicht in [Y] enthalten | G115: OK | H115: Abweichung | I115: 24098600 | J115: Other Reserves | K115: Liabilities and Equity > Equity > Equity - Reserve Accounts | L115: Bezeichnung Gewinnrücklagen passt, 24098200 ist aber in [Y] nicht vorhanden. Neu Other Reserves (andere Rücklagen) in Equity - Reserve Accounts, entsprechend dem Kundenausweis andere Gewinnrücklagen. n:1: die Trennung der drei Rücklagen (ausschüttungsgesperrt, Investitionszulage, Abzugsbeträge) geht verloren – für die Ausschüttungssperre relevant, eigene Konten prüfen. | M115: mittel | N115: korrigiert
A116: 080200 | B116: Gewinn- und Verlustvortrag | C116: 90002000 | D116: Abgegrenzter Verlustvortrag | E116: Passiva > A. Eigenkapital > IV. Gewinn-/Verlustvortrag [2014000] | F116: Not assigned (in FPA1 keiner Position zugeordnet) | G116: Abweichung | H116: Abweichung | I116: 33000000 | J116: Retained Earnings | K116: Liabilities and Equity > Equity > Equity - Subscribed Capital | L116: Bisher Abgegrenzter Verlustvortrag (steuerlicher Verlustvortrag, in FPA1 nicht zugeordnet): anderer Sachverhalt. Neu Retained Earnings (Ergebnisvortragskonto), das in FPA1 unter Equity - Subscribed Capital geführt wird. | M116: hoch | N116: korrigiert
A117: 781200 | B117: KALK. ZINSEN | C117: 64060000 | D117: Kalkulatorische Zinsen (CO) | E117: Außerhalb GuV > Verrechnung kalkulatorische Kosten (Saldo null) [9020000] | F117: Not assigned (in FPA1 keiner Position zugeordnet) | G117: OK | H117: OK | I117: 64060000 | J117: Kalkulatorische Zinsen (CO) / Accrued interest (CO) | K117: Not assigned (in FPA1 keiner Position zugeordnet) | L117: Bezeichnung passt (Kalkulatorische Zinsen). n:1: die Trennung nach Anlagengruppe geht verloren (Entgeltkalkulation). Kalkulatorische Konten stehen beim Kunden außerhalb der GuV (Saldo null) und im SAP-Standard außerhalb der Bilanzstruktur (Not assigned) – sinngemäß gleiche Position. Das Kalkulatorik-Konzept (Bewertungsbereich der Anlagenbuchhaltung, Ledger) ist gesondert festzulegen. | M117: mittel | N117: unverändert
A118: 094045 | B118: Zuschussrücklage Bundespolizei | C118: 24098400 | D118: Gesetzliche Rücklage | E118: Passiva > B. Sonderposten für Investitionszuschüsse zu Sachanlagen [2024000] | F118: Liabilities and Equity > Equity > Equity - Reserve Accounts | G118: Abweichung | H118: Abweichung | L118: Bisher Gesetzliche Rücklage (Eigenkapital); ein Sonderposten für Investitionszuschüsse ist kein Eigenkapital. In [Y] existiert weder ein Konto noch eine Bilanzposition für Sonderposten. Neuanlage und eigene Bilanzposition zwischen Eigenkapital und Rückstellungen prüfen; ein Rückfall auf Eigenkapital- oder Rückstellungskonten wäre ein Fehlausweis. | M118: hoch | N118: Neuanlage prüfen
A119: 094080 | B119: Zuschussrücklage Sky Train | C119: 24098400 | D119: Gesetzliche Rücklage | E119: Passiva > B. Sonderposten für Investitionszuschüsse zu Sachanlagen [2024000] | F119: Liabilities and Equity > Equity > Equity - Reserve Accounts | G119: Abweichung | H119: Abweichung | L119: Bisher Gesetzliche Rücklage (Eigenkapital); ein Sonderposten für Investitionszuschüsse ist kein Eigenkapital. In [Y] existiert weder ein Konto noch eine Bilanzposition für Sonderposten. Neuanlage und eigene Bilanzposition zwischen Eigenkapital und Rückstellungen prüfen; ein Rückfall auf Eigenkapital- oder Rückstellungskonten wäre ein Fehlausweis. | M119: hoch | N119: Neuanlage prüfen
A120: 094090 | B120: Zuschussrücklage Check-In-Halle | C120: 24098400 | D120: Gesetzliche Rücklage | E120: Passiva > B. Sonderposten für Investitionszuschüsse zu Sachanlagen [2024000] | F120: Liabilities and Equity > Equity > Equity - Reserve Accounts | G120: Abweichung | H120: Abweichung | L120: Bisher Gesetzliche Rücklage (Eigenkapital); ein Sonderposten für Investitionszuschüsse ist kein Eigenkapital. In [Y] existiert weder ein Konto noch eine Bilanzposition für Sonderposten. Neuanlage und eigene Bilanzposition zwischen Eigenkapital und Rückstellungen prüfen; ein Rückfall auf Eigenkapital- oder Rückstellungskonten wäre ein Fehlausweis. | M120: hoch | N120: Neuanlage prüfen
A121: 094020 | B121: Sopo Parkhäuser | C121: TBD | E121: Passiva > C. Sonderposten mit Rücklageanteil [2021003] | G121: kein Mapping (TBD) | H121: kein Mapping (TBD) | L121: Bisher ohne Zuordnung. Sonderposten mit Rücklageanteil. In [Y] existiert weder ein Konto noch eine Bilanzposition für Sonderposten. Neuanlage und eigene Bilanzposition zwischen Eigenkapital und Rückstellungen prüfen; ein Rückfall auf Eigenkapital- oder Rückstellungskonten wäre ein Fehlausweis. | M121: hoch | N121: Neuanlage prüfen
A122: 094021 | B122: §6b Rücklage BISAWA | C122: 24098300 | D122: Kapitalrücklage | E122: Passiva > C. Sonderposten mit Rücklageanteil [2021003] | F122: Liabilities and Equity > Equity > Equity - Reserve Accounts | G122: Abweichung | H122: Abweichung | L122: Bisher Kapitalrücklage (Eigenkapital); die § 6b-Rücklage ist ein Sonderposten mit Rücklageanteil. In [Y] existiert weder ein Konto noch eine Bilanzposition für Sonderposten. Neuanlage und eigene Bilanzposition zwischen Eigenkapital und Rückstellungen prüfen; ein Rückfall auf Eigenkapital- oder Rückstellungskonten wäre ein Fehlausweis. | M122: hoch | N122: Neuanlage prüfen
A123: 096000 | B123: Rückstellung für Versorgungszusagen | C123: 21770000 | D123: Bonusrückstellung | E123: Passiva > D. Rückstellungen > 1. Rückstellungen für Pensionen und ähnliche Verpflichtungen [2031000] | F123: Liabilities and Equity > Liabilities > Non-Current Liabilities > Provisions | G123: Abweichung | H123: OK | I123: 24031000 | J123: Rückst. für Pensionen und ähnliche Verpflichtungen / Pension Provision | K123: Liabilities and Equity > Liabilities > Non-Current Liabilities > Provisions | L123: Bisher Bonusrückstellung (Accrued Volume Rebate, Kundenboni): anderer Sachverhalt. Neu Pension Provision (Rückstellungen für Pensionen und ähnliche Verpflichtungen) in Provisions. | M123: hoch | N123: korrigiert
A124: 096100 | B124: Rückstellung für Beihilfezahlungen | C124: 21770000 | D124: Bonusrückstellung | E124: Passiva > D. Rückstellungen > 1. Rückstellungen für Pensionen und ähnliche Verpflichtungen [2031000] | F124: Liabilities and Equity > Liabilities > Non-Current Liabilities > Provisions | G124: Abweichung | H124: OK | I124: 24031000 | J124: Rückst. für Pensionen und ähnliche Verpflichtungen / Pension Provision | K124: Liabilities and Equity > Liabilities > Non-Current Liabilities > Provisions | L124: Bisher Bonusrückstellung (Kundenboni): anderer Sachverhalt. Beihilfeverpflichtungen zählt der Kunde zu den pensionsähnlichen Verpflichtungen; neu Pension Provision. n:1 mit 096000 (Versorgungszusagen/Beihilfe nicht mehr getrennt). | M124: mittel | N124: korrigiert
A125: 095100 | B125: Rückstellung für Gewerbesteuer | C125: 24032000 | D125: Rückstellungen Gewerbesteuer | E125: Passiva > D. Rückstellungen > 2. Steuerrückstellungen [2033000] | F125: Liabilities and Equity > Liabilities > Non-Current Liabilities > Provisions | G125: OK | H125: OK | I125: 24032000 | J125: Rückstellungen Gewerbesteuer / Trade Tax Provision | K125: Liabilities and Equity > Liabilities > Non-Current Liabilities > Provisions | L125: Bezeichnung und Position (Provisions) passen. | M125: hoch | N125: unverändert
A126: 095300 | B126: RUECKSTELLUNG FUER UMSATZSTEUER | C126: 22006012 | D126: Gezahlte Umsatzsteuer | E126: Passiva > D. Rückstellungen > 2. Steuerrückstellungen [2033000] | F126: nicht in [Y] enthalten | G126: Abweichung | H126: Abweichung | I126: 24030000 | J126: Tax Provisions | K126: Liabilities and Equity > Liabilities > Non-Current Liabilities > Provisions | L126: Bisher Gezahlte Umsatzsteuer (nicht in [Y]); eine Rückstellung ist kein Steuerverrechnungskonto. Neu Tax Provisions (allgemeine Steuerrückstellungen) in Provisions; ein eigenes Konto für Umsatzsteuerrückstellungen gibt es nicht. | M126: mittel | N126: korrigiert
A127: 097060 | B127: Rückstellung für Aussenwohnbereichsentschädigung | C127: 24031100 | D127: Pensionsrückstellung - ledgerspezifisch | E127: Passiva > D. Rückstellungen > 3. Sonstige Rückstellungen (Lärmschutzmaßnahmen) [2034001] | F127: Liabilities and Equity > Liabilities > Non-Current Liabilities > Provisions | G127: Abweichung | H127: OK | I127: 24090000 | J127: Sonstige Rückstellungen / Other Provisions | K127: Liabilities and Equity > Liabilities > Non-Current Liabilities > Provisions | L127: Bisher Pensionsrückstellung (ledgerspezifisch): anderer Sachverhalt. Neu Other Provisions. n:1: 24090000 wird zum Sammelkonto für die sonstigen Rückstellungen; die Trennung nach Rückstellungsart geht verloren (Rückstellungsspiegel) – eigene Konten je wesentlicher Rückstellungsart prüfen. | M127: mittel | N127: korrigiert
A128: 097070 | B128: Rückstellung für Auflagen gem. Betriebsgenehmigung | C128: 21501200 | D128: Rückstellung für 13. Monatsgehalt | E128: Passiva > D. Rückstellungen > 3. Sonstige Rückstellungen (Lärmschutzmaßnahmen) [2034001] | F128: nicht in [Y] enthalten | G128: Abweichung | H128: Abweichung | I128: 24090000 | J128: Sonstige Rückstellungen / Other Provisions | K128: Liabilities and Equity > Liabilities > Non-Current Liabilities > Provisions | L128: Bisher Rückstellung für 13. Monatsgehalt (nicht in [Y]): anderer Sachverhalt. Neu Other Provisions. n:1: 24090000 wird zum Sammelkonto für die sonstigen Rückstellungen; die Trennung nach Rückstellungsart geht verloren (Rückstellungsspiegel) – eigene Konten je wesentlicher Rückstellungsart prüfen. | M128: mittel | N128: korrigiert
A129: 097100 | B129: Rückstellungen für Berufsgenossenschaftsbeiträge | C129: 24033000 | D129: Rückstellungen Körperschaftssteuer | E129: Passiva > D. Rückstellungen > 3. Sonstige Rückstellungen (übrige) [2034002] | F129: Liabilities and Equity > Liabilities > Non-Current Liabilities > Provisions | G129: Abweichung | H129: OK | I129: 24090000 | J129: Sonstige Rückstellungen / Other Provisions | K129: Liabilities and Equity > Liabilities > Non-Current Liabilities > Provisions | L129: Bisher Rückstellung Körperschaftsteuer: anderer Sachverhalt. Neu Other Provisions; 21509000 (Verbindlichkeit Berufsgenossenschaft) liegt in Other Payable und passt nicht zum Ausweis als Rückstellung. n:1: 24090000 wird zum Sammelkonto für die sonstigen Rückstellungen; die Trennung nach Rückstellungsart geht verloren (Rückstellungsspiegel) – eigene Konten je wesentlicher Rückstellungsart prüfen. | M129: mittel | N129: korrigiert
A130: 097200 | B130: Rückstellungen für Urlaubsansprüche | C130: 24090000 | D130: Sonstige Rückstellungen | E130: Passiva > D. Rückstellungen > 3. Sonstige Rückstellungen (übrige) [2034002] | F130: Liabilities and Equity > Liabilities > Non-Current Liabilities > Provisions | G130: OK | H130: OK | I130: 24090000 | J130: Sonstige Rückstellungen / Other Provisions | K130: Liabilities and Equity > Liabilities > Non-Current Liabilities > Provisions | L130: Bezeichnung (Sonstige Rückstellungen) und Position passen. n:1: 24090000 wird zum Sammelkonto für die sonstigen Rückstellungen; die Trennung nach Rückstellungsart geht verloren (Rückstellungsspiegel) – eigene Konten je wesentlicher Rückstellungsart prüfen. | M130: mittel | N130: unverändert
A131: 097300 | B131: Rückstellungen für Restlöhne u. - Gehälter | C131: 21501000 | D131: Auszuzahlende Löhne und Gehälter | E131: Passiva > D. Rückstellungen > 3. Sonstige Rückstellungen (übrige) [2034002] | F131: Liabilities and Equity > Liabilities > Current Liabilities > Other Payable | G131: Abweichung | H131: Abweichung | I131: 24090000 | J131: Sonstige Rückstellungen / Other Provisions | K131: Liabilities and Equity > Liabilities > Non-Current Liabilities > Provisions | L131: Bisher Auszuzahlende Löhne und Gehälter (Verbindlichkeit in Other Payable); der Kunde weist eine Rückstellung aus. Neu Other Provisions. n:1: 24090000 wird zum Sammelkonto für die sonstigen Rückstellungen; die Trennung nach Rückstellungsart geht verloren (Rückstellungsspiegel) – eigene Konten je wesentlicher Rückstellungsart prüfen. | M131: mittel | N131: korrigiert
A132: 097302 | B132: Rückstellungen für Restgehälter (Bonus) | C132: 24032000 | D132: Rückstellungen Gewerbesteuer | E132: Passiva > D. Rückstellungen > 3. Sonstige Rückstellungen (übrige) [2034002] | F132: Liabilities and Equity > Liabilities > Non-Current Liabilities > Provisions | G132: Abweichung | H132: Abweichung | I132: 24090000 | J132: Sonstige Rückstellungen / Other Provisions | K132: Liabilities and Equity > Liabilities > Non-Current Liabilities > Provisions | L132: Bisher Rückstellung Gewerbesteuer: anderer Sachverhalt. Neu Other Provisions; 21770000 Bonusrückstellung betrifft Kundenboni, nicht Mitarbeiterboni. n:1: 24090000 wird zum Sammelkonto für die sonstigen Rückstellungen; die Trennung nach Rückstellungsart geht verloren (Rückstellungsspiegel) – eigene Konten je wesentlicher Rückstellungsart prüfen. | M132: mittel | N132: korrigiert
A133: 097430 | B133: Rückstellungen für Prozesskosten | C133: 24090000 | D133: Sonstige Rückstellungen | E133: Passiva > D. Rückstellungen > 3. Sonstige Rückstellungen (übrige) [2034002] | F133: Liabilities and Equity > Liabilities > Non-Current Liabilities > Provisions | G133: OK | H133: OK | I133: 24090000 | J133: Sonstige Rückstellungen / Other Provisions | K133: Liabilities and Equity > Liabilities > Non-Current Liabilities > Provisions | L133: Bezeichnung (Sonstige Rückstellungen) und Position passen. n:1: 24090000 wird zum Sammelkonto für die sonstigen Rückstellungen; die Trennung nach Rückstellungsart geht verloren (Rückstellungsspiegel) – eigene Konten je wesentlicher Rückstellungsart prüfen. | M133: mittel | N133: unverändert
A134: 097440 | B134: Rückstellungen für Prüfungskosten | C134: 24090000 | D134: Sonstige Rückstellungen | E134: Passiva > D. Rückstellungen > 3. Sonstige Rückstellungen (übrige) [2034002] | F134: Liabilities and Equity > Liabilities > Non-Current Liabilities > Provisions | G134: OK | H134: OK | I134: 24090000 | J134: Sonstige Rückstellungen / Other Provisions | K134: Liabilities and Equity > Liabilities > Non-Current Liabilities > Provisions | L134: Bezeichnung (Sonstige Rückstellungen) und Position passen. n:1: 24090000 wird zum Sammelkonto für die sonstigen Rückstellungen; die Trennung nach Rückstellungsart geht verloren (Rückstellungsspiegel) – eigene Konten je wesentlicher Rückstellungsart prüfen. | M134: mittel | N134: unverändert
... A152: 071100 | B152: Kurzfristige Darlehen | C152: 14102000 | D152: Sonstige Darlehen - kurzfristig | E152: Passiva > E. Verbindlichkeiten > 1. Verbindlichkeiten gegenüber Kreditinstituten > Kurzfristige Darlehen [2042020] | F152: nicht in [Y] enthalten | G152: Abweichung | H152: Abweichung | I152: 22510000 | J152: Loans from Banks (no recon acct) | K152: Liabilities and Equity > Liabilities > Non-Current Liabilities > Bank Loans | L152: Bisher 14102000: Text passt, das Konto steht aber für gewährte Darlehen (Aktivseite) und ist in [Y] nicht vorhanden. Neu Loans from Banks (no recon acct) in Bank Loans. Die Fristigkeit wird in YCOA nicht über das Buchungskonto, sondern über die Umgliederung nach Restlaufzeit abgebildet (29130000 für 1-5 Jahre, 29131000 für über 5 Jahre). n:1: die Trennung Schuldschein / diverse / Förderdarlehen / kurzfristig geht verloren (Darlehensspiegel, Zinsabgrenzung) – eigene Konten oder Abbildung über Treasury prüfen. | M152: hoch | N152: korrigiert
A153: 170290 | B153: VR - Abgrenzung Zinsen Kreditinstitute | C153: 21700000 | D153: Konzernverbindlichkeiten | E153: Passiva > E. Verbindlichkeiten > 1. Verbindlichkeiten gegenüber Kreditinstituten > Sonstige (Zinsabgrenzung) [2042030/00] | F153: nicht in [Y] enthalten | G153: Abweichung | H153: Abweichung | L153: Bisher Konzernverbindlichkeiten (nicht in [Y]): anderer Sachverhalt. Zinsabgrenzung auf Bankdarlehen wird vom Kunden unter Verbindlichkeiten gegenüber Kreditinstituten ausgewiesen; in Bank Loans gibt es kein Zinsabgrenzungskonto, das Treasury-Konto 22542000 ist in FPA1 nicht zugeordnet. Neuanlage prüfen (Kopiervorlage 22510000). Rückfall: 22510000. | M153: mittel | N153: Neuanlage prüfen
A154: 071070 | B154: Verbl. gg. weiteren Darlehensgebern | C154: 14107000 | D154: Mitarbeiterdarlehen | E154: Passiva > E. Verbindlichkeiten > 2. Verbindlichkeiten gegenüber weiteren Darlehensgebern [2043030] | F154: Assets > Non-Current Assets > Other Non-Current Assets > Long-Term Investments | G154: Abweichung | H154: Abweichung | L154: Bisher Mitarbeiterdarlehen (Aktivkonto): falsch. Für Darlehen von Nichtbanken gibt es in den zugeordneten Positionen von [Y] weder ein Konto noch eine eigene Position; die Konten in Bank Loans sind auf Kreditinstitute benannt. Neuanlage prüfen. Bei Abbildung über Treasury: 29140000 Long Term Debts, Unaffiliated (in FPA1 nicht zugeordnet). | M154: hoch | N154: Neuanlage prüfen
A155: 170291 | B155: VR - Abgrenzung Zinsen weiterer Darlehensgeber | C155: 19110000 | D155: Sonstige Darlehen - langfristig | E155: Passiva > E. Verbindlichkeiten > 2. Verbindlichkeiten gegenüber weiteren Darlehensgebern [2043030] | F155: nicht in [Y] enthalten | G155: Abweichung | H155: Abweichung | L155: Bisher Sonstige Darlehen langfristig (nicht in [Y]): eine Zinsabgrenzung ist kein Darlehen. Wie 071070 fehlt für weitere Darlehensgeber Konto und Position; Neuanlage zusammen mit 071070 prüfen. | M155: mittel | N155: Neuanlage prüfen
...

Sheet Zusammenfassung
A1: Überarbeitung Kontenplan-Mapping DUS → YCOA: Zusammenfassung
A2: Stand nach den Entscheidungen des Auftraggebers vom 02.10.2026. Alle Kennzahlen sind Formeln auf das Blatt Mapping und rechnen bei Änderungen dort neu.
A4: 1. Kennzahlen
A5: Geprüfte Kundenkonten | B5: =COUNTA(Mapping!$A$2:$A$601) -> 600
A6: davon mit Bilanz-/GuV-Position in [Z] (bilanziell validiert) | B6: =COUNTIF(Mapping!$H$2:$H$601,"<>nicht prüfbar") -> 533
A7: Nicht bilanziell validierte Konten (kein Eintrag in [Z], nur Bezeichnungsprüfung) | B7: =COUNTIF(Mapping!$H$2:$H$601,"nicht prüfbar") -> 67
A8: Korrekturen (Status korrigiert) | B8: =COUNTIF(Mapping!$N$2:$N$601,"korrigiert") -> 359
A9: davon bisher falsch zugeordnet | B9: =COUNTIFS(Mapping!$N$2:$N$601,"korrigiert",Mapping!$C$2:$C$601,"<>TBD") -> 259
A10: davon bisher ohne Zuordnung (TBD), jetzt zugeordnet | B10: =COUNTIFS(Mapping!$N$2:$N$601,"korrigiert",Mapping!$C$2:$C$601,"TBD") -> 100
A11: Unverändert bestätigt | B11: =COUNTIF(Mapping!$N$2:$N$601,"unverändert") -> 95
A12: Neuanlage (entschieden, Vorschlag im Blatt Neuanlagen) | B12: =COUNTIF(Mapping!$N$2:$N$601,"Neuanlage") -> 85
A13: Offene Fälle gesamt (Neuanlage prüfen + manuell klären) | B13: =B14+B15 -> 61
A14: Neuanlage prüfen (kein passendes YCOA-Konto, kein Vorschlag) | B14: =COUNTIF(Mapping!$N$2:$N$601,"Neuanlage prüfen") -> 39
A15: Manuell klären (Sachverhalt oder Ausweis offen) | B15: =COUNTIF(Mapping!$N$2:$N$601,"manuell klären") -> 22
A16: Kontrolle: Summe aller Status = geprüfte Konten | B16: =IF(B8+B11+B12+B14+B15=B5,"OK","Differenz") -> OK
A17: Kontrolle: alle Nummern im Blatt Neuanlagen frei | B17: =IF(COUNTIF(Neuanlagen!$J$6:$J$90,"frei")=B12,"OK","prüfen") -> OK | C17: Vergleich mit den Konten aus [Y] und [X] sowie innerhalb der Liste
A19: 2. Ergebnis der Prüfung des bisherigen Mappings
A20: Bezeichnungsprüfung: OK | B20: =COUNTIF(Mapping!$G$2:$G$601,"OK") -> 136
A21: Bezeichnungsprüfung: Abweichung | B21: =COUNTIF(Mapping!$G$2:$G$601,"Abweichung") -> 314
A22: Bezeichnungsprüfung: kein Mapping (bisher TBD) | B22: =COUNTIF(Mapping!$G$2:$G$601,"kein Mapping (TBD)") -> 150
A23: Bilanzprüfung: OK | B23: =COUNTIF(Mapping!$H$2:$H$601,"OK") -> 148
A24: Bilanzprüfung: Abweichung | B24: =COUNTIF(Mapping!$H$2:$H$601,"Abweichung") -> 251
A25: Bilanzprüfung: kein Mapping (bisher TBD, Konto in [Z]) | B25: =COUNTIF(Mapping!$H$2:$H$601,"kein Mapping (TBD)") -> 134
A26: Bilanzprüfung: nicht prüfbar (Konto nicht in [Z]) | B26: =COUNTIF(Mapping!$H$2:$H$601,"nicht prüfbar") -> 67
A27: Bisheriges Zielkonto in [Y] nicht vorhanden | B27: =COUNTIF(Mapping!$F$2:$F$601,"nicht in [Y] enthalten") -> 56 | C27: Konten aus [X], die im Buchungskreis 10DU / in FPA1 fehlen (u. a. Länderversionen BR/AU)
A28: Bisheriges Zielkonto in FPA1 keiner Position zugeordnet (Not assigned) | B28: =COUNTIF(Mapping!$F$2:$F$601,"Not assigned*") -> 93 | C28: Treasury-, Leasing- (ROU) und Verrechnungskonten außerhalb der Bilanzstruktur
A30: 3. Konfidenz der neuen Einstufung
A31: hoch | B31: =COUNTIF(Mapping!$M$2:$M$601,"hoch") -> 252
A32: mittel | B32: =COUNTIF(Mapping!$M$2:$M$601,"mittel") -> 332
A33: niedrig | B33: =COUNTIF(Mapping!$M$2:$M$601,"niedrig") -> 16
A35: 4. Status nach Bereich
A36: Bereich | B36: unverändert | C36: korrigiert | D36: Neuanlage | E36: Neuanlage prüfen | F36: manuell klären | G36: Summe
A37: Bilanz Aktiva | B37: =COUNTIFS(Mapping!$E$2:$E$601,"Aktiva*",Mapping!$N$2:$N$601,"unverändert") -> 29 | C37: =COUNTIFS(Mapping!$E$2:$E$601,"Aktiva*",Mapping!$N$2:$N$601,"korrigiert") -> 70 | D37: =COUNTIFS(Mapping!$E$2:$E$601,"Aktiva*",Mapping!$N$2:$N$601,"Neuanlage") -> 0 | E37: =COUNTIFS(Mapping!$E$2:$E$601,"Aktiva*",Mapping!$N$2:$N$601,"Neuanlage prüfen") -> 6 | F37: =COUNTIFS(Mapping!$E$2:$E$601,"Aktiva*",Mapping!$N$2:$N$601,"manuell klären") -> 4 | G37: =SUM(B37:F37) -> 109
A38: Bilanz Passiva | B38: =COUNTIFS(Mapping!$E$2:$E$601,"Passiva*",Mapping!$N$2:$N$601,"unverändert") -> 8 | C38: =COUNTIFS(Mapping!$E$2:$E$601,"Passiva*",Mapping!$N$2:$N$601,"korrigiert") -> 50 | D38: =COUNTIFS(Mapping!$E$2:$E$601,"Passiva*",Mapping!$N$2:$N$601,"Neuanlage") -> 0 | E38: =COUNTIFS(Mapping!$E$2:$E$601,"Passiva*",Mapping!$N$2:$N$601,"Neuanlage prüfen") -> 12 | F38: =COUNTIFS(Mapping!$E$2:$E$601,"Passiva*",Mapping!$N$2:$N$601,"manuell klären") -> 3 | G38: =SUM(B38:F38) -> 73
A39: Gewinn- und Verlustrechnung | B39: =COUNTIFS(Mapping!$E$2:$E$601,"GuV*",Mapping!$N$2:$N$601,"unverändert") -> 40 | C39: =COUNTIFS(Mapping!$E$2:$E$601,"GuV*",Mapping!$N$2:$N$601,"korrigiert") -> 181 | D39: =COUNTIFS(Mapping!$E$2:$E$601,"GuV*",Mapping!$N$2:$N$601,"Neuanlage") -> 76 | E39: =COUNTIFS(Mapping!$E$2:$E$601,"GuV*",Mapping!$N$2:$N$601,"Neuanlage prüfen") -> 18 | F39: =COUNTIFS(Mapping!$E$2:$E$601,"GuV*",Mapping!$N$2:$N$601,"manuell klären") -> 8 | G39: =SUM(B39:F39) -> 323
A40: Kalkulatorische Kosten (außerhalb GuV) | B40: =COUNTIFS(Mapping!$E$2:$E$601,"Außerhalb*",Mapping!$N$2:$N$601,"unverändert") -> 10 | C40: =COUNTIFS(Mapping!$E$2:$E$601,"Außerhalb*",Mapping!$N$2:$N$601,"korrigiert") -> 15 | D40: =COUNTIFS(Mapping!$E$2:$E$601,"Außerhalb*",Mapping!$N$2:$N$601,"Neuanlage") -> 0 | E40: =COUNTIFS(Mapping!$E$2:$E$601,"Außerhalb*",Mapping!$N$2:$N$601,"Neuanlage prüfen") -> 1 | F40: =COUNTIFS(Mapping!$E$2:$E$601,"Außerhalb*",Mapping!$N$2:$N$601,"manuell klären") -> 2 | G40: =SUM(B40:F40) -> 28
A41: Nicht in [Z] (nicht bilanziell validiert) | B41: =COUNTIFS(Mapping!$E$2:$E$601,"nicht in*",Mapping!$N$2:$N$601,"unverändert") -> 8 | C41: =COUNTIFS(Mapping!$E$2:$E$601,"nicht in*",Mapping!$N$2:$N$601,"korrigiert") -> 43 | D41: =COUNTIFS(Mapping!$E$2:$E$601,"nicht in*",Mapping!$N$2:$N$601,"Neuanlage") -> 9 | E41: =COUNTIFS(Mapping!$E$2:$E$601,"nicht in*",Mapping!$N$2:$N$601,"Neuanlage prüfen") -> 2 | F41: =COUNTIFS(Mapping!$E$2:$E$601,"nicht in*",Mapping!$N$2:$N$601,"manuell klären") -> 5 | G41: =SUM(B41:F41) -> 67
A42: Summe | B42: =SUM(B37:B41) -> 95 | C42: =SUM(C37:C41) -> 359 | D42: =SUM(D37:D41) -> 85 | E42: =SUM(E37:E41) -> 39 | F42: =SUM(F37:F41) -> 22 | G42: =SUM(G37:G41) -> 600
A43: Konten mit zwei Positionen in [Z] (157300, 195024, 195500) zählen im Bereich der zuerst genannten Position.
A45: 5. Entscheidungen des Auftraggebers vom 02.10.2026
A46: 1. Erlöskonten: Erlöskonten neu anlegen. | B46: Die 85 Konten der Klasse 8 ohne passendes YCOA-Konto (84 Umsatzerlöskonten und 870000 aktivierte Eigenleistungen) erhalten den Status Neuanlage. Das Blatt Neuanlagen enthält je Konto den Vorschlag für Nummer, Bezeichnung, Kopiervorlage und Position.
A47: 2. Standardkonten ohne FPA1-Position: In der kundeneigenen Bilanzstruktur zuordnen. | B47: 21120000 (WE/RE) wird den Verbindlichkeiten aus L&L zugeordnet, 70020000/70030000 (Anlagenabgang) und 71010200 (Zuschreibungen) den sonstigen betrieblichen Erträgen. Die vier Kundenkonten 300009, 867000, 867001 und 202110 sind damit nicht mehr offen (zwei korrigiert, zwei unverändert).
A48: 3. Zusatzregel ein YCOA-Konto je Kundenzeile: Vorerst beibehalten. | B48: Keine Änderung: 65001000 bleibt den bezogenen Leistungen (GuV 4b) vorbehalten, Fremdleistungen der sonstigen betrieblichen Aufwendungen (GuV 7) laufen auf 65008300; entsprechend 63005000/63009000.
A50: 6. Wesentliche Befunde zum bisherigen Vorschlag
A51: • Kontoart verwechselt: Bestandskonten lagen auf Aufwands-/Ertragskonten und umgekehrt (z. B. Bauten auf einem Abschreibungskonto, Lagermaterial auf Sonstiges Material, Auflösung von Rückstellungen auf dem Rückstellungskonto).
A52: • Bilanzseite vertauscht: Forderungen aus L&L auf einem passiven Abgrenzungsposten, passive auf aktive Rechnungsabgrenzung, Bankdarlehen auf gewährte Darlehen.
A53: • Reine Texttreffer ohne fachlichen Bezug (z. B. Verbindlichkeiten gegenüber FDI → Verbindlichkeiten gegenüber Berufsgenossenschaft, Lärmzuschläge und Beiträge → Zinserträge, Leistungen Ground → Grundstücke ROU).
A54: • Hard Overrides mit falschem Ziel: 12110000 ist in [X] als Forderungen Inland bezeichnet, laut [Y] aber Other Down Payments Made Current Assets (Inventories); 21700000 Konzernverbindlichkeiten existiert in [Y] nicht.
A55: • Zielkonten außerhalb der Bilanzstruktur: Treasury- (TRM), Leasing- (ROU), Immobilien- und sekundäre Verrechnungskonten (9xxxxxxx) sind in FPA1 keiner Position zugeordnet oder nicht direkt bebuchbar.
A56: • Länderfremde Konten (Brasilien, Australien) und weitere Konten aus [X], die im Buchungskreis 10DU nicht vorhanden sind.
A57: • YCOA kennt keine flughafenspezifischen Erlöskonten und keine Konten für Sonderposten, Gesellschafterdarlehen, Beteiligungsunternehmen und Ergebnisabführung. Für die Erlöskonten ist die Neuanlage entschieden (Blatt Neuanlagen); für die übrigen Fälle steht die Entscheidung über Neuanlagen noch aus (Status Neuanlage prüfen).
A58: • Sammelkonten: mehrere generische YCOA-Konten nehmen viele Kundenkonten auf (siehe Blatt Sammelkonten); wo die Trennung fachlich relevant ist, steht ein Hinweis in der Begründung. Jedes Zielkonto bedient dabei nur eine Bilanz-/GuV-Zeile des Kunden, damit dessen Bilanz und GuV aus YCOA-Konten ableitbar bleiben.
A60: Die Zuordnungstabelle der Bilanz-/GuV-Positionen Kunde ↔ SAP-Standard steht im Blatt Positionszuordnung; Methode, Wertebereiche und Annahmen im Blatt Hinweise.

Sheet Neuanlagen
A1: Neuanlagen: Vorschlag für die neu anzulegenden Erlöskonten (Entscheidung vom 02.10.2026)
A2: Diese Konten existieren in YCOA noch nicht. Kontonummer = Präfix + Kundenkonto; das Präfix steht in der gelben Eingabezelle C3 und kann geändert werden, die Nummern im Blatt Mapping folgen per Formel. Spalte J prüft die Nummer nur gegen die Konten aus [Y] und [X] (Blatt YCOA-Konten) und auf Dubletten in dieser Liste; vor der Anlage zusätzlich im System gegen den gesamten Kontenplan YCOA prüfen. Bezeichnung = Bezeichnung des Kundenkontos (Langtext, höchstens 50 Zeichen); Kurztexte sind aus dem Altsystem zu übernehmen.
A3: Präfix für neue Kontonummern | C3: 41 | D3: Eingabezelle. Vorschlag 41: Erlösbereich 41xxxxxx, Block 418xxxxx in [Y]/[X] unbelegt; entspricht der im System bereits verwendeten Konvention 99 + Kundenkonto für die kundeneigenen Verrechnungskonten.
A5: Kundenkonto | B5: Bezeichnung Kunde | C5: Neue Kontonummer (Vorschlag) | D5: Bezeichnung neues Konto (Vorschlag, Langtext) | E5: Kopiervorlage (YCOA) | F5: Bezeichnung Kopiervorlage | G5: Vorgesehene Position SAP-Standard (FPA1) | H5: Erlösgruppe / GuV-Zeile Kunde | I5: Saldo 2025 laut [Z] in EUR (Haben negativ) | J5: Prüfung Nummer | K5: Hinweis
A6: 800000 | B6: Grundentgelte | C6: =$C$3&A6 -> 41800000 | D6: Grundentgelte | E6: 41000000 | F6: Erlöse Inland - Erzeugnis / Revenue Domestic - Product | G6: Gross Revenue (FPA1/022) | H6: 1. Umsatzerlöse > Flughafenentgelte > Landeentgelte (fix) | I6: -33107405 | J6: =IF(COUNTIF('YCOA-Konten'!$A$5:$A$708,C6)>0,"belegt",IF(COUNTIF($C$6:$C$90,C6)>1,"doppelt","frei")) -> frei
A7: 800001 | B7: NOX-Entgelte | C7: =$C$3&A7 -> 41800001 | D7: NOX-Entgelte | E7: 41000000 | F7: Erlöse Inland - Erzeugnis / Revenue Domestic - Product | G7: Gross Revenue (FPA1/022) | H7: 1. Umsatzerlöse > Flughafenentgelte > Landeentgelte (fix) | I7: -2527837.5 | J7: =IF(COUNTIF('YCOA-Konten'!$A$5:$A$708,C7)>0,"belegt",IF(COUNTIF($C$6:$C$90,C7)>1,"doppelt","frei")) -> frei
A8: 800002 | B8: Lärmzuschläge | C8: =$C$3&A8 -> 41800002 | D8: Lärmzuschläge | E8: 41000000 | F8: Erlöse Inland - Erzeugnis / Revenue Domestic - Product | G8: Gross Revenue (FPA1/022) | H8: 1. Umsatzerlöse > Flughafenentgelte > Landeentgelte (fix) | I8: -8812148 | J8: =IF(COUNTIF('YCOA-Konten'!$A$5:$A$708,C8)>0,"belegt",IF(COUNTIF($C$6:$C$90,C8)>1,"doppelt","frei")) -> frei
A9: 800010 | B9: Passagierentgelte Inland | C9: =$C$3&A9 -> 41800010 | D9: Passagierentgelte Inland | E9: 41000000 | F9: Erlöse Inland - Erzeugnis / Revenue Domestic - Product | G9: Gross Revenue (FPA1/022) | H9: 1. Umsatzerlöse > Flughafenentgelte > Landeentgelte (variabel) | I9: -13462831 | J9: =IF(COUNTIF('YCOA-Konten'!$A$5:$A$708,C9)>0,"belegt",IF(COUNTIF($C$6:$C$90,C9)>1,"doppelt","frei")) -> frei
A10: 800020 | B10: Lande und Startentg. GAT | C10: =$C$3&A10 -> 41800020 | D10: Lande und Startentg. GAT | E10: 41000000 | F10: Erlöse Inland - Erzeugnis / Revenue Domestic - Product | G10: Gross Revenue (FPA1/022) | H10: 1. Umsatzerlöse > Flughafenentgelte > Landeentgelte (fix) | I10: -1693316.6 | J10: =IF(COUNTIF('YCOA-Konten'!$A$5:$A$708,C10)>0,"belegt",IF(COUNTIF($C$6:$C$90,C10)>1,"doppelt","frei")) -> frei
A11: 800110 | B11: Passagierentgelte NON EU | C11: =$C$3&A11 -> 41800110 | D11: Passagierentgelte NON EU | E11: 41000000 | F11: Erlöse Inland - Erzeugnis / Revenue Domestic - Product | G11: Gross Revenue (FPA1/022) | H11: 1. Umsatzerlöse > Flughafenentgelte > Landeentgelte (variabel) | I11: -71318907 | J11: =IF(COUNTIF('YCOA-Konten'!$A$5:$A$708,C11)>0,"belegt",IF(COUNTIF($C$6:$C$90,C11)>1,"doppelt","frei")) -> frei
A12: 800111 | B12: Passagierentgelte EU | C12: =$C$3&A12 -> 41800111 | D12: Passagierentgelte EU | E12: 41000000 | F12: Erlöse Inland - Erzeugnis / Revenue Domestic - Product | G12: Gross Revenue (FPA1/022) | H12: 1. Umsatzerlöse > Flughafenentgelte > Landeentgelte (variabel) | I12: -94890996 | J12: =IF(COUNTIF('YCOA-Konten'!$A$5:$A$708,C12)>0,"belegt",IF(COUNTIF($C$6:$C$90,C12)>1,"doppelt","frei")) -> frei
A13: 800400 | B13: PRM-Entgelt (People with reduced Mobility) | C13: =$C$3&A13 -> 41800400 | D13: PRM-Entgelt (People with reduced Mobility) | E13: 41000000 | F13: Erlöse Inland - Erzeugnis / Revenue Domestic - Product | G13: Gross Revenue (FPA1/022) | H13: 1. Umsatzerlöse > Flughafenentgelte > Landeentgelte (PRM) | I13: -10936521 | J13: =IF(COUNTIF('YCOA-Konten'!$A$5:$A$708,C13)>0,"belegt",IF(COUNTIF($C$6:$C$90,C13)>1,"doppelt","frei")) -> frei
A14: 800420 | B14: Passagierentgelte Transit / Transfer | C14: =$C$3&A14 -> 41800420 | D14: Passagierentgelte Transit / Transfer | E14: 41000000 | F14: Erlöse Inland - Erzeugnis / Revenue Domestic - Product | G14: Gross Revenue (FPA1/022) | H14: 1. Umsatzerlöse > Flughafenentgelte > Landeentgelte (variabel) | I14: -2220821.8 | J14: =IF(COUNTIF('YCOA-Konten'!$A$5:$A$708,C14)>0,"belegt",IF(COUNTIF($C$6:$C$90,C14)>1,"doppelt","frei")) -> frei
A15: 800430 | B15: EU-Sicherheitsentgelte | C15: =$C$3&A15 -> 41800430 | D15: EU-Sicherheitsentgelte | E15: 41000000 | F15: Erlöse Inland - Erzeugnis / Revenue Domestic - Product | G15: Gross Revenue (FPA1/022) | H15: 1. Umsatzerlöse > Flughafenentgelte > Landeentgelte (variabel) | I15: -14168786 | J15: =IF(COUNTIF('YCOA-Konten'!$A$5:$A$708,C15)>0,"belegt",IF(COUNTIF($C$6:$C$90,C15)>1,"doppelt","frei")) -> frei
A16: 801000 | B16: Abstellentgelte | C16: =$C$3&A16 -> 41801000 | D16: Abstellentgelte | E16: 41000000 | F16: Erlöse Inland - Erzeugnis / Revenue Domestic - Product | G16: Gross Revenue (FPA1/022) | H16: 1. Umsatzerlöse > Flughafenentgelte > Abstellentgelte | I16: -3237343.6 | J16: =IF(COUNTIF('YCOA-Konten'!$A$5:$A$708,C16)>0,"belegt",IF(COUNTIF($C$6:$C$90,C16)>1,"doppelt","frei")) -> frei
A17: 810030 | B17: Zentrale Infrastruktur Counter | C17: =$C$3&A17 -> 41810030 | D17: Zentrale Infrastruktur Counter | E17: 41000000 | F17: Erlöse Inland - Erzeugnis / Revenue Domestic - Product | G17: Gross Revenue (FPA1/022) | H17: 1. Umsatzerlöse > Bodenverkehrsdienste > Abfertigungsentgelte | I17: -5844947.4 | J17: =IF(COUNTIF('YCOA-Konten'!$A$5:$A$708,C17)>0,"belegt",IF(COUNTIF($C$6:$C$90,C17)>1,"doppelt","frei")) -> frei
... A22: 811040 | B22: Sonderleistungen Vorfeldabfertigung | C22: =$C$3&A22 -> 41811040 | D22: Sonderleistungen Vorfeldabfertigung | E22: 41000000 | F22: Erlöse Inland - Erzeugnis / Revenue Domestic - Product | G22: Gross Revenue (FPA1/022) | H22: 1. Umsatzerlöse > Bodenverkehrsdienste > Sonderleistungen | I22: -1067506.7 | J22: =IF(COUNTIF('YCOA-Konten'!$A$5:$A$708,C22)>0,"belegt",IF(COUNTIF($C$6:$C$90,C22)>1,"doppelt","frei")) -> frei
A23: 811090 | B23: Sonderleistungen Enteisung | C23: =$C$3&A23 -> 41811090 | D23: Sonderleistungen Enteisung | E23: 41000000 | F23: Erlöse Inland - Erzeugnis / Revenue Domestic - Product | G23: Gross Revenue (FPA1/022) | H23: 1. Umsatzerlöse > Bodenverkehrsdienste > Sonderleistungen (analog 811xxx, nicht in [Z]) | J23: =IF(COUNTIF('YCOA-Konten'!$A$5:$A$708,C23)>0,"belegt",IF(COUNTIF($C$6:$C$90,C23)>1,"doppelt","frei")) -> frei | K23: Nicht in [Z] (bei FDG 2025/2024 ohne Saldo): Bedarf vor der Anlage bestätigen.
A24: 811110 | B24: Sonderleistungen Gepäckdienst | C24: =$C$3&A24 -> 41811110 | D24: Sonderleistungen Gepäckdienst | E24: 41000000 | F24: Erlöse Inland - Erzeugnis / Revenue Domestic - Product | G24: Gross Revenue (FPA1/022) | H24: 1. Umsatzerlöse > Bodenverkehrsdienste > Sonderleistungen | I24: -27731.27 | J24: =IF(COUNTIF('YCOA-Konten'!$A$5:$A$708,C24)>0,"belegt",IF(COUNTIF($C$6:$C$90,C24)>1,"doppelt","frei")) -> frei
A25: 811120 | B25: Sonderleistungen Personentransporte | C25: =$C$3&A25 -> 41811120 | D25: Sonderleistungen Personentransporte | E25: 41000000 | F25: Erlöse Inland - Erzeugnis / Revenue Domestic - Product | G25: Gross Revenue (FPA1/022) | H25: 1. Umsatzerlöse > Bodenverkehrsdienste > Sonderleistungen (analog 811xxx, nicht in [Z]) | J25: =IF(COUNTIF('YCOA-Konten'!$A$5:$A$708,C25)>0,"belegt",IF(COUNTIF($C$6:$C$90,C25)>1,"doppelt","frei")) -> frei | K25: Nicht in [Z] (bei FDG 2025/2024 ohne Saldo): Bedarf vor der Anlage bestätigen.
A26: 811121 | B26: Sonderleistungen Crew-Transporte | C26: =$C$3&A26 -> 41811121 | D26: Sonderleistungen Crew-Transporte | E26: 41000000 | F26: Erlöse Inland - Erzeugnis / Revenue Domestic - Product | G26: Gross Revenue (FPA1/022) | H26: 1. Umsatzerlöse > Bodenverkehrsdienste > Sonderleistungen (analog 811xxx, nicht in [Z]) | J26: =IF(COUNTIF('YCOA-Konten'!$A$5:$A$708,C26)>0,"belegt",IF(COUNTIF($C$6:$C$90,C26)>1,"doppelt","frei")) -> frei | K26: Nicht in [Z] (bei FDG 2025/2024 ohne Saldo): Bedarf vor der Anlage bestätigen.
A27: 811130 | B27: Containerlagerung | C27: =$C$3&A27 -> 41811130 | D27: Containerlagerung | E27: 41000000 | F27: Erlöse Inland - Erzeugnis / Revenue Domestic - Product | G27: Gross Revenue (FPA1/022) | H27: 1. Umsatzerlöse > Bodenverkehrsdienste > Sonderleistungen | I27: -450628.26 | J27: =IF(COUNTIF('YCOA-Konten'!$A$5:$A$708,C27)>0,"belegt",IF(COUNTIF($C$6:$C$90,C27)>1,"doppelt","frei")) -> frei
A28: 813051 | B28: Nutzungsentgelt FDG-Lounges | C28: =$C$3&A28 -> 41813051 | D28: Nutzungsentgelt FDG-Lounges | E28: 41000000 | F28: Erlöse Inland - Erzeugnis / Revenue Domestic - Product | G28: Gross Revenue (FPA1/022) | H28: 1. Umsatzerlöse > Sonstige Erlöse | I28: -7156311.9 | J28: =IF(COUNTIF('YCOA-Konten'!$A$5:$A$708,C28)>0,"belegt",IF(COUNTIF($C$6:$C$90,C28)>1,"doppelt","frei")) -> frei
A29: 820000 | B29: Mieterlöse Werbung innen | C29: =$C$3&A29 -> 41820000 | D29: Mieterlöse Werbung innen | E29: 41000000 | F29: Erlöse Inland - Erzeugnis / Revenue Domestic - Product | G29: Gross Revenue (FPA1/022) | H29: 1. Umsatzerlöse > Mieterlöse | I29: -1415304.4 | J29: =IF(COUNTIF('YCOA-Konten'!$A$5:$A$708,C29)>0,"belegt",IF(COUNTIF($C$6:$C$90,C29)>1,"doppelt","frei")) -> frei | K29: Bei Vertrags- und Leasingmanagement Kontenfindung auf dieses Konto umstellen (Standard: 70700000).
A30: 820003 | B30: Mieterlöse Werbung | C30: =$C$3&A30 -> 41820003 | D30: Mieterlöse Werbung | E30: 41000000 | F30: Erlöse Inland - Erzeugnis / Revenue Domestic - Product | G30: Gross Revenue (FPA1/022) | H30: 1. Umsatzerlöse > Mieterlöse | I30: -1078826.6 | J30: =IF(COUNTIF('YCOA-Konten'!$A$5:$A$708,C30)>0,"belegt",IF(COUNTIF($C$6:$C$90,C30)>1,"doppelt","frei")) -> frei | K30: Bei Vertrags- und Leasingmanagement Kontenfindung auf dieses Konto umstellen (Standard: 70700000).
A31: 820004 | B31: Dienstleistungen ZI Basisentgelt FDG | C31: =$C$3&A31 -> 41820004 | D31: Dienstleistungen ZI Basisentgelt FDG | E31: 41001500 | F31: Revenue Affiliate - Product | G31: Gross Revenue (FPA1/022) | H31: 1. Umsatzerlöse > Erlösgruppe klären (Nummernkreis der Mieterlöse, Bezeichnung Dienstleistung; nicht in [Z]) | J31: =IF(COUNTIF('YCOA-Konten'!$A$5:$A$708,C31)>0,"belegt",IF(COUNTIF($C$6:$C$90,C31)>1,"doppelt","frei")) -> frei | K31: Erlöse mit verbundenen Unternehmen: Partnergesellschaft mitführen. Nicht in [Z] (bei FDG 2025/2024 ohne Saldo): Bedarf vor der Anlage bestätigen.
A32: 820030 | B32: Mieterlöse Verkaufsgeschäfte | C32: =$C$3&A32 -> 41820030 | D32: Mieterlöse Verkaufsgeschäfte | E32: 41000000 | F32: Erlöse Inland - Erzeugnis / Revenue Domestic - Product | G32: Gross Revenue (FPA1/022) | H32: 1. Umsatzerlöse > Mieterlöse | I32: -231863.81 | J32: =IF(COUNTIF('YCOA-Konten'!$A$5:$A$708,C32)>0,"belegt",IF(COUNTIF($C$6:$C$90,C32)>1,"doppelt","frei")) -> frei | K32: Bei Vertrags- und Leasingmanagement Kontenfindung auf dieses Konto umstellen (Standard: 70700000).
A33: 820031 | B33: Mieterlöse Gastronomie | C33: =$C$3&A33 -> 41820031 | D33: Mieterlöse Gastronomie | E33: 41000000 | F33: Erlöse Inland - Erzeugnis / Revenue Domestic - Product | G33: Gross Revenue (FPA1/022) | H33: 1. Umsatzerlöse > Mieterlöse | I33: -1110992.1 | J33: =IF(COUNTIF('YCOA-Konten'!$A$5:$A$708,C33)>0,"belegt",IF(COUNTIF($C$6:$C$90,C33)>1,"doppelt","frei")) -> frei | K33: Bei Vertrags- und Leasingmanagement Kontenfindung auf dieses Konto umstellen (Standard: 70700000).
A34: 820033 | B34: Mieterlöse Reisemarkt | C34: =$C$3&A34 -> 41820033 | D34: Mieterlöse Reisemarkt | E34: 41000000 | F34: Erlöse Inland - Erzeugnis / Revenue Domestic - Product | G34: Gross Revenue (FPA1/022) | H34: 1. Umsatzerlöse > Mieterlöse | I34: -205955.93 | J34: =IF(COUNTIF('YCOA-Konten'!$A$5:$A$708,C34)>0,"belegt",IF(COUNTIF($C$6:$C$90,C34)>1,"doppelt","frei")) -> frei | K34: Bei Vertrags- und Leasingmanagement Kontenfindung auf dieses Konto umstellen (Standard: 70700000).
A35: 820034 | B35: Mieterlöse DFS/TrValue | C35: =$C$3&A35 -> 41820034 | D35: Mieterlöse DFS/TrValue | E35: 41000000 | F35: Erlöse Inland - Erzeugnis / Revenue Domestic - Product | G35: Gross Revenue (FPA1/022) | H35: 1. Umsatzerlöse > Mieterlöse | I35: -224555.4 | J35: =IF(COUNTIF('YCOA-Konten'!$A$5:$A$708,C35)>0,"belegt",IF(COUNTIF($C$6:$C$90,C35)>1,"doppelt","frei")) -> frei | K35: Bei Vertrags- und Leasingmanagement Kontenfindung auf dieses Konto umstellen (Standard: 70700000).
A36: 820059 | B36: Mieterlöse Sonstiges CO | C36: =$C$3&A36 -> 41820059 | D36: Mieterlöse Sonstiges CO | E36: 41000000 | F36: Erlöse Inland - Erzeugnis / Revenue Domestic - Product | G36: Gross Revenue (FPA1/022) | H36: 1. Umsatzerlöse > Mieterlöse | I36: -245202.02 | J36: =IF(COUNTIF('YCOA-Konten'!$A$5:$A$708,C36)>0,"belegt",IF(COUNTIF($C$6:$C$90,C36)>1,"doppelt","frei")) -> frei | K36: Bei Vertrags- und Leasingmanagement Kontenfindung auf dieses Konto umstellen (Standard: 70700000).
A37: 820060 | B37: Mieterlöse Parken | C37: =$C$3&A37 -> 41820060 | D37: Mieterlöse Parken | E37: 41000000 | F37: Erlöse Inland - Erzeugnis / Revenue Domestic - Product | G37: Gross Revenue (FPA1/022) | H37: 1. Umsatzerlöse > Mieterlöse | I37: -7458709.1 | J37: =IF(COUNTIF('YCOA-Konten'!$A$5:$A$708,C37)>0,"belegt",IF(COUNTIF($C$6:$C$90,C37)>1,"doppelt","frei")) -> frei | K37: Bei Vertrags- und Leasingmanagement Kontenfindung auf dieses Konto umstellen (Standard: 70700000).
A38: 820061 | B38: Mieterlöse Autovermieter | C38: =$C$3&A38 -> 41820061 | D38: Mieterlöse Autovermieter | E38: 41000000 | F38: Erlöse Inland - Erzeugnis / Revenue Domestic - Product | G38: Gross Revenue (FPA1/022) | H38: 1. Umsatzerlöse > Mieterlöse | I38: -6053784.3 | J38: =IF(COUNTIF('YCOA-Konten'!$A$5:$A$708,C38)>0,"belegt",IF(COUNTIF($C$6:$C$90,C38)>1,"doppelt","frei")) -> frei | K38: Bei Vertrags- und Leasingmanagement Kontenfindung auf dieses Konto umstellen (Standard: 70700000).
A39: 820062 | B39: Mieterlöse Catering | C39: =$C$3&A39 -> 41820062 | D39: Mieterlöse Catering | E39: 41000000 | F39: Erlöse Inland - Erzeugnis / Revenue Domestic - Product | G39: Gross Revenue (FPA1/022) | H39: 1. Umsatzerlöse > Mieterlöse | I39: -364634.52 | J39: =IF(COUNTIF('YCOA-Konten'!$A$5:$A$708,C39)>0,"belegt",IF(COUNTIF($C$6:$C$90,C39)>1,"doppelt","frei")) -> frei | K39: Bei Vertrags- und Leasingmanagement Kontenfindung auf dieses Konto umstellen (Standard: 70700000).
A40: 820063 | B40: Mieterlöse Tankdienste | C40: =$C$3&A40 -> 41820063 | D40: Mieterlöse Tankdienste | E40: 41000000 | F40: Erlöse Inland - Erzeugnis / Revenue Domestic - Product | G40: Gross Revenue (FPA1/022) | H40: 1. Umsatzerlöse > Mieterlöse | I40: -594569.34 | J40: =IF(COUNTIF('YCOA-Konten'!$A$5:$A$708,C40)>0,"belegt",IF(COUNTIF($C$6:$C$90,C40)>1,"doppelt","frei")) -> frei | K40: Bei Vertrags- und Leasingmanagement Kontenfindung auf dieses Konto umstellen (Standard: 70700000).
A41: 820064 | B41: Mieterlöse Vermietung | C41: =$C$3&A41 -> 41820064 | D41: Mieterlöse Vermietung | E41: 41000000 | F41: Erlöse Inland - Erzeugnis / Revenue Domestic - Product | G41: Gross Revenue (FPA1/022) | H41: 1. Umsatzerlöse > Mieterlöse | I41: -22865652 | J41: =IF(COUNTIF('YCOA-Konten'!$A$5:$A$708,C41)>0,"belegt",IF(COUNTIF($C$6:$C$90,C41)>1,"doppelt","frei")) -> frei | K41: Bei Vertrags- und Leasingmanagement Kontenfindung auf dieses Konto umstellen (Standard: 70700000).
A42: 820065 | B42: Mieterlöse Lohausen | C42: =$C$3&A42 -> 41820065 | D42: Mieterlöse Lohausen | E42: 41000000 | F42: Erlöse Inland - Erzeugnis / Revenue Domestic - Product | G42: Gross Revenue (FPA1/022) | H42: 1. Umsatzerlöse > Mieterlöse | I42: -985716.79 | J42: =IF(COUNTIF('YCOA-Konten'!$A$5:$A$708,C42)>0,"belegt",IF(COUNTIF($C$6:$C$90,C42)>1,"doppelt","frei")) -> frei | K42: Bei Vertrags- und Leasingmanagement Kontenfindung auf dieses Konto umstellen (Standard: 70700000).
A43: 820067 | B43: Mieterlöse Telekommunikation | C43: =$C$3&A43 -> 41820067 | D43: Mieterlöse Telekommunikation | E43: 41000000 | F43: Erlöse Inland - Erzeugnis / Revenue Domestic - Product | G43: Gross Revenue (FPA1/022) | H43: 1. Umsatzerlöse > Mieterlöse | I43: -928297.77 | J43: =IF(COUNTIF('YCOA-Konten'!$A$5:$A$708,C43)>0,"belegt",IF(COUNTIF($C$6:$C$90,C43)>1,"doppelt","frei")) -> frei | K43: Bei Vertrags- und Leasingmanagement Kontenfindung auf dieses Konto umstellen (Standard: 70700000).
... A47: 823590 | B47: Mieterlöse aus Gebrauchsüberlassung | C47: =$C$3&A47 -> 41823590 | D47: Mieterlöse aus Gebrauchsüberlassung | E47: 41000000 | F47: Erlöse Inland - Erzeugnis / Revenue Domestic - Product | G47: Gross Revenue (FPA1/022) | H47: 1. Umsatzerlöse > Mieterlöse | I47: -2220000 | J47: =IF(COUNTIF('YCOA-Konten'!$A$5:$A$708,C47)>0,"belegt",IF(COUNTIF($C$6:$C$90,C47)>1,"doppelt","frei")) -> frei | K47: Bei Vertrags- und Leasingmanagement Kontenfindung auf dieses Konto umstellen (Standard: 70700000).
A48: 824951 | B48: Mieterlöse Sonstige Grundstücksflächen | C48: =$C$3&A48 -> 41824951 | D48: Mieterlöse Sonstige Grundstücksflächen | E48: 41000000 | F48: Erlöse Inland - Erzeugnis / Revenue Domestic - Product | G48: Gross Revenue (FPA1/022) | H48: 1. Umsatzerlöse > Mieterlöse (analog 820xxx, nicht in [Z]) | J48: =IF(COUNTIF('YCOA-Konten'!$A$5:$A$708,C48)>0,"belegt",IF(COUNTIF($C$6:$C$90,C48)>1,"doppelt","frei")) -> frei | K48: Bei Vertrags- und Leasingmanagement Kontenfindung auf dieses Konto umstellen (Standard: 70700000). Nicht in [Z] (bei FDG 2025/2024 ohne Saldo): Bedarf vor der Anlage bestätigen.
A49: 824970 | B49: Mieterlöse Konzerngesellschaften | C49: =$C$3&A49 -> 41824970 | D49: Mieterlöse Konzerngesellschaften | E49: 41001500 | F49: Revenue Affiliate - Product | G49: Gross Revenue (FPA1/022) | H49: 1. Umsatzerlöse > Mieterlöse (analog 820xxx, nicht in [Z]) | J49: =IF(COUNTIF('YCOA-Konten'!$A$5:$A$708,C49)>0,"belegt",IF(COUNTIF($C$6:$C$90,C49)>1,"doppelt","frei")) -> frei | K49: Erlöse mit verbundenen Unternehmen: Partnergesellschaft mitführen. Bei Vertrags- und Leasingmanagement Kontenfindung auf dieses Konto umstellen (Standard: 70700000). Nicht in [Z] (bei FDG 2025/2024 ohne Saldo): Bedarf vor der Anlage bestätigen.
A50: 830100 | B50: Umsatzabgabe Werbung innen | C50: =$C$3&A50 -> 41830100 | D50: Umsatzabgabe Werbung innen | E50: 41000000 | F50: Erlöse Inland - Erzeugnis / Revenue Domestic - Product | G50: Gross Revenue (FPA1/022) | H50: 1. Umsatzerlöse > Pachterlöse, Umsatz- und Konzessionsabgaben | I50: -2065554.1 | J50: =IF(COUNTIF('YCOA-Konten'!$A$5:$A$708,C50)>0,"belegt",IF(COUNTIF($C$6:$C$90,C50)>1,"doppelt","frei")) -> frei
A51: 830102 | B51: Umsatzabgabe Werbung Sonstiges | C51: =$C$3&A51 -> 41830102 | D51: Umsatzabgabe Werbung Sonstiges | E51: 41000000 | F51: Erlöse Inland - Erzeugnis / Revenue Domestic - Product | G51: Gross Revenue (FPA1/022) | H51: 1. Umsatzerlöse > Pachterlöse, Umsatz- und Konzessionsabgaben | I51: 182000 | J51: =IF(COUNTIF('YCOA-Konten'!$A$5:$A$708,C51)>0,"belegt",IF(COUNTIF($C$6:$C$90,C51)>1,"doppelt","frei")) -> frei
A52: 830130 | B52: Umsatzabgabe Verkaufsgeschäfte | C52: =$C$3&A52 -> 41830130 | D52: Umsatzabgabe Verkaufsgeschäfte | E52: 41000000 | F52: Erlöse Inland - Erzeugnis / Revenue Domestic - Product | G52: Gross Revenue (FPA1/022) | H52: 1. Umsatzerlöse > Pachterlöse, Umsatz- und Konzessionsabgaben | I52: -4472968.4 | J52: =IF(COUNTIF('YCOA-Konten'!$A$5:$A$708,C52)>0,"belegt",IF(COUNTIF($C$6:$C$90,C52)>1,"doppelt","frei")) -> frei
A53: 830131 | B53: Umsatzabgabe Gastronomie | C53: =$C$3&A53 -> 41830131 | D53: Umsatzabgabe Gastronomie | E53: 41000000 | F53: Erlöse Inland - Erzeugnis / Revenue Domestic - Product | G53: Gross Revenue (FPA1/022) | H53: 1. Umsatzerlöse > Pachterlöse, Umsatz- und Konzessionsabgaben | I53: -14365150 | J53: =IF(COUNTIF('YCOA-Konten'!$A$5:$A$708,C53)>0,"belegt",IF(COUNTIF($C$6:$C$90,C53)>1,"doppelt","frei")) -> frei
A54: 830133 | B54: Umsatzabgabe Reisemarkt | C54: =$C$3&A54 -> 41830133 | D54: Umsatzabgabe Reisemarkt | E54: 41000000 | F54: Erlöse Inland - Erzeugnis / Revenue Domestic - Product | G54: Gross Revenue (FPA1/022) | H54: 1. Umsatzerlöse > Pachterlöse, Umsatz- und Konzessionsabgaben | I54: -126765.94 | J54: =IF(COUNTIF('YCOA-Konten'!$A$5:$A$708,C54)>0,"belegt",IF(COUNTIF($C$6:$C$90,C54)>1,"doppelt","frei")) -> frei
A55: 830134 | B55: Umsatzabgabe DFS/TrValue | C55: =$C$3&A55 -> 41830134 | D55: Umsatzabgabe DFS/TrValue | E55: 41000000 | F55: Erlöse Inland - Erzeugnis / Revenue Domestic - Product | G55: Gross Revenue (FPA1/022) | H55: 1. Umsatzerlöse > Pachterlöse, Umsatz- und Konzessionsabgaben | I55: -11229479 | J55: =IF(COUNTIF('YCOA-Konten'!$A$5:$A$708,C55)>0,"belegt",IF(COUNTIF($C$6:$C$90,C55)>1,"doppelt","frei")) -> frei
A56: 830159 | B56: Umsatzabgabe Sonstiges CO | C56: =$C$3&A56 -> 41830159 | D56: Umsatzabgabe Sonstiges CO | E56: 41000000 | F56: Erlöse Inland - Erzeugnis / Revenue Domestic - Product | G56: Gross Revenue (FPA1/022) | H56: 1. Umsatzerlöse > Pachterlöse, Umsatz- und Konzessionsabgaben | I56: -1259159 | J56: =IF(COUNTIF('YCOA-Konten'!$A$5:$A$708,C56)>0,"belegt",IF(COUNTIF($C$6:$C$90,C56)>1,"doppelt","frei")) -> frei
A57: 830161 | B57: Umsatzabgabe Autovermieter | C57: =$C$3&A57 -> 41830161 | D57: Umsatzabgabe Autovermieter | E57: 41000000 | F57: Erlöse Inland - Erzeugnis / Revenue Domestic - Product | G57: Gross Revenue (FPA1/022) | H57: 1. Umsatzerlöse > Pachterlöse, Umsatz- und Konzessionsabgaben | I57: -8129154.2 | J57: =IF(COUNTIF('YCOA-Konten'!$A$5:$A$708,C57)>0,"belegt",IF(COUNTIF($C$6:$C$90,C57)>1,"doppelt","frei")) -> frei
A58: 830164 | B58: Umsatzabgabe Vermietung | C58: =$C$3&A58 -> 41830164 | D58: Umsatzabgabe Vermietung | E58: 41000000 | F58: Erlöse Inland - Erzeugnis / Revenue Domestic - Product | G58: Gross Revenue (FPA1/022) | H58: 1. Umsatzerlöse > Pachterlöse, Umsatz- und Konzessionsabgaben | I58: -424290.38 | J58: =IF(COUNTIF('YCOA-Konten'!$A$5:$A$708,C58)>0,"belegt",IF(COUNTIF($C$6:$C$90,C58)>1,"doppelt","frei")) -> frei
A59: 830166 | B59: Umsatzabgabe Hotel | C59: =$C$3&A59 -> 41830166 | D59: Umsatzabgabe Hotel | E59: 41000000 | F59: Erlöse Inland - Erzeugnis / Revenue Domestic - Product | G59: Gross Revenue (FPA1/022) | H59: 1. Umsatzerlöse > Pachterlöse, Umsatz- und Konzessionsabgaben | I59: -2501361.6 | J59: =IF(COUNTIF('YCOA-Konten'!$A$5:$A$708,C59)>0,"belegt",IF(COUNTIF($C$6:$C$90,C59)>1,"doppelt","frei")) -> frei
A60: 830167 | B60: Umsatzabgabe Telekommunikation | C60: =$C$3&A60 -> 41830167 | D60: Umsatzabgabe Telekommunikation | E60: 41000000 | F60: Erlöse Inland - Erzeugnis / Revenue Domestic - Product | G60: Gross Revenue (FPA1/022) | H60: 1. Umsatzerlöse > Pachterlöse, Umsatz- und Konzessionsabgaben | I60: -3988.72 | J60: =IF(COUNTIF('YCOA-Konten'!$A$5:$A$708,C60)>0,"belegt",IF(COUNTIF($C$6:$C$90,C60)>1,"doppelt","frei")) -> frei
A61: 830189 | B61: Umsatzabgabe Sonstiges IM | C61: =$C$3&A61 -> 41830189 | D61: Umsatzabgabe Sonstiges IM | E61: 41000000 | F61: Erlöse Inland - Erzeugnis / Revenue Domestic - Product | G61: Gross Revenue (FPA1/022) | H61: 1. Umsatzerlöse > Pachterlöse, Umsatz- und Konzessionsabgaben | I61: -286689.31 | J61: =IF(COUNTIF('YCOA-Konten'!$A$5:$A$708,C61)>0,"belegt",IF(COUNTIF($C$6:$C$90,C61)>1,"doppelt","frei")) -> frei
... A72: 840102 | B72: Erlöse aus Strom Messkosten | C72: =$C$3&A72 -> 41840102 | D72: Erlöse aus Strom Messkosten | E72: 41000000 | F72: Erlöse Inland - Erzeugnis / Revenue Domestic - Product | G72: Gross Revenue (FPA1/022) | H72: 1. Umsatzerlöse > Erlöse aus Nebenkosten- und Versorgungsleistungen | I72: -37139.5 | J72: =IF(COUNTIF('YCOA-Konten'!$A$5:$A$708,C72)>0,"belegt",IF(COUNTIF($C$6:$C$90,C72)>1,"doppelt","frei")) -> frei
A73: 840200 | B73: Mietnebenkosten Strom | C73: =$C$3&A73 -> 41840200 | D73: Mietnebenkosten Strom | E73: 41000000 | F73: Erlöse Inland - Erzeugnis / Revenue Domestic - Product | G73: Gross Revenue (FPA1/022) | H73: 1. Umsatzerlöse > Erlöse aus Nebenkosten- und Versorgungsleistungen | I73: -4633935.3 | J73: =IF(COUNTIF('YCOA-Konten'!$A$5:$A$708,C73)>0,"belegt",IF(COUNTIF($C$6:$C$90,C73)>1,"doppelt","frei")) -> frei | K73: Bei Vertrags- und Leasingmanagement Kontenfindung auf dieses Konto umstellen (Standard: 70800100).
A74: 840201 | B74: Mietnebenkosten Heizung | C74: =$C$3&A74 -> 41840201 | D74: Mietnebenkosten Heizung | E74: 41000000 | F74: Erlöse Inland - Erzeugnis / Revenue Domestic - Product | G74: Gross Revenue (FPA1/022) | H74: 1. Umsatzerlöse > Erlöse aus Nebenkosten- und Versorgungsleistungen | I74: -1575117.1 | J74: =IF(COUNTIF('YCOA-Konten'!$A$5:$A$708,C74)>0,"belegt",IF(COUNTIF($C$6:$C$90,C74)>1,"doppelt","frei")) -> frei | K74: Bei Vertrags- und Leasingmanagement Kontenfindung auf dieses Konto umstellen (Standard: 70800100).
A75: 840202 | B75: Mietnebenkosten Klima | C75: =$C$3&A75 -> 41840202 | D75: Mietnebenkosten Klima | E75: 41000000 | F75: Erlöse Inland - Erzeugnis / Revenue Domestic - Product | G75: Gross Revenue (FPA1/022) | H75: 1. Umsatzerlöse > Erlöse aus Nebenkosten- und Versorgungsleistungen | I75: -2774344.1 | J75: =IF(COUNTIF('YCOA-Konten'!$A$5:$A$708,C75)>0,"belegt",IF(COUNTIF($C$6:$C$90,C75)>1,"doppelt","frei")) -> frei | K75: Bei Vertrags- und Leasingmanagement Kontenfindung auf dieses Konto umstellen (Standard: 70800100).
A76: 840203 | B76: Mietnebenkosten Lüftung | C76: =$C$3&A76 -> 41840203 | D76: Mietnebenkosten Lüftung | E76: 41000000 | F76: Erlöse Inland - Erzeugnis / Revenue Domestic - Product | G76: Gross Revenue (FPA1/022) | H76: 1. Umsatzerlöse > Erlöse aus Nebenkosten- und Versorgungsleistungen | I76: -351577.52 | J76: =IF(COUNTIF('YCOA-Konten'!$A$5:$A$708,C76)>0,"belegt",IF(COUNTIF($C$6:$C$90,C76)>1,"doppelt","frei")) -> frei | K76: Bei Vertrags- und Leasingmanagement Kontenfindung auf dieses Konto umstellen (Standard: 70800100).
A77: 840204 | B77: Mietnebenkosten Wasser /Abwasser kalt | C77: =$C$3&A77 -> 41840204 | D77: Mietnebenkosten Wasser /Abwasser kalt | E77: 41000000 | F77: Erlöse Inland - Erzeugnis / Revenue Domestic - Product | G77: Gross Revenue (FPA1/022) | H77: 1. Umsatzerlöse > Erlöse aus Nebenkosten- und Versorgungsleistungen | I77: -262753.28 | J77: =IF(COUNTIF('YCOA-Konten'!$A$5:$A$708,C77)>0,"belegt",IF(COUNTIF($C$6:$C$90,C77)>1,"doppelt","frei")) -> frei | K77: Bei Vertrags- und Leasingmanagement Kontenfindung auf dieses Konto umstellen (Standard: 70800100).
A78: 840205 | B78: Mietnebenkosten Wasser /Abwasser warm | C78: =$C$3&A78 -> 41840205 | D78: Mietnebenkosten Wasser /Abwasser warm | E78: 41000000 | F78: Erlöse Inland - Erzeugnis / Revenue Domestic - Product | G78: Gross Revenue (FPA1/022) | H78: 1. Umsatzerlöse > Erlöse aus Nebenkosten- und Versorgungsleistungen | I78: -65883.55 | J78: =IF(COUNTIF('YCOA-Konten'!$A$5:$A$708,C78)>0,"belegt",IF(COUNTIF($C$6:$C$90,C78)>1,"doppelt","frei")) -> frei | K78: Bei Vertrags- und Leasingmanagement Kontenfindung auf dieses Konto umstellen (Standard: 70800100).
A79: 840206 | B79: Mietnebenkosten Pauschalen | C79: =$C$3&A79 -> 41840206 | D79: Mietnebenkosten Pauschalen | E79: 41000000 | F79: Erlöse Inland - Erzeugnis / Revenue Domestic - Product | G79: Gross Revenue (FPA1/022) | H79: 1. Umsatzerlöse > Erlöse aus Nebenkosten- und Versorgungsleistungen | I79: -2121405.6 | J79: =IF(COUNTIF('YCOA-Konten'!$A$5:$A$708,C79)>0,"belegt",IF(COUNTIF($C$6:$C$90,C79)>1,"doppelt","frei")) -> frei | K79: Bei Vertrags- und Leasingmanagement Kontenfindung auf dieses Konto umstellen (Standard: 70800100).
A80: 841000 | B80: Erlöse aus Wärmeenergie | C80: =$C$3&A80 -> 41841000 | D80: Erlöse aus Wärmeenergie | E80: 41000000 | F80: Erlöse Inland - Erzeugnis / Revenue Domestic - Product | G80: Gross Revenue (FPA1/022) | H80: 1. Umsatzerlöse > Erlöse aus Nebenkosten- und Versorgungsleistungen | I80: -229916.07 | J80: =IF(COUNTIF('YCOA-Konten'!$A$5:$A$708,C80)>0,"belegt",IF(COUNTIF($C$6:$C$90,C80)>1,"doppelt","frei")) -> frei
A81: 841300 | B81: Erlöse aus Kälteerzeugung/Klimatisierung | C81: =$C$3&A81 -> 41841300 | D81: Erlöse aus Kälteerzeugung/Klimatisierung | E81: 41000000 | F81: Erlöse Inland - Erzeugnis / Revenue Domestic - Product | G81: Gross Revenue (FPA1/022) | H81: 1. Umsatzerlöse > Erlöse aus Nebenkosten- und Versorgungsleistungen (analog 841000, nicht in [Z]) | J81: =IF(COUNTIF('YCOA-Konten'!$A$5:$A$708,C81)>0,"belegt",IF(COUNTIF($C$6:$C$90,C81)>1,"doppelt","frei")) -> frei | K81: Nicht in [Z] (bei FDG 2025/2024 ohne Saldo): Bedarf vor der Anlage bestätigen.
A82: 841400 | B82: Erlöse aus Verteilung Wärme+Kälte / Klimatisierung | C82: =$C$3&A82 -> 41841400 | D82: Erlöse aus Verteilung Wärme+Kälte / Klimatisierung | E82: 41000000 | F82: Erlöse Inland - Erzeugnis / Revenue Domestic - Product | G82: Gross Revenue (FPA1/022) | H82: 1. Umsatzerlöse > Erlöse aus Nebenkosten- und Versorgungsleistungen (analog 841000, nicht in [Z]) | J82: =IF(COUNTIF('YCOA-Konten'!$A$5:$A$708,C82)>0,"belegt",IF(COUNTIF($C$6:$C$90,C82)>1,"doppelt","frei")) -> frei | K82: Nicht in [Z] (bei FDG 2025/2024 ohne Saldo): Bedarf vor der Anlage bestätigen.
A83: 846000 | B83: Erlöse aus Versorg.Leist. VIDEO/FLUGINFO/ELA-ANL. | C83: =$C$3&A83 -> 41846000 | D83: Erlöse aus Versorg.Leist. VIDEO/FLUGINFO/ELA-ANL. | E83: 41000000 | F83: Erlöse Inland - Erzeugnis / Revenue Domestic - Product | G83: Gross Revenue (FPA1/022) | H83: 1. Umsatzerlöse > Erlöse aus Nebenkosten- und Versorgungsleistungen | I83: -295980.72 | J83: =IF(COUNTIF('YCOA-Konten'!$A$5:$A$708,C83)>0,"belegt",IF(COUNTIF($C$6:$C$90,C83)>1,"doppelt","frei")) -> frei
A84: 860000 | B84: Erlöse aus Ersatzverkehr SkyTrain | C84: =$C$3&A84 -> 41860000 | D84: Erlöse aus Ersatzverkehr SkyTrain | E84: 41000000 | F84: Erlöse Inland - Erzeugnis / Revenue Domestic - Product | G84: Gross Revenue (FPA1/022) | H84: 1. Umsatzerlöse > Sonstige Erlöse (analog 863440, nicht in [Z]) | J84: =IF(COUNTIF('YCOA-Konten'!$A$5:$A$708,C84)>0,"belegt",IF(COUNTIF($C$6:$C$90,C84)>1,"doppelt","frei")) -> frei | K84: Nicht in [Z] (bei FDG 2025/2024 ohne Saldo): Bedarf vor der Anlage bestätigen.
A85: 863000 | B85: Erlöse aus Leistungen Werkstätten | C85: =$C$3&A85 -> 41863000 | D85: Erlöse aus Leistungen Werkstätten | E85: 41000000 | F85: Erlöse Inland - Erzeugnis / Revenue Domestic - Product | G85: Gross Revenue (FPA1/022) | H85: 1. Umsatzerlöse > Sonstige Erlöse | I85: -3973830.6 | J85: =IF(COUNTIF('YCOA-Konten'!$A$5:$A$708,C85)>0,"belegt",IF(COUNTIF($C$6:$C$90,C85)>1,"doppelt","frei")) -> frei
A86: 863100 | B86: Erlöse aus Weiterberechnung | C86: =$C$3&A86 -> 41863100 | D86: Erlöse aus Weiterberechnung | E86: 41000000 | F86: Erlöse Inland - Erzeugnis / Revenue Domestic - Product | G86: Gross Revenue (FPA1/022) | H86: 1. Umsatzerlöse > Sonstige Erlöse | I86: -2075744.1 | J86: =IF(COUNTIF('YCOA-Konten'!$A$5:$A$708,C86)>0,"belegt",IF(COUNTIF($C$6:$C$90,C86)>1,"doppelt","frei")) -> frei | K86: Abstimmung mit den Weiterberechnungskonten 529xxx.
A87: 863310 | B87: Erlöse aus Kofferkuli | C87: =$C$3&A87 -> 41863310 | D87: Erlöse aus Kofferkuli | E87: 41000000 | F87: Erlöse Inland - Erzeugnis / Revenue Domestic - Product | G87: Gross Revenue (FPA1/022) | H87: 1. Umsatzerlöse > Sonstige Erlöse | I87: -860291.76 | J87: =IF(COUNTIF('YCOA-Konten'!$A$5:$A$708,C87)>0,"belegt",IF(COUNTIF($C$6:$C$90,C87)>1,"doppelt","frei")) -> frei
A88: 863331 | B88: Cute-Erlöse | C88: =$C$3&A88 -> 41863331 | D88: Cute-Erlöse | E88: 41000000 | F88: Erlöse Inland - Erzeugnis / Revenue Domestic - Product | G88: Gross Revenue (FPA1/022) | H88: 1. Umsatzerlöse > Sonstige Erlöse | I88: -3049048.7 | J88: =IF(COUNTIF('YCOA-Konten'!$A$5:$A$708,C88)>0,"belegt",IF(COUNTIF($C$6:$C$90,C88)>1,"doppelt","frei")) -> frei
A89: 863440 | B89: Erlöse Sky Train (VRR) | C89: =$C$3&A89 -> 41863440 | D89: Erlöse Sky Train (VRR) | E89: 41000000 | F89: Erlöse Inland - Erzeugnis / Revenue Domestic - Product | G89: Gross Revenue (FPA1/022) | H89: 1. Umsatzerlöse > Sonstige Erlöse | I89: -1364736.3 | J89: =IF(COUNTIF('YCOA-Konten'!$A$5:$A$708,C89)>0,"belegt",IF(COUNTIF($C$6:$C$90,C89)>1,"doppelt","frei")) -> frei
A90: 870000 | B90: Erträge aus aktivierten Eigenleistungen | C90: =$C$3&A90 -> 41870000 | D90: Erträge aus aktivierten Eigenleistungen | E90: 41090000 | F90: Sonstige betriebliche Erträge / Other Operating Revenue | G90: in FPA1 ohne Entsprechung; eigene GuV-Zeile 2 in der kundeneigenen Bilanzstruktur (ersatzweise Other Operating Revenue, FPA1/019) | H90: 2. Andere aktivierte Eigenleistungen | I90: -3219669.6 | J90: =IF(COUNTIF('YCOA-Konten'!$A$5:$A$708,C90)>0,"belegt",IF(COUNTIF($C$6:$C$90,C90)>1,"doppelt","frei")) -> frei | K90: Kein Umsatzerlös: eigene GuV-Zeile 2. Nummer außerhalb des Erlösblocks erwägen; Abrechnungslogik der Anlagen im Bau abstimmen.
B91: Anzahl neu anzulegender Konten / Summe Saldo 2025 | C91: =COUNTA(A6:A90) -> 85 | I91: =SUM(I6:I90) -> -4.7685788e+08

Sheet Positionszuordnung
A1: Zuordnung der Bilanz-/GuV-Positionen Kunde [Z] ↔ SAP-Standard [Y] (Bilanzstruktur FPA1)
A2: Grundlage der Bilanzprüfung: ein YCOA-Konto gilt als positionsgleich, wenn seine FPA1-Position zu den hier genannten SAP-Positionen der Kundenposition gehört. Die Strukturen sind unterschiedlich gegliedert (HGB-Gliederung beim Kunden, kostenartenorientierte Standardstruktur in SAP); die Zuordnung erfolgt sinngemäß. Weil die SAP-Positionen gröber sind als die Zeilen der Kundenbilanz/-GuV, gilt zusätzlich: ein YCOA-Konto nimmt nur Kundenkonten derselben Bilanz-/GuV-Zeile auf (siehe Blatt Hinweise).
A4: Bereich | B4: Position Kunde [Z] (Code) | C4: Position Kunde [Z] (Bezeichnung) | D4: Position(en) SAP-Standard [Y] (FPA1) | E4: Art der Zuordnung | F4: Hinweis | G4: Anzahl Kundenkonten
A5: Aktiva | B5: 1031011 | C5: A. Anlagevermögen > I. Immaterielle VG > 1. Konzessionen, Schutzrechte, Lizenzen (Software und sonstige immaterielle WG) | D5: Intangible Assets (FPA1/063); Accumulated Amortization (FPA1/064) | E5: 1:n (verteilt) | F5: Der Nettoausweis des Kunden entspricht Intangible Assets zuzüglich Accumulated Amortization (kumulierte Abschreibungen gesondert). | G5: =COUNTIF(Mapping!$E$2:$E$601,"*["&B5&"*") -> 1
A6: Aktiva | B6: 1031031 | C6: A. Anlagevermögen > I. Immaterielle VG > 2. Geleistete Anzahlungen | D6: Intangible Assets (FPA1/063) | E6: n:1 (zusammengefasst) | F6: In Intangible Assets gibt es kein Anzahlungskonto (Konto 050090: Neuanlage prüfen). | G6: =COUNTIF(Mapping!$E$2:$E$601,"*["&B6&"*") -> 1
A7: Aktiva | B7: 1032011 | C7: A. Anlagevermögen > II. Sachanlagen > 1. Grundstücke und Bauten > a) Flughafenbauten inkl. Grundstücke | D7: Property Plant & Equipment (Gross) (FPA1/052); Accumulated Depreciation (FPA1/062) | E7: 1:n (verteilt) | F7: Der Nettoausweis des Kunden entspricht Property Plant & Equipment (Net): Bestandskonten in Property Plant & Equipment (Gross), kumulierte Abschreibungen gesondert in Accumulated Depreciation. Die Unterpositionen des Kunden kennt der SAP-Standard nicht. | G7: =COUNTIF(Mapping!$E$2:$E$601,"*["&B7&"*") -> 1
A8: Aktiva | B8: 1032012 | C8: A. Anlagevermögen > II. Sachanlagen > 1. Grundstücke und Bauten > b) Grundstücke mit Wohnbauten | D8: Property Plant & Equipment (Gross) (FPA1/052); Accumulated Depreciation (FPA1/062) | E8: 1:n (verteilt) | F8: Der Nettoausweis des Kunden entspricht Property Plant & Equipment (Net): Bestandskonten in Property Plant & Equipment (Gross), kumulierte Abschreibungen gesondert in Accumulated Depreciation. Die Unterpositionen des Kunden kennt der SAP-Standard nicht. | G8: =COUNTIF(Mapping!$E$2:$E$601,"*["&B8&"*") -> 1
A9: Aktiva | B9: 1032013 | C9: A. Anlagevermögen > II. Sachanlagen > 1. Grundstücke und Bauten > c) Grundstücke ohne Bauten | D9: Property Plant & Equipment (Gross) (FPA1/052); Accumulated Depreciation (FPA1/062) | E9: 1:n (verteilt) | F9: Der Nettoausweis des Kunden entspricht Property Plant & Equipment (Net): Bestandskonten in Property Plant & Equipment (Gross), kumulierte Abschreibungen gesondert in Accumulated Depreciation. Die Unterpositionen des Kunden kennt der SAP-Standard nicht. | G9: =COUNTIF(Mapping!$E$2:$E$601,"*["&B9&"*") -> 1
A10: Aktiva | B10: 1032014 | C10: A. Anlagevermögen > II. Sachanlagen > 1. Grundstücke und Bauten > d) Erbbaurechte | D10: Property Plant & Equipment (Gross) (FPA1/052); Accumulated Depreciation (FPA1/062) | E10: 1:n (verteilt) | F10: Der Nettoausweis des Kunden entspricht Property Plant & Equipment (Net): Bestandskonten in Property Plant & Equipment (Gross), kumulierte Abschreibungen gesondert in Accumulated Depreciation. Die Unterpositionen des Kunden kennt der SAP-Standard nicht. | G10: =COUNTIF(Mapping!$E$2:$E$601,"*["&B10&"*") -> 1
A11: Aktiva | B11: 1032021 | C11: A. Anlagevermögen > II. Sachanlagen > 2. Technische Anlagen und Maschinen > a) Flughafenanlagen | D11: Property Plant & Equipment (Gross) (FPA1/052); Accumulated Depreciation (FPA1/062) | E11: 1:n (verteilt) | F11: Der Nettoausweis des Kunden entspricht Property Plant & Equipment (Net): Bestandskonten in Property Plant & Equipment (Gross), kumulierte Abschreibungen gesondert in Accumulated Depreciation. Die Unterpositionen des Kunden kennt der SAP-Standard nicht. | G11: =COUNTIF(Mapping!$E$2:$E$601,"*["&B11&"*") -> 1
A12: Aktiva | B12: 1032022 | C12: A. Anlagevermögen > II. Sachanlagen > 2. Technische Anlagen und Maschinen > b) Betriebsanlagen | D12: Property Plant & Equipment (Gross) (FPA1/052); Accumulated Depreciation (FPA1/062) | E12: 1:n (verteilt) | F12: Der Nettoausweis des Kunden entspricht Property Plant & Equipment (Net): Bestandskonten in Property Plant & Equipment (Gross), kumulierte Abschreibungen gesondert in Accumulated Depreciation. Die Unterpositionen des Kunden kennt der SAP-Standard nicht. | G12: =COUNTIF(Mapping!$E$2:$E$601,"*["&B12&"*") -> 1
A13: Aktiva | B13: 1032031 | C13: A. Anlagevermögen > II. Sachanlagen > 3. Andere Anlagen, Betriebs- und Geschäftsausstattung | D13: Property Plant & Equipment (Gross) (FPA1/052); Accumulated Depreciation (FPA1/062) | E13: 1:n (verteilt) | F13: Der Nettoausweis des Kunden entspricht Property Plant & Equipment (Net): Bestandskonten in Property Plant & Equipment (Gross), kumulierte Abschreibungen gesondert in Accumulated Depreciation. Die Unterpositionen des Kunden kennt der SAP-Standard nicht. | G13: =COUNTIF(Mapping!$E$2:$E$601,"*["&B13&"*") -> 1
A14: Aktiva | B14: 1032041 | C14: A. Anlagevermögen > II. Sachanlagen > 4. Geleistete Anzahlungen und Anlagen im Bau | D14: Property Plant & Equipment (Gross) (FPA1/052); Accumulated Depreciation (FPA1/062) | E14: 1:n (verteilt) | F14: Anlagen im Bau und geleistete Anzahlungen auf Sachanlagen liegen im SAP-Standard in Property Plant & Equipment (Gross); Wertberichtigungen in Accumulated Depreciation. | G14: =COUNTIF(Mapping!$E$2:$E$601,"*["&B14&"*") -> 1
A15: Aktiva | B15: 1033010 | C15: A. Anlagevermögen > III. Finanzanlagen > 1. Anteile an verbundenen Unternehmen | D15: Long-Term Investments (FPA1/065) | E15: n:1 (zusammengefasst) | F15: Der SAP-Standard führt alle Finanzanlagen in einer Position; die HGB-Untergliederung bleibt nur über getrennte Konten erhalten. | G15: =COUNTIF(Mapping!$E$2:$E$601,"*["&B15&"*") -> 4
A16: Aktiva | B16: 1033030/00 | C16: A. Anlagevermögen > III. Finanzanlagen > 2. Beteiligungen | D16: Long-Term Investments (FPA1/065) | E16: n:1 (zusammengefasst) | F16: Der SAP-Standard führt alle Finanzanlagen in einer Position; die HGB-Untergliederung bleibt nur über getrennte Konten erhalten. | G16: =COUNTIF(Mapping!$E$2:$E$601,"*["&B16&"*") -> 3
... A113: Außerhalb GuV | B113: 9020000 | C113: Verrechnung kalkulatorische Kosten (Saldo null) | D113: Not assigned (FPA1/00NOTASSGND) | E113: 1:1 | F113: Kalkulatorische Konten stehen beim Kunden außerhalb der GuV (Saldo null) und im SAP-Standard außerhalb der Bilanzstruktur (Not assigned). | G113: =COUNTIF(Mapping!$E$2:$E$601,"*["&B113&"*") -> 28
F114: Summe (Konten mit zwei Positionen zählen doppelt) | G114: =SUM(G5:G113) -> 536

Sheet Sammelkonten
A1: Neue YCOA-Zielkonten und Anzahl der zugeordneten Kundenkonten (n:1)
A2: Anzahl als Formel auf das Blatt Mapping (Spalte Neues YCOA-Konto); enthält auch vorläufige Vorschläge der Fälle mit Status manuell klären. Jedes Zielkonto bedient genau eine Bilanz-/GuV-Zeile des Kunden (letzte Spalte).
A4: YCOA-Konto | B4: Bezeichnung | C4: Bilanzposition [Y] | D4: Anzahl Kundenkonten | E4: Hinweis zur verlorenen Differenzierung | F4: Bilanz-/GuV-Zeile Kunde (aus in [Z] validierten Zuordnungen)
A5: 24090000 | B5: Sonstige Rückstellungen / Other Provisions | C5: Liabilities and Equity > Liabilities > Non-Current Liabilities > Provisions | D5: =COUNTIF(Mapping!$I$2:$I$601,A5) -> 29 | E5: Rückstellungsarten nicht mehr trennbar (Rückstellungsspiegel) – eigene Konten je wesentlicher Rückstellungsart prüfen. | F5: Passiva D.3 Sonstige Rückstellungen
A6: 13100000 | B6: Inventory - Raw Material | C6: Assets > Current Assets > Inventories | D6: =COUNTIF(Mapping!$I$2:$I$601,A6) -> 21 | E6: Werkstatt/Materialart nicht mehr auf Kontenebene; auswertbar über Bewertungsklasse, Warengruppe oder Lagerort. | F6: Aktiva B.I.1 Roh-, Hilfs- und Betriebsstoffe
A7: 51100000 | B7: Verbrauch - Rohstoff / Consumption - Raw Material | C7: Net Income > Operating Income > Operating Expense > Material Expense | D7: =COUNTIF(Mapping!$I$2:$I$601,A7) -> 20 | E7: Werkstatt/Materialart nicht mehr auf Kontenebene; auswertbar über Kostenstelle, Warengruppe oder Bewertungsklasse. | F7: GuV 4a Roh-, Hilfs- und Betriebsstoffe
A8: 11001000 | B8: Hauptbankkonto (Bar/B) / Main Bank Account (Cash/B) | C8: Assets > Current Assets > Cash & Equivalents | D8: =COUNTIF(Mapping!$I$2:$I$601,A8) -> 19 | E8: Kein Informationsverlust: Bankabstimmkonto, einzelne Bankkonten über Hausbank/Konto-ID. | F8: Aktiva B.III Flüssige Mittel
A9: 65001000 | B9: Bezogene Dienstleistungen / Purchased Services | C9: Net Income > Operating Income > Operating Expense > Employee Expense > Third Party Expense | D9: =COUNTIF(Mapping!$I$2:$I$601,A9) -> 18 | E9: Bezogene Leistungen des Materialaufwands (GuV 4b): Leistungsarten (Instandhaltung, Reinigung, Bodenverkehrsdienste, Sicherheit) nicht mehr trennbar – für wesentliche Leistungsarten eigene Konten prüfen. | F9: GuV 4b Bezogene Leistungen
A10: 66000000 | B10: Other Operating Expenses | C10: Net Income > Operating Income > Operating Expense > Other Operating Expense | D10: =COUNTIF(Mapping!$I$2:$I$601,A10) -> 18 | E10: Sammelkonto sonstige betriebliche Aufwendungen – eigene Konten prüfen, soweit für Anhang, Steuer oder Abstimmung erforderlich (z. B. Weiterberechnungen, periodenfremd, Säumniszuschläge). | F10: GuV 7 Sonstige betriebliche Aufwendungen
A11: 65008300 | B11: Services - General | C11: Net Income > Operating Income > Operating Expense > Employee Expense > Third Party Expense | D11: =COUNTIF(Mapping!$I$2:$I$601,A11) -> 15 | E11: Bezogene Dienstleistungen der sonstigen betrieblichen Aufwendungen (GuV 7), darunter IT-Leistungen SITA mit rund 21 Mio. EUR – eigene Konten prüfen; das Konto dient im Standard der Buchung von Dienstleistungsprodukten. | F11: GuV 7 Sonstige betriebliche Aufwendungen
A12: 71100000 | B12: Zinsaufwendungen / Interest Expense | C12: Net Income > Interest > Interest Expense | D12: =COUNTIF(Mapping!$I$2:$I$601,A12) -> 15 | E12: Zinsaufwand nach Darlehensart nicht mehr trennbar; Gesellschafterzinsen und Auf-/Abzinsung sind gesondert relevant. | F12: GuV 13 Zinsen und ähnliche Aufwendungen
A13: 64050000 | B13: Estimated Depreciation (CO) | C13: Not assigned (in FPA1 keiner Position zugeordnet) | D13: =COUNTIF(Mapping!$I$2:$I$601,A13) -> 12 | E13: Kalkulatorische Abschreibung nach Anlagengruppe nicht mehr trennbar (Entgeltkalkulation); über Anlagenklasse auswertbar. | F13: Kalkulatorische Kosten (außerhalb GuV)
A14: 21720000 | B14: Other Payables (no recon acct) | C14: Liabilities and Equity > Liabilities > Current Liabilities > Other Payable | D14: =COUNTIF(Mapping!$I$2:$I$601,A14) -> 11 | E14: Sammelkonto sonstige Verbindlichkeiten (Kautionen, Airlines, Fundsachen, Verrechnungskonten) – eigene Konten prüfen. | F14: Passiva E.7 Sonstige Verbindlichkeiten
A15: 41090000 | B15: Sonstige betriebliche Erträge / Other Operating Revenue | C15: Net Income > Operating Income > Other Operating Revenue | D15: =COUNTIF(Mapping!$I$2:$I$601,A15) -> 11 | E15: Sammelkonto sonstige betriebliche Erträge – periodenfremde Erträge und steuerlich relevante Sachverhalte gesondert prüfen. | F15: GuV 3 Sonstige betriebliche Erträge
A16: 64060000 | B16: Kalkulatorische Zinsen (CO) / Accrued interest (CO) | C16: Not assigned (in FPA1 keiner Position zugeordnet) | D16: =COUNTIF(Mapping!$I$2:$I$601,A16) -> 11 | E16: Kalkulatorische Zinsen nach Anlagengruppe nicht mehr trennbar (Entgeltkalkulation); über Anlagenklasse auswertbar. | F16: Kalkulatorische Kosten (außerhalb GuV)
... A37: 65300000 | B37: Rechts- und Beratungskosten / Legal and Audit Services | C37: Net Income > Operating Income > Operating Expense > Employee Expense > Office Expense | D37: =COUNTIF(Mapping!$I$2:$I$601,A37) -> 4 | E37: Prüfungs-, Beratungs- und Rechtskosten nicht getrennt (Abschlussprüferhonorar § 285 Nr. 17 HGB). | F37: GuV 7 Sonstige betriebliche Aufwendungen
A38: 12541000 | B38: Receivables from Tax Authorities (no recon acct) | C38: Assets > Current Assets > Other Current Assets | D38: =COUNTIF(Mapping!$I$2:$I$601,A38) -> 3 | F38: Aktiva B.II.4 Sonstige Vermögensgegenstände
A39: 16000000 | B39: Grundstücke und grundstücksgleiche Rechte / Land & Land Improvements | C39: Assets > Non-Current Assets > Property Plant & Equipment (Net) > Property Plant & Equipment (Gross) | D39: =COUNTIF(Mapping!$I$2:$I$601,A39) -> 3 | E39: Grundstücke und Erbbaurechte nicht mehr auf Kontenebene getrennt; über Anlagenklasse auswertbar. | F39: Aktiva A.II.1 Grundstücke und Bauten
A40: 21303000 | B40: Payables vs affiliated Companies (no recon acct) | C40: Liabilities and Equity > Liabilities > Current Liabilities > Other Payable | D40: =COUNTIF(Mapping!$I$2:$I$601,A40) -> 3 | E40: Spiegelkonten der Tochtergesellschaften gegenüber FDG (nicht in [Z]); Sollsalden über 12303000. | F40: – (nur Konten ohne [Z] bzw. vorläufig)
A41: 21725000 | B41: RechungsabgrenzPosten – Lieferungen und Leistungen / Accrued Expenses–Goods & Services | C41: Liabilities and Equity > Liabilities > Non-Current Liabilities > Provisions | D41: =COUNTIF(Mapping!$I$2:$I$601,A41) -> 3 | E41: Ausstehende Rechnungen Anlagevermögen und Schätzkosten nicht mehr getrennt. | F41: Passiva D.3 Sonstige Rückstellungen
A42: 24098600 | B42: Other Reserves | C42: Liabilities and Equity > Equity > Equity - Reserve Accounts | D42: =COUNTIF(Mapping!$I$2:$I$601,A42) -> 3 | E42: Zweckbestimmung der Rücklagen (Ausschüttungssperre) nicht mehr trennbar. | F42: Passiva A.III Gewinnrücklagen
A43: 61100000 | B43: Gehälter / Payroll Expense - Salaries | C43: Net Income > Operating Income > Operating Expense > Employee Expense > Payroll and Benefits > Payroll Salary & Wages | D43: =COUNTIF(Mapping!$I$2:$I$601,A43) -> 3 | E43: Stammstellen, Aushilfen und Auszubildende nicht mehr auf Kontenebene; über Personalabrechnung auswertbar. | F43: GuV 5a Löhne und Gehälter
A44: 63005000 | B44: Office/Building Rent | C44: Net Income > Operating Income > Operating Expense > Building Expense > Periodic Building Expense | D44: =COUNTIF(Mapping!$I$2:$I$601,A44) -> 3 | E44: Mieten und Pachten des Materialaufwands (GuV 4b): Geländepacht und Gebäudemiete nicht mehr trennbar – eigenes Pachtkonto prüfen. | F44: GuV 4b Bezogene Leistungen
A45: 65100000 | B45: Büromaterial / Office Supplies | C45: Net Income > Operating Income > Operating Expense > Employee Expense > Office Expense | D45: =COUNTIF(Mapping!$I$2:$I$601,A45) -> 3 | F45: GuV 7 Sonstige betriebliche Aufwendungen
A46: 71010700 | B46: Estimated depreciation (FI-AA) | C46: Not assigned (in FPA1 keiner Position zugeordnet) | D46: =COUNTIF(Mapping!$I$2:$I$601,A46) -> 3 | E46: Gegenkonten der kalkulatorischen Abschreibung; Rolle von 780609/780611 klären. | F46: Kalkulatorische Kosten (außerhalb GuV)
A47: 12100000 | B47: Receivables Domestic | C47: Assets > Current Assets > Accounts Receivable | D47: =COUNTIF(Mapping!$I$2:$I$601,A47) -> 2 | F47: Aktiva B.II.1 Forderungen aus L&L
A48: 12542000 | B48: Receivables from Employees Overpay (no recon acct) | C48: Assets > Current Assets > Accounts Receivable | D48: =COUNTIF(Mapping!$I$2:$I$601,A48) -> 2 | F48: Aktiva B.II.4 Sonstige Vermögensgegenstände
A49: 12562000 | B49: Deferred Income | C49: Liabilities and Equity > Liabilities > Current Liabilities > Other Payable | D49: =COUNTIF(Mapping!$I$2:$I$601,A49) -> 2 | F49: Passiva F. Rechnungsabgrenzungsposten
A50: 16001000 | B50: Gebäude / Buildings | C50: Assets > Non-Current Assets > Property Plant & Equipment (Net) > Property Plant & Equipment (Gross) | D50: =COUNTIF(Mapping!$I$2:$I$601,A50) -> 2 | E50: Flughafenbauten und Wohnbauten nicht mehr auf Kontenebene getrennt; über Anlagenklasse auswertbar. | F50: Aktiva A.II.1 Grundstücke und Bauten
A51: 16002000 | B51: Machinery & Equipment | C51: Assets > Non-Current Assets > Property Plant & Equipment (Net) > Property Plant & Equipment (Gross) | D51: =COUNTIF(Mapping!$I$2:$I$601,A51) -> 2 | E51: Flughafenanlagen und Betriebsanlagen nicht mehr auf Kontenebene getrennt; über Anlagenklasse auswertbar. | F51: Aktiva A.II.2 Technische Anlagen und Maschinen
A52: 21105000 | B52: Travel Expenses Payable | C52: Liabilities and Equity > Liabilities > Current Liabilities > Other Payable | D52: =COUNTIF(Mapping!$I$2:$I$601,A52) -> 2 | F52: – (nur Konten ohne [Z] bzw. vorläufig)
A53: 21538000 | B53: Sonstige Steuer - zu zahlen | C53: nicht in [Y] enthalten (Konto nur aus [X]) | D53: =COUNTIF(Mapping!$I$2:$I$601,A53) -> 2 | F53: – (nur Konten ohne [Z] bzw. vorläufig)
A54: 24031000 | B54: Rückst. für Pensionen und ähnliche Verpflichtungen / Pension Provision | C54: Liabilities and Equity > Liabilities > Non-Current Liabilities > Provisions | D54: =COUNTIF(Mapping!$I$2:$I$601,A54) -> 2 | E54: Versorgungszusagen und Beihilfe nicht mehr getrennt. | F54: Passiva D.1 Pensionsrückstellungen
A55: 41000000 | B55: Erlöse Inland - Erzeugnis / Revenue Domestic - Product | C55: Net Income > Operating Income > Gross Margin > Net Revenue > Gross Revenue | D55: =COUNTIF(Mapping!$I$2:$I$601,A55) -> 2 | E55: Allgemeines Erlöskonto für Verkäufe und sonstige Lieferungen und Leistungen; spezifische Erlösarten werden neu angelegt (Blatt Neuanlagen). | F55: GuV 1 Umsatzerlöse
A56: 44001000 | B56: Sales Rebates | C56: Net Income > Operating Income > Gross Margin > Net Revenue > Sales Deductions | D56: =COUNTIF(Mapping!$I$2:$I$601,A56) -> 2 | F56: GuV 1 Umsatzerlöse
A57: 52501000 | B57: Ertrag aus Inventurdifferenzen (Roh/Handel) / Gain Inventory Variance (Raw & Trade) | C57: Net Income > Operating Income > Other Operating Revenue | D57: =COUNTIF(Mapping!$I$2:$I$601,A57) -> 2 | F57: GuV 3 Sonstige betriebliche Erträge
A58: 61008000 | B58: Travel Expenses - Miscellaneous | C58: Net Income > Operating Income > Operating Expense > Employee Expense > Travel Expense | D58: =COUNTIF(Mapping!$I$2:$I$601,A58) -> 2 | F58: GuV 7 Sonstige betriebliche Aufwendungen
A59: 61061000 | B59: Arbeitgeberleistungen / Payroll - Benefits | C59: Net Income > Operating Income > Operating Expense > Employee Expense > Payroll and Benefits > Payroll Benefits | D59: =COUNTIF(Mapping!$I$2:$I$601,A59) -> 2 | F59: GuV 5b Soziale Abgaben, Altersversorgung, Unterstützung
A60: 61400000 | B60: Training and Education | C60: Net Income > Operating Income > Operating Expense > Employee Expense > Employee Expense Other | D60: =COUNTIF(Mapping!$I$2:$I$601,A60) -> 2 | F60: GuV 7 Sonstige betriebliche Aufwendungen
A61: 63008000 | B61: Gebäude - periodischer Service / Building Periodic Service | C61: Net Income > Operating Income > Operating Expense > Employee Expense > Office Expense | D61: =COUNTIF(Mapping!$I$2:$I$601,A61) -> 2 | E61: Gebäudereinigung und Gebäudereparaturen der sonstigen betrieblichen Aufwendungen. | F61: GuV 7 Sonstige betriebliche Aufwendungen
A62: 65200000 | B62: Sonstiges Material / Other Supplies | C62: Net Income > Operating Income > Operating Expense > Employee Expense > Office Expense | D62: =COUNTIF(Mapping!$I$2:$I$601,A62) -> 2 | F62: GuV 7 Sonstige betriebliche Aufwendungen
A63: 66000500 | B63: Erträge - Kürzung von Rückstellungen / Income - reduction in provisions | C63: Net Income > Operating Income > Other Operating Revenue | D63: =COUNTIF(Mapping!$I$2:$I$601,A63) -> 2 | F63: GuV 3 Sonstige betriebliche Erträge
A64: 70300100 | B64: Gain from Long Term Investment | C64: Net Income > Other Income and Expense > Non-Operating Income > Non-Operating Revenue | D64: =COUNTIF(Mapping!$I$2:$I$601,A64) -> 2 | F64: GuV 8 Erträge aus Beteiligungen
A65: 75002000 | B65: Aufwendungen für Körperschaftssteuer / Corporate Income Tax Expense | C65: Net Income > Taxes | D65: =COUNTIF(Mapping!$I$2:$I$601,A65) -> 2 | F65: GuV 14 Steuern vom Einkommen und Ertrag
A66: 75008000 | B66: Gewerbesteuer / Trade Tax | C66: Net Income > Taxes | D66: =COUNTIF(Mapping!$I$2:$I$601,A66) -> 2 | F66: GuV 14 Steuern vom Einkommen und Ertrag
A67: 75009900 | B67: Sonstige betriebliche Steuern / Other Company Taxes | C67: Net Income > Taxes | D67: =COUNTIF(Mapping!$I$2:$I$601,A67) -> 2 | F67: GuV 16 Sonstige Steuern
A68: 11001030 | B68: Sonstige Zwischenbuchungen (Bar/Unterkonto) / Other Interim Transfers (Cash/S) | C68: Assets > Current Assets > Cash & Equivalents | D68: =COUNTIF(Mapping!$I$2:$I$601,A68) -> 1 | E68: 1:1-Zuordnung | F68: – (nur Konten ohne [Z] bzw. vorläufig)
A69: 12102000 | B69: Receivables Domestic Adjustments | C69: Assets > Current Assets > Accounts Receivable | D69: =COUNTIF(Mapping!$I$2:$I$601,A69) -> 1 | E69: 1:1-Zuordnung | F69: Aktiva B.II.1 Forderungen aus L&L
A70: 12401000 | B70: Einzelwertberichtigungen zu Forderungen / Individual Value Adjustments for Receivables | C70: Assets > Current Assets > Accounts Receivable | D70: =COUNTIF(Mapping!$I$2:$I$601,A70) -> 1 | E70: 1:1-Zuordnung | F70: Aktiva B.II.1 Forderungen aus L&L
A71: 12401100 | B71: Allowance for Doubtful Receivables(Valuation) | C71: Assets > Current Assets > Accounts Receivable | D71: =COUNTIF(Mapping!$I$2:$I$601,A71) -> 1 | E71: 1:1-Zuordnung | F71: Aktiva B.II.1 Forderungen aus L&L
A72: 12550000 | B72: Unbilled Revenue | C72: Assets > Current Assets > Other Current Assets | D72: =COUNTIF(Mapping!$I$2:$I$601,A72) -> 1 | E72: 1:1-Zuordnung | F72: – (nur Konten ohne [Z] bzw. vorläufig)
A73: 12561000 | B73: Aktive Rechnungsabgrenzung / Prepaid Expenses | C73: Assets > Current Assets > Other Current Assets | D73: =COUNTIF(Mapping!$I$2:$I$601,A73) -> 1 | E73: 1:1-Zuordnung | F73: Aktiva C. Rechnungsabgrenzungsposten
A74: 13100900 | B74: Inventory - Revaluation Raw Material | C74: Assets > Current Assets > Inventories | D74: =COUNTIF(Mapping!$I$2:$I$601,A74) -> 1 | E74: 1:1-Zuordnung | F74: Aktiva B.I.1 Roh-, Hilfs- und Betriebsstoffe
A75: 14107000 | B75: Mitarbeiterdarlehen / Loans to Staff | C75: Assets > Non-Current Assets > Other Non-Current Assets > Long-Term Investments | D75: =COUNTIF(Mapping!$I$2:$I$601,A75) -> 1 | E75: 1:1-Zuordnung | F75: Aktiva A.III.4 Sonstige Ausleihungen
A76: 16005000 | B76: Betriebs- und Geschäftsausstattung / Office Equipment | C76: Assets > Non-Current Assets > Property Plant & Equipment (Net) > Property Plant & Equipment (Gross) | D76: =COUNTIF(Mapping!$I$2:$I$601,A76) -> 1 | E76: 1:1-Zuordnung | F76: Aktiva A.II.3 Betriebs- und Geschäftsausstattung
A77: 16009000 | B77: Anlagen im Bau / Assets under Construction | C77: Assets > Non-Current Assets > Property Plant & Equipment (Net) > Property Plant & Equipment (Gross) | D77: =COUNTIF(Mapping!$I$2:$I$601,A77) -> 1 | E77: 1:1-Zuordnung | F77: Aktiva A.II.4 Anzahlungen und Anlagen im Bau
A78: 19210000 | B78: Other Receivables > 1 year | C78: Assets > Current Assets > Notes Receivable | D78: =COUNTIF(Mapping!$I$2:$I$601,A78) -> 1 | E78: 1:1-Zuordnung | F78: Aktiva B.II.4 Sonstige Vermögensgegenstände
A79: 19320000 | B79: Intangible Assets | C79: Assets > Non-Current Assets > Other Non-Current Assets > Intangible Assets | D79: =COUNTIF(Mapping!$I$2:$I$601,A79) -> 1 | E79: Software kann je Anlagenklasse auf 16008000 geführt werden. | F79: Aktiva A.I.1 Immaterielle VG
... A139: 75007000 | B139: Grundsteuer / Property Taxes | C139: Net Income > Taxes | D139: =COUNTIF(Mapping!$I$2:$I$601,A139) -> 1 | E139: 1:1-Zuordnung | F139: GuV 16 Sonstige Steuern
C140: Summe zugeordneter Kundenkonten | D140: =SUM(D5:D139) -> 469

Sheet Hinweise
A1: Hinweise: Quellen, Vorgehen, Wertebereiche, Annahmen
A3: Quellen
A4: [X] Bisheriges Mapping | B4: DUS_YCOA_MappingOutcomeV3.xlsx, Blatt Mapping_Neu: 600 Kundenkonten mit bisherigem YCOA-Konto (417 MAPPED, 183 TBD). Reihenfolge der Zeilen im Blatt Mapping wie in [X].
A5: [Y] SAP-Standardbilanz | B5: 20261002-065925_2CCFIFINSTMTCMP.xlsx: Bilanz/GuV-Struktur FPA1 (SAP Best Practices Financial Stmt for FP&A), Buchungskreis 10DU, inkl. Konten ohne Saldo: 684 YCOA-Konten in 76 Strukturknoten, davon ein großer Block Not assigned (in FPA1 keiner Position zugeordnet). Kontonummer = Stellen 7–14 des Schlüssels YCOA00xxxxxxxx0A.
A6: [Z] Bilanz/GuV des Kunden | B6: 1000 FDG Bilanz und GuV 2025 15.01.2026 mit Verkn..xlsx, Blatt SAP-Auszug: 533 Kundenkonten mit Bilanz- oder GuV-Position; 67 Konten aus [X] fehlen dort. Da [Z] und [Y] auch die GuV enthalten, wurde die Positionsprüfung auf GuV-Konten ausgedehnt.
A7: Vorgehen je Kundenkonto
A8: 1. Bezeichnungsprüfung | B8: Vergleich Kundenkonto ↔ bisheriges YCOA-Konto nach Kontoart, Sachverhalt, Fristigkeit und Steuerbezug. Spalte G: OK / Abweichung; kein Mapping (TBD), wenn [X] kein Zielkonto enthielt.
A9: 2. Bilanzprüfung | B9: Nur für Konten in [Z]: Position des Kundenkontos aus [Z], Position des YCOA-Kontos aus [Y]; positionsgleich ist ein YCOA-Konto, wenn seine FPA1-Position laut Blatt Positionszuordnung zur Kundenposition gehört. Spalte H: OK / Abweichung; Abweichung auch dann, wenn das bisherige Zielkonto in [Y] fehlt oder Not assigned ist (Ausnahmen: kalkulatorische Konten, siehe unten, und die per Entscheidung in der kundeneigenen Bilanzstruktur zugeordneten Standardkonten 21120000, 70020000, 70030000, 71010200). kein Mapping (TBD), wenn kein Zielkonto vorlag.
A10: 3. Konten ohne Eintrag in [Z] | B10: Spalte E: nicht in [Z] enthalten – nicht bilanziell validiert; Spalte H: nicht prüfbar; Begründung beginnt mit Nicht bilanziell validiert. Zuordnung nur nach Bezeichnung und analog zu gleichartigen, validierten Konten.
A11: 4. Ein YCOA-Konto je Kundenzeile | B11: Die SAP-Positionen in [Y] sind gröber als die Zeilen der Kundenbilanz/-GuV (z. B. liegen bezogene Leistungen des Materialaufwands und Fremdleistungen der sonstigen betrieblichen Aufwendungen beide in Third Party Expense). Damit Bilanz und GuV des Kunden aus den YCOA-Konten ableitbar bleiben, nimmt jedes neue Zielkonto nur Kundenkonten derselben Bilanz-/GuV-Zeile auf (Gliederungsebene der Blätter Bilanz und G+V in [Z]; programmatisch geprüft, Übersicht im Blatt Sammelkonten). Ein bisheriges Zielkonto, das nach dieser Regel einer anderen Kundenzeile gehört, gilt in Spalte H als Abweichung. Ausnahmen: saldierte Positionen verbundener Unternehmen und saldoabhängige Verrechnungskonten; Unterpositionen a) bis d) der Sachanlagen bleiben über die Anlagenklasse auswertbar.
A12: Status
A13: unverändert | B13: Bisheriges Zielkonto besteht beide Prüfungen (bzw. die Bezeichnungsprüfung bei Konten ohne [Z]) und wird bestätigt.
A14: korrigiert | B14: Neues Zielkonto aus [Y], das fachlich passt und – bei Konten in [Z] – in der entsprechenden SAP-Position liegt und nur eine Kundenzeile bedient (beides programmatisch für alle Zeilen geprüft). Umfasst auch bisherige TBD-Fälle, die jetzt zugeordnet sind.
A15: Neuanlage | B15: Entscheidung des Auftraggebers vom 02.10.2026: das Konto wird neu angelegt (85 Erlöskonten der Klasse 8). Die Spalten Neues YCOA-Konto und Bezeichnung neues YCOA zeigen per Formel den Vorschlag aus dem Blatt Neuanlagen; diese Konten existieren in YCOA noch nicht. Status außerhalb der ursprünglichen Werteliste, weil der Fall nicht mehr offen ist.
A16: Neuanlage prüfen | B16: Kein vorhandenes YCOA-Konto erfüllt beide Kriterien: entweder bildet kein Konto den Sachverhalt ab, oder es gibt nur ein generisches Sammelkonto, mit dem eine in der Kundenbilanz/-GuV eigens gegliederte oder gesetzlich gesondert auszuweisende Position verloren ginge. Kein Kontovorschlag; die Begründung nennt Kopiervorlage und Rückfalloption.
A17: manuell klären | B17: Sachverhalt unklar oder Entscheidung zum Ausweis nötig: fachlich passendes Konto liegt in [Y] in anderer oder keiner Position, Konto ist saldoabhängig, 1:n-Aufteilung oder Inhalt nicht erkennbar. Ein vorläufiges Konto ist nur eingetragen, wo eines benennbar ist; es erfüllt die Positionsregel nicht in jedem Fall.
A18: Konfidenz | B18: Sicherheit der Aussage der Zeile (bei Neuanlage prüfen: Sicherheit, dass kein passendes Konto existiert). niedrig wird nur zusammen mit manuell klären vergeben.
A19: Entscheidungen des Auftraggebers vom 02.10.2026
A20: 1. Erlöskonten | B20: Erlöskonten neu anlegen. Die 85 Konten der Klasse 8 ohne passendes YCOA-Konto (84 Umsatzerlöskonten und 870000 aktivierte Eigenleistungen) erhalten den Status Neuanlage. Das Blatt Neuanlagen enthält je Konto den Vorschlag für Nummer, Bezeichnung, Kopiervorlage und Position.
A21: 2. Standardkonten ohne FPA1-Position | B21: In der kundeneigenen Bilanzstruktur zuordnen. 21120000 (WE/RE) wird den Verbindlichkeiten aus L&L zugeordnet, 70020000/70030000 (Anlagenabgang) und 71010200 (Zuschreibungen) den sonstigen betrieblichen Erträgen. Die vier Kundenkonten 300009, 867000, 867001 und 202110 sind damit nicht mehr offen (zwei korrigiert, zwei unverändert).
A22: 3. Zusatzregel ein YCOA-Konto je Kundenzeile | B22: Vorerst beibehalten. Keine Änderung: 65001000 bleibt den bezogenen Leistungen (GuV 4b) vorbehalten, Fremdleistungen der sonstigen betrieblichen Aufwendungen (GuV 7) laufen auf 65008300; entsprechend 63005000/63009000.
A23: Annahmen und Einschränkungen
A24: Verwendete YCOA-Konten | B24: Zielkonten mit Status unverändert und korrigiert stammen ausschließlich aus [Y]. Einzige Ausnahme bei den vorläufigen Vorschlägen: 21538000 Sonstige Steuer - zu zahlen (nur in [X]) bei 157300 und 174020, gekennzeichnet mit manuell klären. Für vorhandene Konten wurden keine Kontonummern erfunden.
A25: Nummern der Neuanlagen | B25: Die Kontonummern im Blatt Neuanlagen sind Vorschläge für noch anzulegende Konten: Präfix (Eingabezelle, Vorschlag 41) + sechsstelliges Kundenkonto. Sie sind gegen alle Konten aus [Y] und [X] geprüft (Blatt YCOA-Konten). [Y] zeigt nur den Buchungskreis 10DU; vor der Anlage ist im System gegen den gesamten Kontenplan YCOA zu prüfen. Kopiervorlage, Position und Erlösgruppe sind Vorschläge; Kontengruppe, Steuerkategorie und Kurztext sind bei der Anlage festzulegen.
A26: Kontenbezeichnungen | B26: Bezeichnung bisheriges YCOA wie in [X] (deutsch). Bezeichnung neues YCOA: deutscher Text aus [X], soweit dort vorhanden, sonst bzw. zusätzlich der englische Text aus [Y].
A27: Abweichung [X] ↔ [Y] | B27: 20 in [X] verwendete YCOA-Konten fehlen in [Y] (12010000, 14102000, 19110000, 21460000, 21501100, 21501200, 21512000, 21538000, 21539106, 21540000, 21700000, 22006011, 22006012, 24098200, 41090010, 41090011, 44007000, 61022020, 64000000, 75004010). 12110000 ist in [X] als Forderungen Inland bezeichnet, laut [Y] aber Other Down Payments Made Current Assets.
A28: Anlagevermögen | B28: Der Kunde führt Anschaffungskosten und kumulierte Abschreibung auf einem Konto (Nettoausweis). In YCOA sind Bestands- und Wertberichtigungskonten getrennt und je Anlagenklasse differenziert; die Anlagenkonten sind daher ihrer Natur nach 1:n-Zuordnungen. Die Zeilen nennen das führende Bestandskonto, die Aufteilung (Wertberichtigung, weitere Anlagenklassen) erfolgt über die Kontenfindung der Anlagenbuchhaltung. Für die Abschreibungen auf Sachanlagen (220009) gibt es kein führendes Konto, daher manuell klären.
A29: Saldierter Ausweis | B29: Forderungen und Verbindlichkeiten gegenüber verbundenen Unternehmen saldiert der Kunde je Gesellschaft; einzelne Verrechnungskonten wechseln saldoabhängig die Bilanzseite (157300, 195024, 195500). Die Positionszuordnung lässt hierfür beide Seiten zu. Verrechnungskonten der FDG mit verbundenen Unternehmen (Verrechnung, Cash-Pooling, Ergebnisabführung) sind unabhängig vom aktuellen Saldo einheitlich 12303000 zugeordnet, die Spiegelkonten der Tochtergesellschaften 21303000; Salden der jeweils anderen Seite werden umgegliedert.
A30: Kalkulatorische Konten | B30: Position 9020000 des Kunden (Verrechnung kalkulatorischer Kosten, Saldo null) wird der SAP-Position Not assigned gleichgestellt, weil kalkulatorische Konten in beiden Strukturen außerhalb der Bilanz/GuV stehen.
A31: Nicht geprüft | B31: Salden wurden nicht abgestimmt; die Prüfung beruht auf Bezeichnungen und Positionen. Kontenfindung, Steuerkennzeichen und Buchungskreis-Einstellungen der YCOA-Konten waren nicht Gegenstand. Hinweise auf HGB- und Steuervorschriften dienen der Einordnung der verlorenen Differenzierung und ersetzen keine fachliche Abstimmung mit Kunde und Abschlussprüfer.

Sheet YCOA-Konten
A1: YCOA-Konten laut [Y] (Buchungskreis 10DU, Bilanzstruktur FPA1) und zusätzlich nur in [X] genannte Konten
A2: Referenzliste und Grundlage der Nummernprüfung im Blatt Neuanlagen. Quelle [Y]: Konto im Buchungskreis 10DU vorhanden; nur [X]: im bisherigen Mapping verwendet, in [Y] nicht vorhanden.
A4: YCOA-Konto | B4: Bezeichnung (englisch, aus [Y]) | C4: Bezeichnung (deutsch, aus [X], soweit dort verwendet) | D4: Position FPA1 | E4: Quelle
A5: 00700080 | B5: GMV Miete (WACC) | D5: Not assigned | E5: [Y]
A6: 00700511 | B6: GMV Stellplätze | D6: Not assigned | E6: [Y]
A7: 10010000 | B7: Petty Cash | D7: Assets > Current Assets > Cash & Equivalents | E7: [Y]
A8: 10020000 | B8: Petty Cash Journal - postings automatic only | D8: Assets > Current Assets > Cash & Equivalents | E8: [Y]
A9: 11001000 | B9: Main Bank Account (Cash/B) | C9: Hauptbankkonto (Bar/B) | D9: Assets > Current Assets > Cash & Equivalents | E9: [Y]
A10: 11001010 | B10: Cash Payment (Cash/S) | D10: Assets > Current Assets > Cash & Equivalents | E10: [Y]
A11: 11001020 | B11: Bank Transfer (Domestic/SEPA/Foreign) (Cash/S) | D11: Assets > Current Assets > Cash & Equivalents | E11: [Y]
A12: 11001030 | B12: Other Interim Transfers (Cash/S) | C12: Sonstige Zwischenbuchungen (Bar/Unterkonto) | D12: Assets > Current Assets > Cash & Equivalents | E12: [Y]
A13: 11001040 | B13: Direct Debit (C/S) | D13: Assets > Current Assets > Cash & Equivalents | E13: [Y]
A14: 11001045 | B14: Returns (Cash/S) | D14: Assets > Current Assets > Cash & Equivalents | E14: [Y]
A15: 11001050 | B15: Checks Out (C/S) | D15: Assets > Current Assets > Cash & Equivalents | E15: [Y]
A16: 11001060 | B16: Checks In (C/S) | D16: Assets > Current Assets > Cash & Equivalents | E16: [Y]
A17: 11001070 | B17: Check Clearing Account (Cash/S) | D17: Assets > Current Assets > Cash & Equivalents | E17: [Y]
A18: 11001080 | B18: Cash Receipt (C/S) | D18: Assets > Current Assets > Cash & Equivalents | E18: [Y]
A19: 11001090 | B19: Technical Account for Bank Statement (Cash/S) | D19: Assets > Current Assets > Cash & Equivalents | E19: [Y]
A20: 11008000 | B20: Digital Payments Acquirer Bank (Cash/B) | D20: Assets > Current Assets > Cash & Equivalents | E20: [Y]
A21: 11008030 | B21: Digital Payments Transfer Account (Cash/S) | D21: Assets > Current Assets > Cash & Equivalents | E21: [Y]
A22: 11008050 | B22: DP Acquirer Clrng (Stlmnt) (Cash/S) pending | D22: Not assigned | E22: [Y]
A23: 11008070 | B23: Digital Payments Acquirer Clrng (Stlmnt) (Cash/S) | D23: Assets > Current Assets > Cash & Equivalents | E23: [Y]
A24: 12010000 | C24: Kurzfristige Investitionen | D24: nicht in [Y] enthalten | E24: nur [X]
A25: 12021000 | B25: Short Term Investments, Unaffiliated(TRM) | D25: Not assigned | E25: [Y]
A26: 12021100 | B26: Short Term Investments, Affili., No Consolid.(TRM) | D26: Not assigned | E26: [Y]
A27: 12021200 | B27: Short Term Investments, Affiliated, Consolid.(TRM) | D27: Not assigned | E27: [Y]
A28: 12041000 | B28: Derivatives Valuation Balances, Unaffiliated(TRM) | D28: Not assigned | E28: [Y]
A29: 12041100 | B29: Derivatives Valuation Bal, Affil., No Consol.(TRM) | D29: Not assigned | E29: [Y]
A30: 12041200 | B30: Derivatives Valuation Bal, Affili., Consolid.(TRM) | D30: Not assigned | E30: [Y]
A31: 12042000 | B31: Derivatives Assets, Unaffiliated(TRM) | D31: Not assigned | E31: [Y]
A32: 12042100 | B32: Derivatives Assets, Affiliated, No Consolid.(TRM) | D32: Not assigned | E32: [Y]
A33: 12042200 | B33: Derivatives Assets, Affiliated, Consolidation(TRM) | D33: Not assigned | E33: [Y]
A34: 12100000 | B34: Receivables Domestic | D34: Assets > Current Assets > Accounts Receivable | E34: [Y]
A35: 12100100 | B35: Receivables Domestic - One Time Accounts | D35: Assets > Current Assets > Accounts Receivable | E35: [Y]
A36: 12101000 | B36: Receivables Domestic due > 1 Year | D36: Assets > Current Assets > Notes Receivable | E36: [Y]
A37: 12102000 | B37: Receivables Domestic Adjustments | D37: Assets > Current Assets > Accounts Receivable | E37: [Y]
A38: 12110000 | B38: Other Down Payments Made Current Assets | C38: (in [X] abweichend als Forderungen Inland bezeichnet) | D38: Assets > Current Assets > Inventories | E38: [Y]
A39: 12110100 | B39: Down Payments Made due > 1 Year | D39: Assets > Current Assets > Notes Receivable | E39: [Y]
A40: 12111000 | B40: Input Tax Clrg-other Down Pyts Made for Curr. Asts | D40: Assets > Current Assets > Accounts Receivable | E40: [Y]
A41: 12112000 | B41: Down Payments made for Inventory | D41: Assets > Current Assets > Inventories | E41: [Y]
A42: 12119000 | B42: Down Payment Requests Vendors | D42: Assets > Current Assets > Accounts Receivable | E42: [Y]
A43: 12119200 | B43: Adjustment Account Vendor Down Payments | D43: Assets > Current Assets > Accounts Receivable | E43: [Y]
A44: 12120000 | B44: Receivables Foreign | D44: Assets > Current Assets > Accounts Receivable | E44: [Y]
A45: 12120100 | B45: Receivables Foreign - One Time Accounts | D45: Assets > Current Assets > Accounts Receivable | E45: [Y]
A46: 12121000 | B46: Receivables Foreign due > 1 Year | D46: Assets > Current Assets > Notes Receivable | E46: [Y]
A47: 12122000 | B47: Receivables Foreign Adjustments | D47: Assets > Current Assets > Accounts Receivable | E47: [Y]
A48: 12300000 | B48: Receivables affiliated Companies | D48: Assets > Current Assets > Accounts Receivable | E48: [Y]
A49: 12301000 | B49: Receivables affiliated Companies > 1 Year | D49: Assets > Current Assets > Notes Receivable | E49: [Y]
A50: 12302000 | B50: Receivables affiliated Companies Adjustments | D50: Assets > Current Assets > Accounts Receivable | E50: [Y]
A51: 12303000 | B51: Receivables vs affil. Companies (no recon acct) | D51: Assets > Current Assets > Accounts Receivable | E51: [Y]
A52: 12400000 | B52: Allowance for Doubtful Receivables | C52: Zweifelhafte Forderungen | D52: Assets > Current Assets > Accounts Receivable | E52: [Y]
A53: 12401000 | B53: Individual Value Adjustments for Receivables | C53: Einzelwertberichtigungen zu Forderungen | D53: Assets > Current Assets > Accounts Receivable | E53: [Y]
A54: 12401100 | B54: Allowance for Doubtful Receivables(Valuation) | D54: Assets > Current Assets > Accounts Receivable | E54: [Y]
A55: 12402000 | B55: Depreciation Receivables from Aff.Companies | C55: Wertberichtigungen zu Forderungen gg. Verbundene | D55: Assets > Current Assets > Notes Receivable | E55: [Y]
A56: 12410000 | B56: Clearing of Guarantee Given (Customers) | D56: Not assigned | E56: [Y]
A57: 12411000 | B57: Guarantees given to Customers | D57: Not assigned | E57: [Y]
A58: 12420000 | B58: Security Deposit Customers | D58: Assets > Current Assets > Accounts Receivable | E58: [Y]
A59: 12500000 | B59: Interest Receivables | C59: Zins-Forderungen | D59: Assets > Current Assets > Accounts Receivable | E59: [Y]
A60: 12501000 | B60: Clearing Interest Receivables | D60: Assets > Current Assets > Accounts Receivable | E60: [Y]
A61: 12510000 | B61: Accounts Receivable - BoE Receivable | D61: Not assigned | E61: [Y]
A62: 12530000 | B62: Accounts Receivable - Payment Cards | C62: Forderungen aus Zahlungskarten | D62: Assets > Current Assets > Accounts Receivable | E62: [Y]
A63: 12540000 | B63: Other Receivables (no recon acct) | D63: Assets > Current Assets > Accounts Receivable | E63: [Y]
A64: 12540200 | B64: Other Receivables Adjustments | D64: Assets > Current Assets > Accounts Receivable | E64: [Y]
A65: 12541000 | B65: Receivables from Tax Authorities (no recon acct) | D65: Assets > Current Assets > Other Current Assets | E65: [Y]
A66: 12542000 | B66: Receivables from Employees Overpay (no recon acct) | D66: Assets > Current Assets > Accounts Receivable | E66: [Y]
A67: 12543000 | B67: Receivables from Partners (no recon acct) | D67: Assets > Current Assets > Accounts Receivable | E67: [Y]
A68: 12549000 | B68: Depreciation from other Receivables | D68: Assets > Current Assets > Accounts Receivable | E68: [Y]
A69: 12550000 | B69: Unbilled Revenue | D69: Assets > Current Assets > Other Current Assets | E69: [Y]
A70: 12561000 | B70: Prepaid Expenses | C70: Aktive Rechnungsabgrenzung | D70: Assets > Current Assets > Other Current Assets | E70: [Y]
A71: 12562000 | B71: Deferred Income | D71: Liabilities and Equity > Liabilities > Current Liabilities > Other Payable | E71: [Y]
A72: 12590000 | B72: Vendors with a Debit Balance | D72: Assets > Current Assets > Accounts Receivable | E72: [Y]
A73: 12600000 | B73: Input Tax (VST) | D73: Assets > Current Assets > Other Current Assets | E73: [Y]
A74: 12605000 | B74: Import Sales Tax paid (VST) | D74: Assets > Current Assets > Other Current Assets | E74: [Y]
A75: 12610000 | B75: Input Tax | D75: Assets > Current Assets > Other Current Assets | E75: [Y]
A76: 12660000 | B76: Reclaimable Tax for Interest Income(TRM) | D76: Not assigned | E76: [Y]
A77: 12701000 | B77: Accr. Interest Inc./Defer. Int. Exp., Unaffi.(TRM) | D77: Not assigned | E77: [Y]
A78: 12701100 | B78: Accr. Int. Inc./Defer. Int. Exp., Aff., NoCo.(TRM) | D78: Not assigned | E78: [Y]
A79: 12701200 | B79: Accr. Int. Inc./Defer. Int. Exp., Affi., Con.(TRM) | D79: Not assigned | E79: [Y]
A80: 13100000 | B80: Inventory - Raw Material | D80: Assets > Current Assets > Inventories | E80: [Y]
A81: 13100900 | B81: Inventory - Revaluation Raw Material | D81: Assets > Current Assets > Inventories | E81: [Y]
A82: 13200000 | B82: Inventory - Work In Progress | D82: Assets > Current Assets > Inventories | E82: [Y]
... A99: 13815600 | B99: Deferrals Revenue - On Account Adjustment | D99: Liabilities and Equity > Liabilities > Current Liabilities > Other Payable | E99: [Y]
A100: 14102000 | C100: Sonstige Darlehen - kurzfristig | D100: nicht in [Y] enthalten | E100: nur [X]
A101: 14107000 | B101: Loans to Staff | C101: Mitarbeiterdarlehen | D101: Assets > Non-Current Assets > Other Non-Current Assets > Long-Term Investments | E101: [Y]
A102: 15200000 | B102: Salary and Wages Advances | C102: Lohn- und Gehaltsvorschüsse | D102: Assets > Current Assets > Accounts Receivable | E102: [Y]
A103: 15300000 | B103: Trip Costs in Advance | D103: Assets > Current Assets > Accounts Receivable | E103: [Y]
A104: 16000000 | B104: Land & Land Improvements | C104: Grundstücke und grundstücksgleiche Rechte | D104: Assets > Non-Current Assets > Property Plant & Equipment (Net) > Property Plant & Equipment (Gross) | E104: [Y]
A105: 16001000 | B105: Buildings | C105: Gebäude | D105: Assets > Non-Current Assets > Property Plant & Equipment (Net) > Property Plant & Equipment (Gross) | E105: [Y]
A106: 16002000 | B106: Machinery & Equipment | D106: Assets > Non-Current Assets > Property Plant & Equipment (Net) > Property Plant & Equipment (Gross) | E106: [Y]
A107: 16003000 | B107: Building Improvements | D107: Assets > Non-Current Assets > Property Plant & Equipment (Net) > Property Plant & Equipment (Gross) | E107: [Y]
A108: 16004000 | B108: Motor Vehicles | D108: Assets > Non-Current Assets > Property Plant & Equipment (Net) > Property Plant & Equipment (Gross) | E108: [Y]
A109: 16005000 | B109: Office Equipment | C109: Betriebs- und Geschäftsausstattung | D109: Assets > Non-Current Assets > Property Plant & Equipment (Net) > Property Plant & Equipment (Gross) | E109: [Y]
A110: 16006000 | B110: Furniture and Fixtures | D110: Assets > Non-Current Assets > Property Plant & Equipment (Net) > Property Plant & Equipment (Gross) | E110: [Y]
A111: 16007000 | B111: Computer Hardware and Equipment | D111: Assets > Non-Current Assets > Property Plant & Equipment (Net) > Property Plant & Equipment (Gross) | E111: [Y]
A112: 16008000 | B112: Computer Software | D112: Assets > Non-Current Assets > Other Non-Current Assets > Intangible Assets | E112: [Y]
A113: 16009000 | B113: Assets under Construction | C113: Anlagen im Bau | D113: Assets > Non-Current Assets > Property Plant & Equipment (Net) > Property Plant & Equipment (Gross) | E113: [Y]
A114: 16010000 | B114: Down Payments made on Tangible Assets w/o FI-AA | D114: Assets > Non-Current Assets > Property Plant & Equipment (Net) > Property Plant & Equipment (Gross) | E114: [Y]
A115: 16010500 | B115: Input Tax Clearing Tangibles Down Payments made | D115: Assets > Non-Current Assets > Property Plant & Equipment (Net) > Property Plant & Equipment (Gross) | E115: [Y]
A116: 16012000 | B116: Capitalized Down Payments made on Fixed Assets | C116: Aktivierte Anzahlungen auf Anlagen | D116: Assets > Non-Current Assets > Property Plant & Equipment (Net) > Property Plant & Equipment (Gross) | E116: [Y]
A117: 16013000 | B117: Clearing capitalized Down Payments on Fixed Assets | D117: Assets > Non-Current Assets > Property Plant & Equipment (Net) > Property Plant & Equipment (Gross) | E117: [Y]
...
